Workbook

Sheet DATA MTD
B1: PASTE DISINI
B6: WITEL | C6: PRE PI | D6: REGISTERED (RE) | E6: INPROGRESS SC | F6: QC1 | G6: FCC | H6: CANCEL BY FCC | I6: SURVEY NEW MANJA | J6: UN-SC | K6: OGP | Y6: JML COMP (PS) | Z6: CANCEL | AD6: TOTAL CANCEL | AE6: REVOKE | AF6: PI/RE (%) | AG6: PS/RE (%) | AH6: PS/PI (%)
K7: PRE PI | L7: PI | O7: TOTAL PI | P7: FALLOUT | W7: TOTAL FALLOUT | X7: ACT COMP (QC2)
P8: WFM | T8: UIM | U8: ASP | V8: OSM
L9: < 1 HARI | M9: 1 - 3 HARI | N9: > 3 HARI | P9: KNDL PLGN | Q9: KNDL TEKNIS | R9: KNDL SYS | S9: OTHERS | Z9: KNDL PLGN | AA9: KNDL TEKNIS | AB9: KNDL SYS | AC9: OTHERS
B10: BALI | C10: 0 | D10: 19 | E10: 1 | F10: 2 | G10: 1 | H10: 0 | I10: 7 | J10: 0 | K10: 0 | L10: 2 | M10: 0 | N10: 0 | O10: 2 | P10: 0 | Q10: 0 | R10: 0 | S10: 0 | T10: 0 | U10: 0 | V10: 0 | W10: 0 | X10: 0 | Y10: 5 | Z10: 0 | AA10: 0 | AB10: 0 | AC10: 0 | AD10: 0 | AE10: 0 | AF10: 36.84 | AG10: 26.32 | AH10: 71.43
B11: JATIM BARAT | C11: 0 | D11: 30 | E11: 2 | F11: 2 | G11: 0 | H11: 0 | I11: 11 | J11: 1 | K11: 5 | L11: 1 | M11: 0 | N11: 0 | O11: 1 | P11: 0 | Q11: 0 | R11: 0 | S11: 0 | T11: 0 | U11: 0 | V11: 0 | W11: 0 | X11: 1 | Y11: 6 | Z11: 0 | AA11: 0 | AB11: 0 | AC11: 0 | AD11: 0 | AE11: 1 | AF11: 26.67 | AG11: 21.43 | AH11: 75.00
B12: JATIM TIMUR | C12: 0 | D12: 27 | E12: 2 | F12: 0 | G12: 1 | H12: 0 | I12: 9 | J12: 0 | K12: 1 | L12: 0 | M12: 0 | N12: 0 | O12: 0 | P12: 0 | Q12: 0 | R12: 0 | S12: 0 | T12: 0 | U12: 0 | V12: 0 | W12: 0 | X12: 0 | Y12: 7 | Z12: 0 | AA12: 0 | AB12: 0 | AC12: 0 | AD12: 0 | AE12: 0 | AF12: 25.93 | AG12: 25.93 | AH12: 100.00
B13: NUSA TENGGARA | C13: 0 | D13: 23 | E13: 0 | F13: 0 | G13: 1 | H13: 0 | I13: 16 | J13: 0 | K13: 0 | L13: 2 | M13: 0 | N13: 0 | O13: 2 | P13: 0 | Q13: 0 | R13: 0 | S13: 0 | T13: 0 | U13: 0 | V13: 0 | W13: 0 | X13: 1 | Y13: 2 | Z13: 0 | AA13: 0 | AB13: 0 | AC13: 0 | AD13: 0 | AE13: 0 | AF13: 21.74 | AG13: 8.70 | AH13: 40.00
B14: SEMARANG JATENG UTARA | C14: 0 | D14: 15 | E14: 4 | F14: 0 | G14: 0 | H14: 0 | I14: 9 | J14: 0 | K14: 0 | L14: 0 | M14: 0 | N14: 0 | O14: 0 | P14: 0 | Q14: 0 | R14: 0 | S14: 0 | T14: 0 | U14: 0 | V14: 0 | W14: 0 | X14: 0 | Y14: 2 | Z14: 0 | AA14: 0 | AB14: 0 | AC14: 0 | AD14: 0 | AE14: 0 | AF14: 13.33 | AG14: 13.33 | AH14: 100.00
B15: SOLO JATENG TIMUR | C15: 0 | D15: 15 | E15: 3 | F15: 3 | G15: 1 | H15: 0 | I15: 2 | J15: 0 | K15: 0 | L15: 3 | M15: 0 | N15: 0 | O15: 3 | P15: 0 | Q15: 0 | R15: 0 | S15: 0 | T15: 0 | U15: 0 | V15: 0 | W15: 0 | X15: 1 | Y15: 1 | Z15: 0 | AA15: 0 | AB15: 0 | AC15: 0 | AD15: 0 | AE15: 0 | AF15: 33.33 | AG15: 6.67 | AH15: 20.00
B16: SURAMADU | C16: 0 | D16: 31 | E16: 1 | F16: 0 | G16: 0 | H16: 0 | I16: 15 | J16: 1 | K16: 0 | L16: 2 | M16: 0 | N16: 0 | O16: 2 | P16: 0 | Q16: 0 | R16: 0 | S16: 1 | T16: 0 | U16: 0 | V16: 0 | W16: 1 | X16: 2 | Y16: 6 | Z16: 0 | AA16: 0 | AB16: 0 | AC16: 0 | AD16: 0 | AE16: 1 | AF16: 35.48 | AG16: 20.69 | AH16: 54.55
B17: YOGYA JATENG SELATAN | C17: 0 | D17: 27 | E17: 1 | F17: 2 | G17: 2 | H17: 0 | I17: 10 | J17: 0 | K17: 0 | L17: 2 | M17: 0 | N17: 0 | O17: 2 | P17: 0 | Q17: 0 | R17: 0 | S17: 0 | T17: 0 | U17: 0 | V17: 0 | W17: 0 | X17: 0 | Y17: 9 | Z17: 0 | AA17: 0 | AB17: 0 | AC17: 0 | AD17: 0 | AE17: 0 | AF17: 40.74 | AG17: 33.33 | AH17: 81.82
B18: TOTAL | C18: 0 | D18: 187 | E18: 14 | F18: 9 | G18: 6 | H18: 0 | I18: 79 | J18: 2 | K18: 6 | L18: 12 | M18: 0 | N18: 0 | O18: 12 | P18: 0 | Q18: 0 | R18: 0 | S18: 1 | T18: 0 | U18: 0 | V18: 0 | W18: 1 | X18: 5 | Y18: 38 | Z18: 0 | AA18: 0 | AB18: 0 | AC18: 0 | AD18: 0 | AE18: 2 | AF18: 29.95 | AG18: 20.77 | AH18: 67.86
B20: ="PROVISIONING INDIBIZ TR3 JBN HARIAN "&TEXT(TODAY(),"YYYY-MM-DD ")&TEXT(NOW(),"HH:MM")&" WIB" -> PROVISIONING INDIBIZ TR3 JBN HARIAN 2026-10-16 10:57 WIB
B21: Last update proses : 30-08-2024 15:48:52 WIB (Source: ETL XPRO)
B23: WITEL | C23: REGISTERED (RE) | D23: INPROGRESS SC+QC1+FCC | E23: CANCEL BY FCC | F23: SURVEY NEW MANJA | G23: UN-SC | H23: OGP | L23: TOTAL OGP | M23: JML COMP (PS) | N23: CANCEL | P23: TOTAL CANCEL | Q23: REVOKE
H24: PRE PI | I24: PI | J24: FALLOUT | K24: ACT COMP (QC2)
N26: KNDL PLGN | O26: KNDL NON PLGN
B27: BALI | C27: =D10 -> 19 | D27: =E10+F10+G10 -> 4 | E27: =H10 -> 0 | F27: =I10 -> 7 | G27: =J10 -> 0 | H27: =K10 -> 0 | I27: =O10 -> 2 | J27: =W10 -> 0 | K27: =X10 -> 0 | L27: =SUM(H27:K27) -> 2 | M27: =Y10 -> 5 | N27: =Z10 -> 0 | O27: =AD10-N27 -> 0 | P27: =SUM(N27:O27) -> 0 | Q27: =AE10 -> 0
B28: JATIM BARAT | C28: =D11 -> 30 | D28: =E11+F11+G11 -> 4 | E28: =H11 -> 0 | F28: =I11 -> 11 | G28: =J11 -> 1 | H28: =K11 -> 5 | I28: =O11 -> 1 | J28: =W11 -> 0 | K28: =X11 -> 1 | L28: =SUM(H28:K28) -> 7 | M28: =Y11 -> 6 | N28: =Z11 -> 0 | O28: =AD11-N28 -> 0 | P28: =SUM(N28:O28) -> 0 | Q28: =AE11 -> 1
B29: JATIM TIMUR | C29: =D12 -> 27 | D29: =E12+F12+G12 -> 3 | E29: =H12 -> 0 | F29: =I12 -> 9 | G29: =J12 -> 0 | H29: =K12 -> 1 | I29: =O12 -> 0 | J29: =W12 -> 0 | K29: =X12 -> 0 | L29: =SUM(H29:K29) -> 1 | M29: =Y12 -> 7 | N29: =Z12 -> 0 | O29: =AD12-N29 -> 0 | P29: =SUM(N29:O29) -> 0 | Q29: =AE12 -> 0
B30: NUSRA | C30: =D13 -> 23 | D30: =E13+F13+G13 -> 1 | E30: =H13 -> 0 | F30: =I13 -> 16 | G30: =J13 -> 0 | H30: =K13 -> 0 | I30: =O13 -> 2 | J30: =W13 -> 0 | K30: =X13 -> 1 | L30: =SUM(H30:K30) -> 3 | M30: =Y13 -> 2 | N30: =Z13 -> 0 | O30: =AD13-N30 -> 0 | P30: =SUM(N30:O30) -> 0 | Q30: =AE13 -> 0
B31: SURAMADU | C31: =D16 -> 31 | D31: =SUM(E16,F16,G16) -> 1 | E31: =H16 -> 0 | F31: =I16 -> 15 | G31: =J16 -> 1 | H31: =K16 -> 0 | I31: =O16 -> 2 | J31: =W16 -> 1 | K31: =X16 -> 2 | L31: =SUM(H31:K31) -> 5 | M31: =Y16 -> 6 | N31: =Z16 -> 0 | O31: =AD16-N31 -> 0 | P31: =SUM(N31:O31) -> 0 | Q31: =AE16 -> 1
B32: TOTAL | C32: =SUM(C27:C31) -> 130 | D32: =SUM(D27:D31) -> 13 | E32: =SUM(E27:E31) -> 0 | F32: =SUM(F27:F31) -> 58 | G32: =SUM(G27:G31) -> 2 | H32: =SUM(H27:H31) -> 6 | I32: =SUM(I27:I31) -> 7 | J32: =SUM(J27:J31) -> 1 | ... Q32: =SUM(Q27:Q31) -> 2
B34: Keterangan | C34: UIC
C35: Inputer, DIT, FCC
C36: Order Cancel & Revoke
C37: TA, BGESOPS, DAMAN, DIT
C38: Completed (PS)
B40: ="PROVISIONING INDIBIZ TR3 JBN BY TELDA MTD "&TEXT(TODAY(),"YYYY-MM-DD ")&TEXT(NOW(),"HH:MM")&" WIB" -> PROVISIONING INDIBIZ TR3 JBN BY TELDA MTD 2026-10-16 10:57 WIB
B41: Last update proses : 30-08-2024 13:48:46 WIB (Source: ETL XPRO)
B43: WITEL | C43: TELDA | D43: REGISTERED (RE) | E43: INPROGRESS SC+QC1+FCC | F43: CANCEL BY FCC | G43: SURVEY NEW MANJA | H43: UN-SC | I43: OGP | M43: TOTAL OGP | N43: JML COMP (PS) | O43: CANCEL | Q43: TOTAL CANCEL | R43: REVOKE
I44: PRE PI | J44: PI | K44: FALLOUT | L44: ACT COMP (QC2)
O46: KNDL PLGN | P46: KNDL NON PLGN
B47: BALI | C47: GIANYAR | D47: ='LOOKUP telda'!E7 -> 12 | E47: ='LOOKUP telda'!F7+'LOOKUP telda'!G7+'LOOKUP telda'!H7 -> 0 | F47: ='LOOKUP telda'!I7 -> 0 | G47: ='LOOKUP telda'!J7 -> 0 | H47: ='LOOKUP telda'!K7 -> 0 | I47: ='LOOKUP telda'!L7 -> 0 | J47: ='LOOKUP telda'!P7 -> 0 | K47: ='LOOKUP telda'!X7 -> 0 | L47: ='LOOKUP telda'!Y7 -> 0 | M47: =SUM('DATA MTD'!I47:L47) -> 0 | N47: ='LOOKUP telda'!Z7 -> 9 | O47: ='LOOKUP telda'!AA7 -> 0 | P47: ='LOOKUP telda'!AE7-'LOOKUP telda'!AA7 -> 0 | Q47: =SUM(O47:P47) -> 0 | R47: ='LOOKUP telda'!AF7 -> 3
C48: JEMBRANA | D48: ='LOOKUP telda'!E8 -> 1 | E48: ='LOOKUP telda'!F8+'LOOKUP telda'!G8+'LOOKUP telda'!H8 -> 0 | F48: ='LOOKUP telda'!I8 -> 0 | G48: ='LOOKUP telda'!J8 -> 0 | H48: ='LOOKUP telda'!K8 -> 0 | I48: ='LOOKUP telda'!L8 -> 0 | J48: ='LOOKUP telda'!P8 -> 0 | K48: ='LOOKUP telda'!X8 -> 0 | L48: ='LOOKUP telda'!Y8 -> 0 | M48: =SUM('DATA MTD'!I48:L48) -> 0 | N48: ='LOOKUP telda'!Z8 -> 1 | O48: ='LOOKUP telda'!AA8 -> 0 | P48: ='LOOKUP telda'!AE8-'LOOKUP telda'!AA8 -> 0 | Q48: =SUM(O48:P48) -> 0 | R48: ='LOOKUP telda'!AF8 -> 0
C49: JIMBARAN | D49: ='LOOKUP telda'!E9 -> 15 | E49: ='LOOKUP telda'!F9+'LOOKUP telda'!G9+'LOOKUP telda'!H9 -> 0 | F49: ='LOOKUP telda'!I9 -> 3 | G49: ='LOOKUP telda'!J9 -> 1 | H49: ='LOOKUP telda'!K9 -> 0 | I49: ='LOOKUP telda'!L9 -> 0 | J49: ='LOOKUP telda'!P9 -> 3 | K49: ='LOOKUP telda'!X9 -> 1 | L49: ='LOOKUP telda'!Y9 -> 0 | M49: =SUM('DATA MTD'!I49:L49) -> 4 | N49: ='LOOKUP telda'!Z9 -> 5 | O49: ='LOOKUP telda'!AA9 -> 0 | P49: ='LOOKUP telda'!AE9-'LOOKUP telda'!AA9 -> 0 | Q49: =SUM(O49:P49) -> 0 | R49: ='LOOKUP telda'!AF9 -> 2
C50: KLUNGKUNG | D50: ='LOOKUP telda'!E10 -> 11 | E50: ='LOOKUP telda'!F10+'LOOKUP telda'!G10+'LOOKUP telda'!H10 -> 0 | F50: ='LOOKUP telda'!I10 -> 1 | G50: ='LOOKUP telda'!J10 -> 2 | H50: ='LOOKUP telda'!K10 -> 0 | I50: ='LOOKUP telda'!L10 -> 0 | J50: ='LOOKUP telda'!P10 -> 1 | K50: ='LOOKUP telda'!X10 -> 0 | L50: ='LOOKUP telda'!Y10 -> 0 | M50: =SUM('DATA MTD'!I50:L50) -> 1 | N50: ='LOOKUP telda'!Z10 -> 6 | O50: ='LOOKUP telda'!AA10 -> 0 | P50: ='LOOKUP telda'!AE10-'LOOKUP telda'!AA10 -> 0 | Q50: =SUM(O50:P50) -> 0 | R50: ='LOOKUP telda'!AF10 -> 1
C51: SANUR | D51: ='LOOKUP telda'!E11 -> 14 | E51: ='LOOKUP telda'!F11+'LOOKUP telda'!G11+'LOOKUP telda'!H11 -> 0 | F51: ='LOOKUP telda'!I11 -> 1 | G51: ='LOOKUP telda'!J11 -> 1 | H51: ='LOOKUP telda'!K11 -> 0 | I51: ='LOOKUP telda'!L11 -> 0 | J51: ='LOOKUP telda'!P11 -> 0 | K51: ='LOOKUP telda'!X11 -> 0 | L51: ='LOOKUP telda'!Y11 -> 1 | M51: =SUM('DATA MTD'!I51:L51) -> 1 | N51: ='LOOKUP telda'!Z11 -> 10 | O51: ='LOOKUP telda'!AA11 -> 0 | P51: ='LOOKUP telda'!AE11-'LOOKUP telda'!AA11 -> 0 | Q51: =SUM(O51:P51) -> 0 | R51: ='LOOKUP telda'!AF11 -> 1
C52: SINGARAJA | D52: ='LOOKUP telda'!E12 -> 7 | E52: ='LOOKUP telda'!F12+'LOOKUP telda'!G12+'LOOKUP telda'!H12 -> 0 | F52: ='LOOKUP telda'!I12 -> 0 | G52: ='LOOKUP telda'!J12 -> 0 | H52: ='LOOKUP telda'!K12 -> 0 | I52: ='LOOKUP telda'!L12 -> 0 | J52: ='LOOKUP telda'!P12 -> 1 | K52: ='LOOKUP telda'!X12 -> 0 | L52: ='LOOKUP telda'!Y12 -> 0 | M52: =SUM('DATA MTD'!I52:L52) -> 1 | N52: ='LOOKUP telda'!Z12 -> 5 | O52: ='LOOKUP telda'!AA12 -> 0 | P52: ='LOOKUP telda'!AE12-'LOOKUP telda'!AA12 -> 0 | Q52: =SUM(O52:P52) -> 0 | R52: ='LOOKUP telda'!AF12 -> 1
C53: TABANAN | D53: ='LOOKUP telda'!E13 -> 48 | E53: ='LOOKUP telda'!F13+'LOOKUP telda'!G13+'LOOKUP telda'!H13 -> 1 | F53: ='LOOKUP telda'!I13 -> 2 | G53: ='LOOKUP telda'!J13 -> 1 | H53: ='LOOKUP telda'!K13 -> 10 | I53: ='LOOKUP telda'!L13 -> 0 | J53: ='LOOKUP telda'!P13 -> 3 | K53: ='LOOKUP telda'!X13 -> 2 | L53: ='LOOKUP telda'!Y13 -> 0 | M53: =SUM('DATA MTD'!I53:L53) -> 5 | N53: ='LOOKUP telda'!Z13 -> 15 | O53: ='LOOKUP telda'!AA13 -> 0 | P53: ='LOOKUP telda'!AE13-'LOOKUP telda'!AA13 -> 11 | Q53: =SUM(O53:P53) -> 11 | R53: ='LOOKUP telda'!AF13 -> 3
C54: UBUNG | D54: ='LOOKUP telda'!E14 -> 18 | E54: ='LOOKUP telda'!F14+'LOOKUP telda'!G14+'LOOKUP telda'!H14 -> 0 | F54: ='LOOKUP telda'!I14 -> 0 | G54: ='LOOKUP telda'!J14 -> 0 | H54: ='LOOKUP telda'!K14 -> 0 | I54: ='LOOKUP telda'!L14 -> 0 | J54: ='LOOKUP telda'!P14 -> 4 | K54: ='LOOKUP telda'!X14 -> 1 | L54: ='LOOKUP telda'!Y14 -> 0 | M54: =SUM('DATA MTD'!I54:L54) -> 5 | N54: ='LOOKUP telda'!Z14 -> 9 | O54: ='LOOKUP telda'!AA14 -> 1 | P54: ='LOOKUP telda'!AE14-'LOOKUP telda'!AA14 -> 0 | Q54: =SUM(O54:P54) -> 1 | R54: ='LOOKUP telda'!AF14 -> 3
B55: JATIM BARAT | C55: BATU | D55: ='LOOKUP telda'!#REF! -> #REF! | E55: ='LOOKUP telda'!#REF!+'LOOKUP telda'!#REF!+'LOOKUP telda'!#REF! -> #REF! | F55: ='LOOKUP telda'!#REF! -> #REF! | G55: ='LOOKUP telda'!#REF! -> #REF! | H55: ='LOOKUP telda'!#REF! -> #REF! | I55: ='LOOKUP telda'!#REF! -> #REF! | J55: ='LOOKUP telda'!#REF! -> #REF! | K55: ='LOOKUP telda'!#REF! -> #REF! | L55: ='LOOKUP telda'!#REF! -> #REF! | M55: =SUM('DATA MTD'!I55:L55) -> #REF! | N55: ='LOOKUP telda'!#REF! -> #REF! | O55: ='LOOKUP telda'!#REF! -> #REF! | P55: ='LOOKUP telda'!#REF!-'LOOKUP telda'!#REF! -> #REF! | Q55: =SUM(O55:P55) -> #REF! | R55: ='LOOKUP telda'!#REF! -> #REF!
C56: BLITAR | D56: ='LOOKUP telda'!E15 -> 31 | E56: ='LOOKUP telda'!F15+'LOOKUP telda'!G15+'LOOKUP telda'!H15 -> 3 | F56: ='LOOKUP telda'!I15 -> 0 | G56: ='LOOKUP telda'!J15 -> 8 | H56: ='LOOKUP telda'!K15 -> 0 | I56: ='LOOKUP telda'!L15 -> 0 | J56: ='LOOKUP telda'!P15 -> 0 | K56: ='LOOKUP telda'!X15 -> 0 | L56: ='LOOKUP telda'!Y15 -> 0 | M56: =SUM('DATA MTD'!I56:L56) -> 0 | N56: ='LOOKUP telda'!Z15 -> 16 | O56: ='LOOKUP telda'!AA15 -> 0 | P56: ='LOOKUP telda'!AE15-'LOOKUP telda'!AA15 -> 3 | Q56: =SUM(O56:P56) -> 3 | R56: ='LOOKUP telda'!AF15 -> 1
C57: BOJONEGORO | D57: ='LOOKUP telda'!E16 -> 12 | E57: ='LOOKUP telda'!F16+'LOOKUP telda'!G16+'LOOKUP telda'!H16 -> 0 | F57: ='LOOKUP telda'!I16 -> 0 | G57: ='LOOKUP telda'!J16 -> 0 | H57: ='LOOKUP telda'!K16 -> 0 | I57: ='LOOKUP telda'!L16 -> 0 | J57: ='LOOKUP telda'!P16 -> 0 | K57: ='LOOKUP telda'!X16 -> 0 | L57: ='LOOKUP telda'!Y16 -> 0 | M57: =SUM('DATA MTD'!I57:L57) -> 0 | N57: ='LOOKUP telda'!Z16 -> 12 | O57: ='LOOKUP telda'!AA16 -> 0 | P57: ='LOOKUP telda'!AE16-'LOOKUP telda'!AA16 -> 0 | Q57: =SUM(O57:P57) -> 0 | R57: ='LOOKUP telda'!AF16 -> 0
C58: KEDIRI | D58: ='LOOKUP telda'!E17 -> 21 | E58: ='LOOKUP telda'!F17+'LOOKUP telda'!G17+'LOOKUP telda'!H17 -> 0 | F58: ='LOOKUP telda'!I17 -> 1 | G58: ='LOOKUP telda'!J17 -> 0 | H58: ='LOOKUP telda'!K17 -> 0 | I58: ='LOOKUP telda'!L17 -> 0 | J58: ='LOOKUP telda'!P17 -> 0 | K58: ='LOOKUP telda'!X17 -> 0 | L58: ='LOOKUP telda'!Y17 -> 1 | M58: =SUM('DATA MTD'!I58:L58) -> 1 | N58: ='LOOKUP telda'!Z17 -> 16 | O58: ='LOOKUP telda'!AA17 -> 0 | P58: ='LOOKUP telda'!AE17-'LOOKUP telda'!AA17 -> 0 | Q58: =SUM(O58:P58) -> 0 | R58: ='LOOKUP telda'!AF17 -> 3
C59: KEPANJEN | D59: ='LOOKUP telda'!E18 -> 33 | E59: ='LOOKUP telda'!F18+'LOOKUP telda'!G18+'LOOKUP telda'!H18 -> 1 | F59: ='LOOKUP telda'!I18 -> 0 | G59: ='LOOKUP telda'!J18 -> 0 | H59: ='LOOKUP telda'!K18 -> 0 | I59: ='LOOKUP telda'!L18 -> 0 | J59: ='LOOKUP telda'!P18 -> 0 | K59: ='LOOKUP telda'!X18 -> 0 | L59: ='LOOKUP telda'!Y18 -> 1 | M59: =SUM('DATA MTD'!I59:L59) -> 1 | N59: ='LOOKUP telda'!Z18 -> 30 | O59: ='LOOKUP telda'!AA18 -> 0 | P59: ='LOOKUP telda'!AE18-'LOOKUP telda'!AA18 -> 1 | Q59: =SUM(O59:P59) -> 1 | R59: ='LOOKUP telda'!AF18 -> 0
C60: MADIUN | D60: ='LOOKUP telda'!E19 -> 34 | E60: ='LOOKUP telda'!F19+'LOOKUP telda'!G19+'LOOKUP telda'!H19 -> 0 | F60: ='LOOKUP telda'!I19 -> 0 | G60: ='LOOKUP telda'!J19 -> 0 | H60: ='LOOKUP telda'!K19 -> 0 | I60: ='LOOKUP telda'!L19 -> 0 | J60: ='LOOKUP telda'!P19 -> 0 | K60: ='LOOKUP telda'!X19 -> 0 | L60: ='LOOKUP telda'!Y19 -> 0 | M60: =SUM('DATA MTD'!I60:L60) -> 0 | N60: ='LOOKUP telda'!Z19 -> 31 | O60: ='LOOKUP telda'!AA19 -> 0 | P60: ='LOOKUP telda'!AE19-'LOOKUP telda'!AA19 -> 0 | Q60: =SUM(O60:P60) -> 0 | R60: ='LOOKUP telda'!AF19 -> 3
C61: NGANJUK | D61: ='LOOKUP telda'!E20 -> 8 | E61: ='LOOKUP telda'!F20+'LOOKUP telda'!G20+'LOOKUP telda'!H20 -> 0 | F61: ='LOOKUP telda'!I20 -> 0 | G61: ='LOOKUP telda'!J20 -> 0 | H61: ='LOOKUP telda'!K20 -> 0 | I61: ='LOOKUP telda'!L20 -> 0 | J61: ='LOOKUP telda'!P20 -> 0 | K61: ='LOOKUP telda'!X20 -> 0 | L61: ='LOOKUP telda'!Y20 -> 0 | M61: =SUM('DATA MTD'!I61:L61) -> 0 | N61: ='LOOKUP telda'!Z20 -> 7 | O61: ='LOOKUP telda'!AA20 -> 0 | P61: ='LOOKUP telda'!AE20-'LOOKUP telda'!AA20 -> 0 | Q61: =SUM(O61:P61) -> 0 | R61: ='LOOKUP telda'!AF20 -> 0
C62: NGAWI | D62: ='LOOKUP telda'!E21 -> 20 | E62: ='LOOKUP telda'!F21+'LOOKUP telda'!G21+'LOOKUP telda'!H21 -> 0 | F62: ='LOOKUP telda'!I21 -> 0 | G62: ='LOOKUP telda'!J21 -> 1 | H62: ='LOOKUP telda'!K21 -> 5 | I62: ='LOOKUP telda'!L21 -> 0 | J62: ='LOOKUP telda'!P21 -> 1 | K62: ='LOOKUP telda'!X21 -> 0 | L62: ='LOOKUP telda'!Y21 -> 1 | M62: =SUM('DATA MTD'!I62:L62) -> 2 | N62: ='LOOKUP telda'!Z21 -> 9 | O62: ='LOOKUP telda'!AA21 -> 0 | P62: ='LOOKUP telda'!AE21-'LOOKUP telda'!AA21 -> 1 | Q62: =SUM(O62:P62) -> 1 | R62: ='LOOKUP telda'!AF21 -> 2
C63: PONOROGO | D63: ='LOOKUP telda'!E22 -> 8 | E63: ='LOOKUP telda'!F22+'LOOKUP telda'!G22+'LOOKUP telda'!H22 -> 0 | F63: ='LOOKUP telda'!I22 -> 0 | G63: ='LOOKUP telda'!J22 -> 1 | H63: ='LOOKUP telda'!K22 -> 0 | I63: ='LOOKUP telda'!L22 -> 0 | J63: ='LOOKUP telda'!P22 -> 0 | K63: ='LOOKUP telda'!X22 -> 1 | L63: ='LOOKUP telda'!Y22 -> 0 | M63: =SUM('DATA MTD'!I63:L63) -> 1 | N63: ='LOOKUP telda'!Z22 -> 6 | O63: ='LOOKUP telda'!AA22 -> 0 | P63: ='LOOKUP telda'!AE22-'LOOKUP telda'!AA22 -> 0 | Q63: =SUM(O63:P63) -> 0 | R63: ='LOOKUP telda'!AF22 -> 0
C64: TRENGGALEK | D64: ='LOOKUP telda'!E23 -> 21 | E64: ='LOOKUP telda'!F23+'LOOKUP telda'!G23+'LOOKUP telda'!H23 -> 0 | F64: ='LOOKUP telda'!I23 -> 0 | G64: ='LOOKUP telda'!J23 -> 2 | H64: ='LOOKUP telda'!K23 -> 1 | I64: ='LOOKUP telda'!L23 -> 0 | J64: ='LOOKUP telda'!P23 -> 0 | K64: ='LOOKUP telda'!X23 -> 0 | L64: ='LOOKUP telda'!Y23 -> 0 | M64: =SUM('DATA MTD'!I64:L64) -> 0 | N64: ='LOOKUP telda'!Z23 -> 15 | O64: ='LOOKUP telda'!AA23 -> 0 | P64: ='LOOKUP telda'!AE23-'LOOKUP telda'!AA23 -> 1 | Q64: =SUM(O64:P64) -> 1 | R64: ='LOOKUP telda'!AF23 -> 2
C65: TUBAN | D65: ='LOOKUP telda'!E24 -> 8 | E65: ='LOOKUP telda'!F24+'LOOKUP telda'!G24+'LOOKUP telda'!H24 -> 0 | F65: ='LOOKUP telda'!I24 -> 0 | G65: ='LOOKUP telda'!J24 -> 0 | H65: ='LOOKUP telda'!K24 -> 0 | I65: ='LOOKUP telda'!L24 -> 0 | J65: ='LOOKUP telda'!P24 -> 0 | K65: ='LOOKUP telda'!X24 -> 0 | L65: ='LOOKUP telda'!Y24 -> 0 | M65: =SUM('DATA MTD'!I65:L65) -> 0 | N65: ='LOOKUP telda'!Z24 -> 6 | O65: ='LOOKUP telda'!AA24 -> 2 | P65: ='LOOKUP telda'!AE24-'LOOKUP telda'!AA24 -> 0 | Q65: =SUM(O65:P65) -> 2 | R65: ='LOOKUP telda'!AF24 -> 0
C66: TULUNGAGUNG | D66: ='LOOKUP telda'!E25 -> 22 | E66: ='LOOKUP telda'!F25+'LOOKUP telda'!G25+'LOOKUP telda'!H25 -> 1 | F66: ='LOOKUP telda'!I25 -> 2 | G66: ='LOOKUP telda'!J25 -> 0 | H66: ='LOOKUP telda'!K25 -> 2 | I66: ='LOOKUP telda'!L25 -> 0 | J66: ='LOOKUP telda'!P25 -> 0 | K66: ='LOOKUP telda'!X25 -> 0 | L66: ='LOOKUP telda'!Y25 -> 0 | M66: =SUM('DATA MTD'!I66:L66) -> 0 | N66: ='LOOKUP telda'!Z25 -> 13 | O66: ='LOOKUP telda'!AA25 -> 1 | P66: ='LOOKUP telda'!AE25-'LOOKUP telda'!AA25 -> 1 | Q66: =SUM(O66:P66) -> 2 | R66: ='LOOKUP telda'!AF25 -> 2
B67: JATIM TIMUR | C67: BANYUWANGI | D67: ='LOOKUP telda'!E26 -> 13 | E67: ='LOOKUP telda'!F26+'LOOKUP telda'!G26+'LOOKUP telda'!H26 -> 0 | F67: ='LOOKUP telda'!I26 -> 2 | G67: ='LOOKUP telda'!J26 -> 2 | H67: ='LOOKUP telda'!K26 -> 0 | I67: ='LOOKUP telda'!L26 -> 0 | J67: ='LOOKUP telda'!P26 -> 0 | K67: ='LOOKUP telda'!X26 -> 0 | L67: ='LOOKUP telda'!Y26 -> 0 | M67: =SUM('DATA MTD'!I67:L67) -> 0 | N67: ='LOOKUP telda'!Z26 -> 8 | O67: ='LOOKUP telda'!AA26 -> 0 | P67: ='LOOKUP telda'!AE26-'LOOKUP telda'!AA26 -> 1 | Q67: =SUM(O67:P67) -> 1 | R67: ='LOOKUP telda'!AF26 -> 0
C68: BONDOWOSO | D68: ='LOOKUP telda'!E27 -> 18 | E68: ='LOOKUP telda'!F27+'LOOKUP telda'!G27+'LOOKUP telda'!H27 -> 0 | F68: ='LOOKUP telda'!I27 -> 0 | G68: ='LOOKUP telda'!J27 -> 2 | H68: ='LOOKUP telda'!K27 -> 0 | I68: ='LOOKUP telda'!L27 -> 0 | J68: ='LOOKUP telda'!P27 -> 0 | K68: ='LOOKUP telda'!X27 -> 0 | L68: ='LOOKUP telda'!Y27 -> 0 | M68: =SUM('DATA MTD'!I68:L68) -> 0 | N68: ='LOOKUP telda'!Z27 -> 13 | O68: ='LOOKUP telda'!AA27 -> 1 | P68: ='LOOKUP telda'!AE27-'LOOKUP telda'!AA27 -> 2 | Q68: =SUM(O68:P68) -> 3 | R68: ='LOOKUP telda'!AF27 -> 0
C69: INNER - JATIM TIMUR | D69: ='LOOKUP telda'!E28 -> 12 | E69: ='LOOKUP telda'!F28+'LOOKUP telda'!G28+'LOOKUP telda'!H28 -> 0 | F69: ='LOOKUP telda'!I28 -> 0 | G69: ='LOOKUP telda'!J28 -> 0 | H69: ='LOOKUP telda'!K28 -> 0 | I69: ='LOOKUP telda'!L28 -> 0 | J69: ='LOOKUP telda'!P28 -> 0 | K69: ='LOOKUP telda'!X28 -> 0 | L69: ='LOOKUP telda'!Y28 -> 0 | M69: =SUM('DATA MTD'!I69:L69) -> 0 | N69: ='LOOKUP telda'!Z28 -> 11 | O69: ='LOOKUP telda'!AA28 -> 0 | P69: ='LOOKUP telda'!AE28-'LOOKUP telda'!AA28 -> 1 | Q69: =SUM(O69:P69) -> 1 | R69: ='LOOKUP telda'!AF28 -> 0
C70: JEMBER | D70: ='LOOKUP telda'!E29 -> 32 | E70: ='LOOKUP telda'!F29+'LOOKUP telda'!G29+'LOOKUP telda'!H29 -> 0 | F70: ='LOOKUP telda'!I29 -> 0 | G70: ='LOOKUP telda'!J29 -> 0 | H70: ='LOOKUP telda'!K29 -> 1 | I70: ='LOOKUP telda'!L29 -> 0 | J70: ='LOOKUP telda'!P29 -> 0 | K70: ='LOOKUP telda'!X29 -> 0 | L70: ='LOOKUP telda'!Y29 -> 1 | M70: =SUM('DATA MTD'!I70:L70) -> 1 | N70: ='LOOKUP telda'!Z29 -> 24 | O70: ='LOOKUP telda'!AA29 -> 1 | P70: ='LOOKUP telda'!AE29-'LOOKUP telda'!AA29 -> 2 | Q70: =SUM(O70:P70) -> 3 | R70: ='LOOKUP telda'!AF29 -> 3
C71: JOMBANG | D71: ='LOOKUP telda'!E30 -> 10 | E71: ='LOOKUP telda'!F30+'LOOKUP telda'!G30+'LOOKUP telda'!H30 -> 0 | F71: ='LOOKUP telda'!I30 -> 0 | G71: ='LOOKUP telda'!J30 -> 0 | H71: ='LOOKUP telda'!K30 -> 0 | I71: ='LOOKUP telda'!L30 -> 0 | J71: ='LOOKUP telda'!P30 -> 0 | K71: ='LOOKUP telda'!X30 -> 0 | L71: ='LOOKUP telda'!Y30 -> 1 | M71: =SUM('DATA MTD'!I71:L71) -> 1 | N71: ='LOOKUP telda'!Z30 -> 9 | O71: ='LOOKUP telda'!AA30 -> 0 | P71: ='LOOKUP telda'!AE30-'LOOKUP telda'!AA30 -> 0 | Q71: =SUM(O71:P71) -> 0 | R71: ='LOOKUP telda'!AF30 -> 0
C72: LUMAJANG | D72: ='LOOKUP telda'!E31 -> 21 | E72: ='LOOKUP telda'!F31+'LOOKUP telda'!G31+'LOOKUP telda'!H31 -> 0 | F72: ='LOOKUP telda'!I31 -> 0 | G72: ='LOOKUP telda'!J31 -> 0 | H72: ='LOOKUP telda'!K31 -> 1 | I72: ='LOOKUP telda'!L31 -> 0 | J72: ='LOOKUP telda'!P31 -> 0 | K72: ='LOOKUP telda'!X31 -> 0 | L72: ='LOOKUP telda'!Y31 -> 2 | M72: =SUM('DATA MTD'!I72:L72) -> 2 | N72: ='LOOKUP telda'!Z31 -> 14 | O72: ='LOOKUP telda'!AA31 -> 0 | P72: ='LOOKUP telda'!AE31-'LOOKUP telda'!AA31 -> 1 | Q72: =SUM(O72:P72) -> 1 | R72: ='LOOKUP telda'!AF31 -> 3
C73: MOJOKERTO | D73: ='LOOKUP telda'!E32 -> 8 | E73: ='LOOKUP telda'!F32+'LOOKUP telda'!G32+'LOOKUP telda'!H32 -> 0 | F73: ='LOOKUP telda'!I32 -> 0 | G73: ='LOOKUP telda'!J32 -> 0 | H73: ='LOOKUP telda'!K32 -> 0 | I73: ='LOOKUP telda'!L32 -> 0 | J73: ='LOOKUP telda'!P32 -> 0 | K73: ='LOOKUP telda'!X32 -> 2 | L73: ='LOOKUP telda'!Y32 -> 0 | M73: =SUM('DATA MTD'!I73:L73) -> 2 | N73: ='LOOKUP telda'!Z32 -> 6 | O73: ='LOOKUP telda'!AA32 -> 0 | P73: ='LOOKUP telda'!AE32-'LOOKUP telda'!AA32 -> 0 | Q73: =SUM(O73:P73) -> 0 | R73: ='LOOKUP telda'!AF32 -> 0
C74: PASURUAN | D74: ='LOOKUP telda'!E33 -> 30 | E74: ='LOOKUP telda'!F33+'LOOKUP telda'!G33+'LOOKUP telda'!H33 -> 2 | F74: ='LOOKUP telda'!I33 -> 1 | G74: ='LOOKUP telda'!J33 -> 2 | H74: ='LOOKUP telda'!K33 -> 0 | I74: ='LOOKUP telda'!L33 -> 0 | J74: ='LOOKUP telda'!P33 -> 0 | K74: ='LOOKUP telda'!X33 -> 0 | L74: ='LOOKUP telda'!Y33 -> 0 | M74: =SUM('DATA MTD'!I74:L74) -> 0 | N74: ='LOOKUP telda'!Z33 -> 22 | O74: ='LOOKUP telda'!AA33 -> 0 | P74: ='LOOKUP telda'!AE33-'LOOKUP telda'!AA33 -> 0 | Q74: =SUM(O74:P74) -> 0 | R74: ='LOOKUP telda'!AF33 -> 3
C75: PROBOLINGGO | D75: ='LOOKUP telda'!E34 -> 23 | E75: ='LOOKUP telda'!F34+'LOOKUP telda'!G34+'LOOKUP telda'!H34 -> 2 | F75: ='LOOKUP telda'!I34 -> 1 | G75: ='LOOKUP telda'!J34 -> 0 | H75: ='LOOKUP telda'!K34 -> 0 | I75: ='LOOKUP telda'!L34 -> 0 | J75: ='LOOKUP telda'!P34 -> 0 | K75: ='LOOKUP telda'!X34 -> 0 | L75: ='LOOKUP telda'!Y34 -> 0 | M75: =SUM('DATA MTD'!I75:L75) -> 0 | N75: ='LOOKUP telda'!Z34 -> 16 | O75: ='LOOKUP telda'!AA34 -> 2 | P75: ='LOOKUP telda'!AE34-'LOOKUP telda'!AA34 -> 2 | Q75: =SUM(O75:P75) -> 4 | R75: ='LOOKUP telda'!AF34 -> 0
C76: SITUBONDO | D76: ='LOOKUP telda'!E35 -> 16 | E76: ='LOOKUP telda'!F35+'LOOKUP telda'!G35+'LOOKUP telda'!H35 -> 0 | F76: ='LOOKUP telda'!I35 -> 0 | G76: ='LOOKUP telda'!J35 -> 1 | H76: ='LOOKUP telda'!K35 -> 0 | I76: ='LOOKUP telda'!L35 -> 0 | J76: ='LOOKUP telda'!P35 -> 1 | K76: ='LOOKUP telda'!X35 -> 0 | L76: ='LOOKUP telda'!Y35 -> 1 | M76: =SUM('DATA MTD'!I76:L76) -> 2 | N76: ='LOOKUP telda'!Z35 -> 12 | O76: ='LOOKUP telda'!AA35 -> 1 | P76: ='LOOKUP telda'!AE35-'LOOKUP telda'!AA35 -> 0 | Q76: =SUM(O76:P76) -> 1 | R76: ='LOOKUP telda'!AF35 -> 0
B77: NUSRA | C77: ATAMBUA | D77: ='LOOKUP telda'!E36 -> 3 | E77: ='LOOKUP telda'!F36+'LOOKUP telda'!G36+'LOOKUP telda'!H36 -> 0 | F77: ='LOOKUP telda'!I36 -> 0 | G77: ='LOOKUP telda'!J36 -> 0 | H77: ='LOOKUP telda'!K36 -> 0 | I77: ='LOOKUP telda'!L36 -> 0 | J77: ='LOOKUP telda'!P36 -> 0 | K77: ='LOOKUP telda'!X36 -> 0 | L77: ='LOOKUP telda'!Y36 -> 0 | M77: =SUM('DATA MTD'!I77:L77) -> 0 | N77: ='LOOKUP telda'!Z36 -> 3 | O77: ='LOOKUP telda'!AA36 -> 0 | P77: ='LOOKUP telda'!AE36-'LOOKUP telda'!AA36 -> 0 | Q77: =SUM(O77:P77) -> 0 | R77: ='LOOKUP telda'!AF36 -> 0
C78: BIMA | D78: ='LOOKUP telda'!E37 -> 2 | E78: ='LOOKUP telda'!F37+'LOOKUP telda'!G37+'LOOKUP telda'!H37 -> 1 | F78: ='LOOKUP telda'!I37 -> 0 | G78: ='LOOKUP telda'!J37 -> 0 | H78: ='LOOKUP telda'!K37 -> 0 | I78: ='LOOKUP telda'!L37 -> 0 | J78: ='LOOKUP telda'!P37 -> 0 | K78: ='LOOKUP telda'!X37 -> 0 | L78: ='LOOKUP telda'!Y37 -> 0 | M78: =SUM('DATA MTD'!I78:L78) -> 0 | N78: ='LOOKUP telda'!Z37 -> 1 | O78: ='LOOKUP telda'!AA37 -> 0 | P78: ='LOOKUP telda'!AE37-'LOOKUP telda'!AA37 -> 0 | Q78: =SUM(O78:P78) -> 0 | R78: ='LOOKUP telda'!AF37 -> 0
C79: ENDE | D79: ='LOOKUP telda'!E38 -> 18 | E79: ='LOOKUP telda'!F38+'LOOKUP telda'!G38+'LOOKUP telda'!H38 -> 0 | F79: ='LOOKUP telda'!I38 -> 0 | G79: ='LOOKUP telda'!J38 -> 0 | H79: ='LOOKUP telda'!K38 -> 0 | I79: ='LOOKUP telda'!L38 -> 1 | J79: ='LOOKUP telda'!P38 -> 1 | K79: ='LOOKUP telda'!X38 -> 1 | L79: ='LOOKUP telda'!Y38 -> 1 | M79: =SUM('DATA MTD'!I79:L79) -> 4 | N79: ='LOOKUP telda'!Z38 -> 9 | O79: ='LOOKUP telda'!AA38 -> 0 | P79: ='LOOKUP telda'!AE38-'LOOKUP telda'!AA38 -> 0 | Q79: =SUM(O79:P79) -> 0 | R79: ='LOOKUP telda'!AF38 -> 5
C80: INNER - NUSA TENGGARA | D80: ='LOOKUP telda'!E39 -> 14 | E80: ='LOOKUP telda'!F39+'LOOKUP telda'!G39+'LOOKUP telda'!H39 -> 0 | F80: ='LOOKUP telda'!I39 -> 0 | G80: ='LOOKUP telda'!J39 -> 0 | H80: ='LOOKUP telda'!K39 -> 0 | I80: ='LOOKUP telda'!L39 -> 0 | J80: ='LOOKUP telda'!P39 -> 2 | K80: ='LOOKUP telda'!X39 -> 0 | L80: ='LOOKUP telda'!Y39 -> 0 | M80: =SUM('DATA MTD'!I80:L80) -> 2 | N80: ='LOOKUP telda'!Z39 -> 12 | O80: ='LOOKUP telda'!AA39 -> 0 | P80: ='LOOKUP telda'!AE39-'LOOKUP telda'!AA39 -> 0 | Q80: =SUM(O80:P80) -> 0 | R80: ='LOOKUP telda'!AF39 -> 0
C81: KUPANG | D81: ='LOOKUP telda'!E40 -> 26 | E81: ='LOOKUP telda'!F40+'LOOKUP telda'!G40+'LOOKUP telda'!H40 -> 0 | F81: ='LOOKUP telda'!I40 -> 0 | G81: ='LOOKUP telda'!J40 -> 0 | H81: ='LOOKUP telda'!K40 -> 0 | I81: ='LOOKUP telda'!L40 -> 0 | J81: ='LOOKUP telda'!P40 -> 3 | K81: ='LOOKUP telda'!X40 -> 0 | L81: ='LOOKUP telda'!Y40 -> 0 | M81: =SUM('DATA MTD'!I81:L81) -> 3 | N81: ='LOOKUP telda'!Z40 -> 16 | O81: ='LOOKUP telda'!AA40 -> 1 | P81: ='LOOKUP telda'!AE40-'LOOKUP telda'!AA40 -> 0 | Q81: =SUM(O81:P81) -> 1 | R81: ='LOOKUP telda'!AF40 -> 6
C82: LABOAN BAJO | D82: ='LOOKUP telda'!E41 -> 24 | E82: ='LOOKUP telda'!F41+'LOOKUP telda'!G41+'LOOKUP telda'!H41 -> 0 | F82: ='LOOKUP telda'!I41 -> 1 | G82: ='LOOKUP telda'!J41 -> 2 | H82: ='LOOKUP telda'!K41 -> 2 | I82: ='LOOKUP telda'!L41 -> 0 | J82: ='LOOKUP telda'!P41 -> 6 | K82: ='LOOKUP telda'!X41 -> 0 | L82: ='LOOKUP telda'!Y41 -> 1 | M82: =SUM('DATA MTD'!I82:L82) -> 7 | N82: ='LOOKUP telda'!Z41 -> 10 | O82: ='LOOKUP telda'!AA41 -> 0 | P82: ='LOOKUP telda'!AE41-'LOOKUP telda'!AA41 -> 3 | Q82: =SUM(O82:P82) -> 3 | R82: ='LOOKUP telda'!AF41 -> 0
C83: LOMBOK BARAT TENGAH | D83: ='LOOKUP telda'!E42 -> 9 | E83: ='LOOKUP telda'!F42+'LOOKUP telda'!G42+'LOOKUP telda'!H42 -> 0 | F83: ='LOOKUP telda'!I42 -> 0 | G83: ='LOOKUP telda'!J42 -> 0 | H83: ='LOOKUP telda'!K42 -> 2 | I83: ='LOOKUP telda'!L42 -> 0 | J83: ='LOOKUP telda'!P42 -> 1 | K83: ='LOOKUP telda'!X42 -> 0 | L83: ='LOOKUP telda'!Y42 -> 0 | M83: =SUM('DATA MTD'!I83:L83) -> 1 | N83: ='LOOKUP telda'!Z42 -> 6 | O83: ='LOOKUP telda'!AA42 -> 0 | P83: ='LOOKUP telda'!AE42-'LOOKUP telda'!AA42 -> 0 | Q83: =SUM(O83:P83) -> 0 | R83: ='LOOKUP telda'!AF42 -> 0
C84: LOMBOK TIMUR UTARA | D84: ='LOOKUP telda'!E43 -> 32 | E84: ='LOOKUP telda'!F43+'LOOKUP telda'!G43+'LOOKUP telda'!H43 -> 1 | F84: ='LOOKUP telda'!I43 -> 1 | G84: ='LOOKUP telda'!J43 -> 2 | H84: ='LOOKUP telda'!K43 -> 1 | I84: ='LOOKUP telda'!L43 -> 0 | J84: ='LOOKUP telda'!P43 -> 2 | K84: ='LOOKUP telda'!X43 -> 2 | L84: ='LOOKUP telda'!Y43 -> 0 | M84: =SUM('DATA MTD'!I84:L84) -> 4 | N84: ='LOOKUP telda'!Z43 -> 19 | O84: ='LOOKUP telda'!AA43 -> 0 | P84: ='LOOKUP telda'!AE43-'LOOKUP telda'!AA43 -> 0 | Q84: =SUM(O84:P84) -> 0 | R84: ='LOOKUP telda'!AF43 -> 4
C85: MAUMERE | D85: ='LOOKUP telda'!E44 -> 32 | E85: ='LOOKUP telda'!F44+'LOOKUP telda'!G44+'LOOKUP telda'!H44 -> 1 | F85: ='LOOKUP telda'!I44 -> 1 | G85: ='LOOKUP telda'!J44 -> 2 | H85: ='LOOKUP telda'!K44 -> 0 | I85: ='LOOKUP telda'!L44 -> 0 | J85: ='LOOKUP telda'!P44 -> 1 | K85: ='LOOKUP telda'!X44 -> 1 | L85: ='LOOKUP telda'!Y44 -> 1 | M85: =SUM('DATA MTD'!I85:L85) -> 3 | N85: ='LOOKUP telda'!Z44 -> 19 | O85: ='LOOKUP telda'!AA44 -> 0 | P85: ='LOOKUP telda'!AE44-'LOOKUP telda'!AA44 -> 0 | Q85: =SUM(O85:P85) -> 0 | R85: ='LOOKUP telda'!AF44 -> 6
C86: SUMBAWA | D86: ='LOOKUP telda'!E45 -> 8 | E86: ='LOOKUP telda'!F45+'LOOKUP telda'!G45+'LOOKUP telda'!H45 -> 0 | F86: ='LOOKUP telda'!I45 -> 0 | G86: ='LOOKUP telda'!J45 -> 0 | H86: ='LOOKUP telda'!K45 -> 0 | I86: ='LOOKUP telda'!L45 -> 0 | J86: ='LOOKUP telda'!P45 -> 2 | K86: ='LOOKUP telda'!X45 -> 0 | L86: ='LOOKUP telda'!Y45 -> 2 | M86: =SUM('DATA MTD'!I86:L86) -> 4 | N86: ='LOOKUP telda'!Z45 -> 4 | O86: ='LOOKUP telda'!AA45 -> 0 | P86: ='LOOKUP telda'!AE45-'LOOKUP telda'!AA45 -> 0 | Q86: =SUM(O86:P86) -> 0 | R86: ='LOOKUP telda'!AF45 -> 0
C87: WAIKABUBAK | D87: ='LOOKUP telda'!E46 -> 38 | E87: ='LOOKUP telda'!F46+'LOOKUP telda'!G46+'LOOKUP telda'!H46 -> 3 | F87: ='LOOKUP telda'!I46 -> 0 | G87: ='LOOKUP telda'!J46 -> 3 | H87: ='LOOKUP telda'!K46 -> 0 | I87: ='LOOKUP telda'!L46 -> 0 | J87: ='LOOKUP telda'!P46 -> 1 | K87: ='LOOKUP telda'!X46 -> 1 | L87: ='LOOKUP telda'!Y46 -> 0 | M87: =SUM('DATA MTD'!I87:L87) -> 2 | N87: ='LOOKUP telda'!Z46 -> 20 | O87: ='LOOKUP telda'!AA46 -> 0 | P87: ='LOOKUP telda'!AE46-'LOOKUP telda'!AA46 -> 0 | Q87: =SUM(O87:P87) -> 0 | R87: ='LOOKUP telda'!AF46 -> 10
C88: WAINGAPU | D88: ='LOOKUP telda'!E47 -> 2 | E88: ='LOOKUP telda'!F47+'LOOKUP telda'!G47+'LOOKUP telda'!H47 -> 0 | F88: ='LOOKUP telda'!I47 -> 0 | G88: ='LOOKUP telda'!J47 -> 0 | H88: ='LOOKUP telda'!K47 -> 0 | I88: ='LOOKUP telda'!L47 -> 0 | J88: ='LOOKUP telda'!P47 -> 0 | K88: ='LOOKUP telda'!X47 -> 0 | L88: ='LOOKUP telda'!Y47 -> 0 | M88: =SUM('DATA MTD'!I88:L88) -> 0 | N88: ='LOOKUP telda'!Z47 -> 1 | O88: ='LOOKUP telda'!AA47 -> 1 | P88: ='LOOKUP telda'!AE47-'LOOKUP telda'!AA47 -> 0 | Q88: =SUM(O88:P88) -> 1 | R88: ='LOOKUP telda'!AF47 -> 0
B89: SURAMADU | C89: BANGKALAN | D89: ='LOOKUP telda'!E48 -> 5 | E89: ='LOOKUP telda'!F48+'LOOKUP telda'!G48+'LOOKUP telda'!H48 -> 0 | F89: ='LOOKUP telda'!I48 -> 1 | G89: ='LOOKUP telda'!J48 -> 0 | H89: ='LOOKUP telda'!K48 -> 0 | I89: ='LOOKUP telda'!L48 -> 0 | J89: ='LOOKUP telda'!P48 -> 0 | K89: ='LOOKUP telda'!X48 -> 0 | L89: ='LOOKUP telda'!Y48 -> 0 | M89: =SUM('DATA MTD'!I89:L89) -> 0 | N89: ='LOOKUP telda'!Z48 -> 4 | O89: ='LOOKUP telda'!AA48 -> 0 | P89: ='LOOKUP telda'!AE48-'LOOKUP telda'!AA48 -> 0 | Q89: =SUM(O89:P89) -> 0 | R89: ='LOOKUP telda'!AF48 -> 0
C90: GRESIK | D90: ='LOOKUP telda'!E49 -> 23 | E90: ='LOOKUP telda'!F49+'LOOKUP telda'!G49+'LOOKUP telda'!H49 -> 3 | F90: ='LOOKUP telda'!I49 -> 0 | G90: ='LOOKUP telda'!J49 -> 1 | H90: ='LOOKUP telda'!K49 -> 0 | I90: ='LOOKUP telda'!L49 -> 0 | J90: ='LOOKUP telda'!P49 -> 0 | K90: ='LOOKUP telda'!X49 -> 0 | L90: ='LOOKUP telda'!Y49 -> 0 | M90: =SUM('DATA MTD'!I90:L90) -> 0 | N90: ='LOOKUP telda'!Z49 -> 14 | O90: ='LOOKUP telda'!AA49 -> 0 | P90: ='LOOKUP telda'!AE49-'LOOKUP telda'!AA49 -> 0 | Q90: =SUM(O90:P90) -> 0 | R90: ='LOOKUP telda'!AF49 -> 5
C91: KENJERAN | D91: ='LOOKUP telda'!E50 -> 44 | E91: ='LOOKUP telda'!F50+'LOOKUP telda'!G50+'LOOKUP telda'!H50 -> 0 | F91: ='LOOKUP telda'!I50 -> 1 | G91: ='LOOKUP telda'!J50 -> 3 | H91: ='LOOKUP telda'!K50 -> 0 | I91: ='LOOKUP telda'!L50 -> 1 | J91: ='LOOKUP telda'!P50 -> 0 | K91: ='LOOKUP telda'!X50 -> 1 | L91: ='LOOKUP telda'!Y50 -> 2 | M91: =SUM('DATA MTD'!I91:L91) -> 4 | N91: ='LOOKUP telda'!Z50 -> 25 | O91: ='LOOKUP telda'!AA50 -> 0 | P91: ='LOOKUP telda'!AE50-'LOOKUP telda'!AA50 -> 0 | Q91: =SUM(O91:P91) -> 0 | R91: ='LOOKUP telda'!AF50 -> 11
C92: KETINTANG | D92: ='LOOKUP telda'!E51 -> 22 | E92: ='LOOKUP telda'!F51+'LOOKUP telda'!G51+'LOOKUP telda'!H51 -> 0 | F92: ='LOOKUP telda'!I51 -> 1 | G92: ='LOOKUP telda'!J51 -> 2 | H92: ='LOOKUP telda'!K51 -> 0 | I92: ='LOOKUP telda'!L51 -> 0 | J92: ='LOOKUP telda'!P51 -> 0 | K92: ='LOOKUP telda'!X51 -> 0 | L92: ='LOOKUP telda'!Y51 -> 1 | M92: =SUM('DATA MTD'!I92:L92) -> 1 | N92: ='LOOKUP telda'!Z51 -> 14 | O92: ='LOOKUP telda'!AA51 -> 0 | P92: ='LOOKUP telda'!AE51-'LOOKUP telda'!AA51 -> 0 | Q92: =SUM(O92:P92) -> 0 | R92: ='LOOKUP telda'!AF51 -> 4
C93: LAMONGAN | D93: ='LOOKUP telda'!E52 -> 37 | E93: ='LOOKUP telda'!F52+'LOOKUP telda'!G52+'LOOKUP telda'!H52 -> 2 | F93: ='LOOKUP telda'!I52 -> 1 | G93: ='LOOKUP telda'!J52 -> 3 | H93: ='LOOKUP telda'!K52 -> 0 | I93: ='LOOKUP telda'!L52 -> 0 | J93: ='LOOKUP telda'!P52 -> 0 | K93: ='LOOKUP telda'!X52 -> 1 | L93: ='LOOKUP telda'!Y52 -> 0 | M93: =SUM('DATA MTD'!I93:L93) -> 1 | N93: ='LOOKUP telda'!Z52 -> 22 | O93: ='LOOKUP telda'!AA52 -> 0 | P93: ='LOOKUP telda'!AE52-'LOOKUP telda'!AA52 -> 0 | Q93: =SUM(O93:P93) -> 0 | R93: ='LOOKUP telda'!AF52 -> 8
C94: MANYAR | D94: ='LOOKUP telda'!E53 -> 32 | E94: ='LOOKUP telda'!F53+'LOOKUP telda'!G53+'LOOKUP telda'!H53 -> 2 | F94: ='LOOKUP telda'!I53 -> 1 | G94: ='LOOKUP telda'!J53 -> 3 | H94: ='LOOKUP telda'!K53 -> 1 | I94: ='LOOKUP telda'!L53 -> 0 | J94: ='LOOKUP telda'!P53 -> 1 | K94: ='LOOKUP telda'!X53 -> 3 | L94: ='LOOKUP telda'!Y53 -> 0 | M94: =SUM('DATA MTD'!I94:L94) -> 4 | N94: ='LOOKUP telda'!Z53 -> 19 | O94: ='LOOKUP telda'!AA53 -> 0 | P94: ='LOOKUP telda'!AE53-'LOOKUP telda'!AA53 -> 1 | Q94: =SUM(O94:P94) -> 1 | R94: ='LOOKUP telda'!AF53 -> 1
C95: PAMEKASAN | D95: ='LOOKUP telda'!E54 -> 35 | E95: ='LOOKUP telda'!F54+'LOOKUP telda'!G54+'LOOKUP telda'!H54 -> 1 | F95: ='LOOKUP telda'!I54 -> 0 | G95: ='LOOKUP telda'!J54 -> 5 | H95: ='LOOKUP telda'!K54 -> 0 | I95: ='LOOKUP telda'!L54 -> 0 | J95: ='LOOKUP telda'!P54 -> 0 | K95: ='LOOKUP telda'!X54 -> 0 | L95: ='LOOKUP telda'!Y54 -> 1 | M95: =SUM('DATA MTD'!I95:L95) -> 1 | N95: ='LOOKUP telda'!Z54 -> 23 | O95: ='LOOKUP telda'!AA54 -> 1 | P95: ='LOOKUP telda'!AE54-'LOOKUP telda'!AA54 -> 0 | Q95: =SUM(O95:P95) -> 1 | R95: ='LOOKUP telda'!AF54 -> 4
C96: TANDES | D96: ='LOOKUP telda'!E55 -> 38 | E96: ='LOOKUP telda'!F55+'LOOKUP telda'!G55+'LOOKUP telda'!H55 -> 1 | F96: ='LOOKUP telda'!I55 -> 0 | G96: ='LOOKUP telda'!J55 -> 3 | H96: ='LOOKUP telda'!K55 -> 0 | I96: ='LOOKUP telda'!L55 -> 0 | J96: ='LOOKUP telda'!P55 -> 0 | K96: ='LOOKUP telda'!X55 -> 0 | L96: ='LOOKUP telda'!Y55 -> 0 | M96: =SUM('DATA MTD'!I96:L96) -> 0 | N96: ='LOOKUP telda'!Z55 -> 27 | O96: ='LOOKUP telda'!AA55 -> 0 | P96: ='LOOKUP telda'!AE55-'LOOKUP telda'!AA55 -> 1 | Q96: =SUM(O96:P96) -> 1 | R96: ='LOOKUP telda'!AF55 -> 6
B97: TOTAL | D97: =SUM(D47:D96) -> #REF! | E97: =SUM(E47:E96) -> #REF! | F97: =SUM(F47:F96) -> #REF! | G97: =SUM(G47:G96) -> #REF! | H97: =SUM(H47:H96) -> #REF! | I97: =SUM(I47:I96) -> #REF! | J97: =SUM(J47:J96) -> #REF! | K97: =SUM(K47:K96) -> #REF! | ... R97: =SUM(R47:R96) -> #REF!

Sheet HARIAN
C2: ="PROVISIONING NEW SALES INDIBIZ TR3 JBN MTD "&TEXT(TODAY()-1,"YYYY-MM-DD ") -> PROVISIONING NEW SALES INDIBIZ TR3 JBN MTD 2026-10-15
C3: ="PERIODE ORDER & PS : 2026-01-01 to "&TEXT(TODAY()-1,"YYYY-MM-DD ") -> PERIODE ORDER & PS : 2026-01-01 to 2026-10-15
C4: Last update proses : 06-03-2026 15:19:48 WIB (Source: ETL XPRO)
C6: WITEL | D6: (RE) | E6: INPROGRESS SC+QC1+FCC | F6: CANCEL | I6: REVOKE | J6: SURVEY NEW MANJA | K6: UN-SC | L6: OGP | P6: JML COMP (PS) | Q6: PS/RE (%) (Target 80%) | R6: PS/PI (%) (Target 88%) | S6: TTI COMPLY 1X 24 (%) (Target 85%)
F9: BY FCC | G9: KNDL PLGN | H9: KNDL NON PLGN | L9: PRE PI | M9: PI | N9: FALLOUT | O9: ACT COMP (QC2) | X9: =205/216 -> 0.94907407
C10: BALI | D10: ='COPY DATA XPRO'!E63 -> 126 | E10: ='COPY DATA XPRO'!F63+'COPY DATA XPRO'!G63+'COPY DATA XPRO'!H63 -> 1 | F10: ='COPY DATA XPRO'!I63 -> 7 | G10: ='COPY DATA XPRO'!AA63 -> 1 | H10: ='COPY DATA XPRO'!AE63-HARIAN!G10 -> 11 | I10: ='COPY DATA XPRO'!AF63 -> 14 | J10: ='COPY DATA XPRO'!J63 -> 5 | K10: ='COPY DATA XPRO'!K63 -> 10 | L10: ='COPY DATA XPRO'!L63 -> 0 | M10: ='COPY DATA XPRO'!P63 -> 12 | N10: ='COPY DATA XPRO'!X63 -> 4 | O10: ='COPY DATA XPRO'!Y63 -> 1 | P10: ='COPY DATA XPRO'!Z63 -> 60 | Q10: =T10 -> 0.63157895 | R10: =U10 -> 0.77922078 | S10: =VLOOKUP(C10,Sheet3!$A$19:$G$81,7,FALSE) -> 0.91666667 | T10: =P10/(D10-F10-K10-I10) -> 0.63157895 | U10: =P10/(M10+N10+O10+P10) -> 0.77922078
C11: JATIM BARAT | D11: ='COPY DATA XPRO'!E64 -> 231 | E11: ='COPY DATA XPRO'!F64+'COPY DATA XPRO'!G64+'COPY DATA XPRO'!H64 -> 5 | F11: ='COPY DATA XPRO'!I64 -> 5 | G11: ='COPY DATA XPRO'!AA64 -> 3 | H11: ='COPY DATA XPRO'!AE64-HARIAN!G11 -> 8 | I11: ='COPY DATA XPRO'!AF64 -> 13 | J11: ='COPY DATA XPRO'!J64 -> 14 | K11: ='COPY DATA XPRO'!K64 -> 8 | L11: ='COPY DATA XPRO'!L64 -> 0 | M11: ='COPY DATA XPRO'!P64 -> 1 | N11: ='COPY DATA XPRO'!X64 -> 1 | O11: ='COPY DATA XPRO'!Y64 -> 3 | P11: ='COPY DATA XPRO'!Z64 -> 169 | Q11: =T11 -> 0.82439024 | R11: =U11 -> 0.97126437 | S11: =VLOOKUP(C11,Sheet3!$A$19:$G$81,7,FALSE) -> 0.98224852 | T11: =P11/(D11-F11-K11-I11) -> 0.82439024 | U11: =P11/(M11+N11+O11+P11) -> 0.97126437
C12: JATIM TIMUR | D12: ='COPY DATA XPRO'!E65 -> 173 | E12: ='COPY DATA XPRO'!F65+'COPY DATA XPRO'!G65+'COPY DATA XPRO'!H65 -> 4 | F12: ='COPY DATA XPRO'!I65 -> 2 | G12: ='COPY DATA XPRO'!AA65 -> 5 | H12: ='COPY DATA XPRO'!AE65-HARIAN!G12 -> 8 | I12: ='COPY DATA XPRO'!AF65 -> 9 | J12: ='COPY DATA XPRO'!J65 -> 5 | K12: ='COPY DATA XPRO'!K65 -> 2 | L12: ='COPY DATA XPRO'!L65 -> 0 | M12: ='COPY DATA XPRO'!P65 -> 1 | N12: ='COPY DATA XPRO'!X65 -> 2 | O12: ='COPY DATA XPRO'!Y65 -> 5 | P12: ='COPY DATA XPRO'!Z65 -> 130 | Q12: =T12 -> 0.8125 | R12: =U12 -> 0.94202899 | S12: =VLOOKUP(C12,Sheet3!$A$19:$G$81,7,FALSE) -> 1 | T12: =P12/(D12-F12-K12-I12) -> 0.8125 | U12: =P12/(M12+N12+O12+P12) -> 0.94202899
C13: NUSA TENGGARA | D13: ='COPY DATA XPRO'!E66 -> 210 | E13: ='COPY DATA XPRO'!F66+'COPY DATA XPRO'!G66+'COPY DATA XPRO'!H66 -> 6 | F13: ='COPY DATA XPRO'!I66 -> 4 | G13: ='COPY DATA XPRO'!AA66 -> 2 | H13: ='COPY DATA XPRO'!AE66-HARIAN!G13 -> 3 | I13: ='COPY DATA XPRO'!AF66 -> 31 | J13: ='COPY DATA XPRO'!J66 -> 9 | K13: ='COPY DATA XPRO'!K66 -> 5 | L13: ='COPY DATA XPRO'!L66 -> 1 | M13: ='COPY DATA XPRO'!P66 -> 19 | N13: ='COPY DATA XPRO'!X66 -> 5 | O13: ='COPY DATA XPRO'!Y66 -> 5 | P13: ='COPY DATA XPRO'!Z66 -> 121 | Q13: =T13 -> 0.71176471 | R13: =U13 -> 0.80666667 | S13: =VLOOKUP(C13,Sheet3!$A$19:$G$81,7,FALSE) -> 0.76033058 | T13: =P13/(D13-F13-K13-I13) -> 0.71176471 | U13: =P13/(M13+N13+O13+P13) -> 0.80666667
C14: SURAMADU | D14: ='COPY DATA XPRO'!E69 -> 274 | E14: ='COPY DATA XPRO'!F69+'COPY DATA XPRO'!G69+'COPY DATA XPRO'!H69 -> 11 | F14: ='COPY DATA XPRO'!I69 -> 6 | G14: ='COPY DATA XPRO'!AA69 -> 1 | H14: ='COPY DATA XPRO'!AE69-HARIAN!G14 -> 3 | I14: ='COPY DATA XPRO'!AF69 -> 47 | J14: ='COPY DATA XPRO'!J69 -> 29 | K14: ='COPY DATA XPRO'!K69 -> 2 | L14: ='COPY DATA XPRO'!L69 -> 1 | M14: ='COPY DATA XPRO'!P69 -> 1 | N14: ='COPY DATA XPRO'!X69 -> 5 | O14: ='COPY DATA XPRO'!Y69 -> 4 | P14: ='COPY DATA XPRO'!Z69 -> 164 | Q14: =T14 -> 0.74885845 | R14: =U14 -> 0.94252874 | S14: =VLOOKUP(C14,Sheet3!$A$19:$G$81,7,FALSE) -> 0.98170732 | T14: =P14/(D14-F14-K14-I14) -> 0.74885845 | U14: =P14/(M14+N14+O14+P14) -> 0.94252874
C15: TOTAL | D15: =SUM(D10:D14) -> 1014 | E15: =SUM(E10:E14) -> 27 | F15: =SUM(F10:F14) -> 24 | G15: =SUM(G10:G14) -> 12 | H15: =SUM(H10:H14) -> 33 | I15: =SUM(I10:I14) -> 114 | J15: =SUM(J10:J14) -> 62 | K15: =SUM(K10:K14) -> 27 | ... P15: =SUM(P10:P14) -> 644 | Q15: =T15 -> 0.75853946 | R15: =U15 -> 0.90322581 | S15: =Sheet3!G10 -> 0.9378882 | T15: =P15/(D15-F15-K15-I15) -> 0.75853946 | U15: =P15/(M15+N15+O15+P15) -> 0.90322581
C17: Keterangan | D17: UIC | G17: * Target PS/PI Sesuai dengan Draft SLA MSA 2025 | L17: FORMULA
D18: Inputer, DIT, FCC | G18: 1. Time To Install (TTI) Comply Indibiz | 1x24 jam | L18: PI/RE : (Total PI + Total Fallout + Act Comp + Jumlah PS + Total Cancel) / Registered
D19: Order Cancel & Revoke | G19: 2. Fulfillment Guarantee (FFG) Indibiz | 60 hari | L19: PS/RE : PS / (Registered - Cancel by FCC - UNSC - Revoke)
D20: TA, BGESOPS, DAMAN, DIT | G20: 3. TTR Fulfillment Guarantee Indibiz | 3 jam | L20: PS/PI : PS / (Total PI + Total Fallout + Act Comp + Jumlah PS)
D21: Completed (PS) | G21: 4. PS to PI Ratio Indibiz Q3 88 % (Incremental)
D22: Performansi | G22: 5. Underspec warranty Indibiz | <= -25dBm
B24: =C2 -> PROVISIONING NEW SALES INDIBIZ TR3 JBN MTD 2026-10-15
B25: =C3 -> PERIODE ORDER & PS : 2026-01-01 to 2026-10-15
B26: =C4 -> Last update proses : 06-03-2026 15:19:48 WIB (Source: ETL XPRO)
B29: WITEL | C29: TELDA | D29: (RE) | E29: INPROGRESS SC+QC1+FCC | F29: CANCEL | I29: REVOKE | J29: SURVEY NEW MANJA | K29: UN-SC | L29: OGP | P29: JML COMP (PS) | Q29: PS/RE (%) (Target 80%) | R29: PS/PI (%) (Target 88%) | S29: TTI COMPLY 1X 24 (%) (Target 85%)
F32: BY FCC | G32: KNDL PLGN | H32: KNDL NON PLGN | L32: PRE PI | M32: PI | N32: FALLOUT | O32: ACT COMP (QC2) | V32: new telda
B33: BALI | C33: GIANYAR | D33: ='LOOKUP telda'!E7 -> 12 | E33: ='LOOKUP telda'!F7+'LOOKUP telda'!G7+'LOOKUP telda'!H7 -> 0 | F33: ='LOOKUP telda'!I7 -> 0 | G33: ='LOOKUP telda'!AA7 -> 0 | H33: ='LOOKUP telda'!AE7-'LOOKUP telda'!AA7 -> 0 | I33: ='LOOKUP telda'!AF7 -> 3 | J33: ='LOOKUP telda'!J7 -> 0 | K33: ='LOOKUP telda'!K7 -> 0 | L33: ='LOOKUP telda'!L7 -> 0 | M33: ='LOOKUP telda'!P7 -> 0 | N33: ='LOOKUP telda'!X7 -> 0 | O33: ='LOOKUP telda'!Y7 -> 0 | P33: ='LOOKUP telda'!Z7 -> 9 | Q33: =T33 -> 1 | R33: =U33 -> 1 | S33: =VLOOKUP(C33,Sheet3!$A$19:$G$81,7,FALSE) -> 0.66666667 | T33: =IFERROR(P33/(D33-F33-K33-I33),0) -> 1 | U33: =IFERROR(P33/(M33+N33+O33+P33),0) -> 1 | V33: =VLOOKUP(C33,Sheet5!$A$2:$J$270,8,FALSE) -> GIANYAR
C34: JEMBRANA | D34: ='LOOKUP telda'!E8 -> 1 | E34: ='LOOKUP telda'!F8+'LOOKUP telda'!G8+'LOOKUP telda'!H8 -> 0 | F34: ='LOOKUP telda'!I8 -> 0 | G34: ='LOOKUP telda'!AA8 -> 0 | H34: ='LOOKUP telda'!AE8-'LOOKUP telda'!AA8 -> 0 | I34: ='LOOKUP telda'!AF8 -> 0 | J34: ='LOOKUP telda'!J8 -> 0 | K34: ='LOOKUP telda'!K8 -> 0 | L34: ='LOOKUP telda'!L8 -> 0 | M34: ='LOOKUP telda'!P8 -> 0 | N34: ='LOOKUP telda'!X8 -> 0 | O34: ='LOOKUP telda'!Y8 -> 0 | P34: ='LOOKUP telda'!Z8 -> 1 | Q34: =T34 -> 1 | R34: =U34 -> 1 | S34: =VLOOKUP(C34,Sheet3!$A$19:$G$81,7,FALSE) -> 1 | T34: =IFERROR(P34/(D34-F34-K34-I34),0) -> 1 | U34: =IFERROR(P34/(M34+N34+O34+P34),0) -> 1 | V34: =VLOOKUP(C34,Sheet5!$A$2:$J$270,8,FALSE) -> TABANAN
C35: JIMBARAN | D35: ='LOOKUP telda'!E9 -> 15 | E35: ='LOOKUP telda'!F9+'LOOKUP telda'!G9+'LOOKUP telda'!H9 -> 0 | F35: ='LOOKUP telda'!I9 -> 3 | G35: ='LOOKUP telda'!AA9 -> 0 | H35: ='LOOKUP telda'!AE9-'LOOKUP telda'!AA9 -> 0 | I35: ='LOOKUP telda'!AF9 -> 2 | J35: ='LOOKUP telda'!J9 -> 1 | K35: ='LOOKUP telda'!K9 -> 0 | L35: ='LOOKUP telda'!L9 -> 0 | M35: ='LOOKUP telda'!P9 -> 3 | N35: ='LOOKUP telda'!X9 -> 1 | O35: ='LOOKUP telda'!Y9 -> 0 | P35: ='LOOKUP telda'!Z9 -> 5 | Q35: =T35 -> 0.5 | R35: =U35 -> 0.55555556 | S35: =VLOOKUP(C35,Sheet3!$A$19:$G$81,7,FALSE) -> 0.8 | T35: =IFERROR(P35/(D35-F35-K35-I35),0) -> 0.5 | U35: =IFERROR(P35/(M35+N35+O35+P35),0) -> 0.55555556 | V35: =VLOOKUP(C35,Sheet5!$A$2:$J$270,8,FALSE) -> JIMBARAN
C36: KLUNGKUNG | D36: ='LOOKUP telda'!E10 -> 11 | E36: ='LOOKUP telda'!F10+'LOOKUP telda'!G10+'LOOKUP telda'!H10 -> 0 | F36: ='LOOKUP telda'!I10 -> 1 | G36: ='LOOKUP telda'!AA10 -> 0 | H36: ='LOOKUP telda'!AE10-'LOOKUP telda'!AA10 -> 0 | I36: ='LOOKUP telda'!AF10 -> 1 | J36: ='LOOKUP telda'!J10 -> 2 | K36: ='LOOKUP telda'!K10 -> 0 | L36: ='LOOKUP telda'!L10 -> 0 | M36: ='LOOKUP telda'!P10 -> 1 | N36: ='LOOKUP telda'!X10 -> 0 | O36: ='LOOKUP telda'!Y10 -> 0 | P36: ='LOOKUP telda'!Z10 -> 6 | Q36: =T36 -> 0.66666667 | R36: =U36 -> 0.85714286 | S36: =VLOOKUP(C36,Sheet3!$A$19:$G$81,7,FALSE) -> 1 | T36: =IFERROR(P36/(D36-F36-K36-I36),0) -> 0.66666667 | U36: =IFERROR(P36/(M36+N36+O36+P36),0) -> 0.85714286 | V36: =VLOOKUP(C36,Sheet5!$A$2:$J$270,8,FALSE) -> KLUNGKUNG
C37: SANUR | D37: ='LOOKUP telda'!E11 -> 14 | E37: ='LOOKUP telda'!F11+'LOOKUP telda'!G11+'LOOKUP telda'!H11 -> 0 | F37: ='LOOKUP telda'!I11 -> 1 | G37: ='LOOKUP telda'!AA11 -> 0 | H37: ='LOOKUP telda'!AE11-'LOOKUP telda'!AA11 -> 0 | I37: ='LOOKUP telda'!AF11 -> 1 | J37: ='LOOKUP telda'!J11 -> 1 | K37: ='LOOKUP telda'!K11 -> 0 | L37: ='LOOKUP telda'!L11 -> 0 | M37: ='LOOKUP telda'!P11 -> 0 | N37: ='LOOKUP telda'!X11 -> 0 | O37: ='LOOKUP telda'!Y11 -> 1 | P37: ='LOOKUP telda'!Z11 -> 10 | Q37: =T37 -> 0.83333333 | R37: =U37 -> 0.90909091 | S37: =VLOOKUP(C37,Sheet3!$A$19:$G$81,7,FALSE) -> 1 | T37: =IFERROR(P37/(D37-F37-K37-I37),0) -> 0.83333333 | U37: =IFERROR(P37/(M37+N37+O37+P37),0) -> 0.90909091 | V37: =VLOOKUP(C37,Sheet5!$A$2:$J$270,8,FALSE) -> SANUR
C38: SINGARAJA | D38: ='LOOKUP telda'!E12 -> 7 | E38: ='LOOKUP telda'!F12+'LOOKUP telda'!G12+'LOOKUP telda'!H12 -> 0 | F38: ='LOOKUP telda'!I12 -> 0 | G38: ='LOOKUP telda'!AA12 -> 0 | H38: ='LOOKUP telda'!AE12-'LOOKUP telda'!AA12 -> 0 | I38: ='LOOKUP telda'!AF12 -> 1 | J38: ='LOOKUP telda'!J12 -> 0 | K38: ='LOOKUP telda'!K12 -> 0 | L38: ='LOOKUP telda'!L12 -> 0 | M38: ='LOOKUP telda'!P12 -> 1 | N38: ='LOOKUP telda'!X12 -> 0 | O38: ='LOOKUP telda'!Y12 -> 0 | P38: ='LOOKUP telda'!Z12 -> 5 | Q38: =T38 -> 0.83333333 | R38: =U38 -> 0.83333333 | S38: =VLOOKUP(C38,Sheet3!$A$19:$G$81,7,FALSE) -> 1 | T38: =IFERROR(P38/(D38-F38-K38-I38),0) -> 0.83333333 | U38: =IFERROR(P38/(M38+N38+O38+P38),0) -> 0.83333333 | V38: =VLOOKUP(C38,Sheet5!$A$2:$J$270,8,FALSE) -> SINGARAJA
C39: TABANAN | D39: ='LOOKUP telda'!E13 -> 48 | E39: ='LOOKUP telda'!F13+'LOOKUP telda'!G13+'LOOKUP telda'!H13 -> 1 | F39: ='LOOKUP telda'!I13 -> 2 | G39: ='LOOKUP telda'!AA13 -> 0 | H39: ='LOOKUP telda'!AE13-'LOOKUP telda'!AA13 -> 11 | I39: ='LOOKUP telda'!AF13 -> 3 | J39: ='LOOKUP telda'!J13 -> 1 | K39: ='LOOKUP telda'!K13 -> 10 | L39: ='LOOKUP telda'!L13 -> 0 | M39: ='LOOKUP telda'!P13 -> 3 | N39: ='LOOKUP telda'!X13 -> 2 | O39: ='LOOKUP telda'!Y13 -> 0 | P39: ='LOOKUP telda'!Z13 -> 15 | Q39: =T39 -> 0.45454545 | R39: =U39 -> 0.75 | S39: =VLOOKUP(C39,Sheet3!$A$19:$G$81,7,FALSE) -> 0.93333333 | T39: =IFERROR(P39/(D39-F39-K39-I39),0) -> 0.45454545 | U39: =IFERROR(P39/(M39+N39+O39+P39),0) -> 0.75 | V39: =VLOOKUP(C39,Sheet5!$A$2:$J$270,8,FALSE) -> TABANAN
C40: UBUNG | D40: ='LOOKUP telda'!E14 -> 18 | E40: ='LOOKUP telda'!F14+'LOOKUP telda'!G14+'LOOKUP telda'!H14 -> 0 | F40: ='LOOKUP telda'!I14 -> 0 | G40: ='LOOKUP telda'!AA14 -> 1 | H40: ='LOOKUP telda'!AE14-'LOOKUP telda'!AA14 -> 0 | I40: ='LOOKUP telda'!AF14 -> 3 | J40: ='LOOKUP telda'!J14 -> 0 | K40: ='LOOKUP telda'!K14 -> 0 | L40: ='LOOKUP telda'!L14 -> 0 | M40: ='LOOKUP telda'!P14 -> 4 | N40: ='LOOKUP telda'!X14 -> 1 | O40: ='LOOKUP telda'!Y14 -> 0 | P40: ='LOOKUP telda'!Z14 -> 9 | Q40: =T40 -> 0.6 | R40: =U40 -> 0.64285714 | S40: =VLOOKUP(C40,Sheet3!$A$19:$G$81,7,FALSE) -> 1 | T40: =IFERROR(P40/(D40-F40-K40-I40),0) -> 0.6 | U40: =IFERROR(P40/(M40+N40+O40+P40),0) -> 0.64285714 | V40: =VLOOKUP(C40,Sheet5!$A$2:$J$270,8,FALSE) -> UBUNG
B41: JATIM BARAT | C41: BATU | D41: ='LOOKUP telda'!E15 -> 31 | E41: ='LOOKUP telda'!F15+'LOOKUP telda'!G15+'LOOKUP telda'!H15 -> 3 | F41: ='LOOKUP telda'!I15 -> 0 | G41: ='LOOKUP telda'!AA15 -> 0 | H41: ='LOOKUP telda'!AE15-'LOOKUP telda'!AA15 -> 3 | I41: ='LOOKUP telda'!AF15 -> 1 | J41: ='LOOKUP telda'!J15 -> 8 | K41: ='LOOKUP telda'!K15 -> 0 | L41: ='LOOKUP telda'!L15 -> 0 | M41: ='LOOKUP telda'!P15 -> 0 | N41: ='LOOKUP telda'!X15 -> 0 | O41: ='LOOKUP telda'!Y15 -> 0 | P41: ='LOOKUP telda'!Z15 -> 16 | Q41: =T41 -> 0.53333333 | R41: =U41 -> 1 | S41: =VLOOKUP(C41,Sheet3!$A$19:$G$81,7,FALSE) -> 1 | T41: =IFERROR(P41/(D41-F41-K41-I41),0) -> 0.53333333 | U41: =IFERROR(P41/(M41+N41+O41+P41),0) -> 1 | V41: =VLOOKUP(C41,Sheet5!$A$2:$J$270,8,FALSE) -> BATU
C42: BLITAR | D42: ='LOOKUP telda'!E16 -> 12 | E42: ='LOOKUP telda'!F16+'LOOKUP telda'!G16+'LOOKUP telda'!H16 -> 0 | F42: ='LOOKUP telda'!I16 -> 0 | G42: ='LOOKUP telda'!AA16 -> 0 | H42: ='LOOKUP telda'!AE16-'LOOKUP telda'!AA16 -> 0 | I42: ='LOOKUP telda'!AF16 -> 0 | J42: ='LOOKUP telda'!J16 -> 0 | K42: ='LOOKUP telda'!K16 -> 0 | L42: ='LOOKUP telda'!L16 -> 0 | M42: ='LOOKUP telda'!P16 -> 0 | N42: ='LOOKUP telda'!X16 -> 0 | O42: ='LOOKUP telda'!Y16 -> 0 | P42: ='LOOKUP telda'!Z16 -> 12 | Q42: =T42 -> 1 | R42: =U42 -> 1 | S42: =VLOOKUP(C42,Sheet3!$A$19:$G$81,7,FALSE) -> 1 | T42: =IFERROR(P42/(D42-F42-K42-I42),0) -> 1 | U42: =IFERROR(P42/(M42+N42+O42+P42),0) -> 1 | V42: =VLOOKUP(C42,Sheet5!$A$2:$J$270,8,FALSE) -> BLITAR
C43: BOJONEGORO | D43: ='LOOKUP telda'!E17 -> 21 | E43: ='LOOKUP telda'!F17+'LOOKUP telda'!G17+'LOOKUP telda'!H17 -> 0 | F43: ='LOOKUP telda'!I17 -> 1 | G43: ='LOOKUP telda'!AA17 -> 0 | H43: ='LOOKUP telda'!AE17-'LOOKUP telda'!AA17 -> 0 | I43: ='LOOKUP telda'!AF17 -> 3 | J43: ='LOOKUP telda'!J17 -> 0 | K43: ='LOOKUP telda'!K17 -> 0 | L43: ='LOOKUP telda'!L17 -> 0 | M43: ='LOOKUP telda'!P17 -> 0 | N43: ='LOOKUP telda'!X17 -> 0 | O43: ='LOOKUP telda'!Y17 -> 1 | P43: ='LOOKUP telda'!Z17 -> 16 | Q43: =T43 -> 0.94117647 | R43: =U43 -> 0.94117647 | S43: =VLOOKUP(C43,Sheet3!$A$19:$G$81,7,FALSE) -> 1 | T43: =IFERROR(P43/(D43-F43-K43-I43),0) -> 0.94117647 | U43: =IFERROR(P43/(M43+N43+O43+P43),0) -> 0.94117647 | V43: =VLOOKUP(C43,Sheet5!$A$2:$J$270,8,FALSE) -> BOJONEGORO
C44: KEDIRI | D44: ='LOOKUP telda'!E18 -> 33 | E44: ='LOOKUP telda'!F18+'LOOKUP telda'!G18+'LOOKUP telda'!H18 -> 1 | F44: ='LOOKUP telda'!I18 -> 0 | G44: ='LOOKUP telda'!AA18 -> 0 | H44: ='LOOKUP telda'!AE18-'LOOKUP telda'!AA18 -> 1 | I44: ='LOOKUP telda'!AF18 -> 0 | J44: ='LOOKUP telda'!J18 -> 0 | K44: ='LOOKUP telda'!K18 -> 0 | L44: ='LOOKUP telda'!L18 -> 0 | M44: ='LOOKUP telda'!P18 -> 0 | N44: ='LOOKUP telda'!X18 -> 0 | O44: ='LOOKUP telda'!Y18 -> 1 | P44: ='LOOKUP telda'!Z18 -> 30 | Q44: =T44 -> 0.90909091 | R44: =U44 -> 0.96774194 | S44: =VLOOKUP(C44,Sheet3!$A$19:$G$81,7,FALSE) -> 0.93333333 | T44: =IFERROR(P44/(D44-F44-K44-I44),0) -> 0.90909091 | U44: =IFERROR(P44/(M44+N44+O44+P44),0) -> 0.96774194 | V44: =VLOOKUP(C44,Sheet5!$A$2:$J$270,8,FALSE) -> KEDIRI
C45: KEPANJEN | D45: ='LOOKUP telda'!E19 -> 34 | E45: ='LOOKUP telda'!F19+'LOOKUP telda'!G19+'LOOKUP telda'!H19 -> 0 | F45: ='LOOKUP telda'!I19 -> 0 | G45: ='LOOKUP telda'!AA19 -> 0 | H45: ='LOOKUP telda'!AE19-'LOOKUP telda'!AA19 -> 0 | I45: ='LOOKUP telda'!AF19 -> 3 | J45: ='LOOKUP telda'!J19 -> 0 | K45: ='LOOKUP telda'!K19 -> 0 | L45: ='LOOKUP telda'!L19 -> 0 | M45: ='LOOKUP telda'!P19 -> 0 | N45: ='LOOKUP telda'!X19 -> 0 | O45: ='LOOKUP telda'!Y19 -> 0 | P45: ='LOOKUP telda'!Z19 -> 31 | Q45: =T45 -> 1 | R45: =U45 -> 1 | S45: =VLOOKUP(C45,Sheet3!$A$19:$G$81,7,FALSE) -> #N/A | T45: =IFERROR(P45/(D45-F45-K45-I45),0) -> 1 | U45: =IFERROR(P45/(M45+N45+O45+P45),0) -> 1 | V45: =VLOOKUP(C45,Sheet5!$A$2:$J$270,8,FALSE) -> MALANG
C46: MADIUN | D46: ='LOOKUP telda'!E20 -> 8 | E46: ='LOOKUP telda'!F20+'LOOKUP telda'!G20+'LOOKUP telda'!H20 -> 0 | F46: ='LOOKUP telda'!I20 -> 0 | G46: ='LOOKUP telda'!AA20 -> 0 | H46: ='LOOKUP telda'!AE20-'LOOKUP telda'!AA20 -> 0 | I46: ='LOOKUP telda'!AF20 -> 0 | J46: ='LOOKUP telda'!J20 -> 0 | K46: ='LOOKUP telda'!K20 -> 0 | L46: ='LOOKUP telda'!L20 -> 0 | M46: ='LOOKUP telda'!P20 -> 0 | N46: ='LOOKUP telda'!X20 -> 0 | O46: ='LOOKUP telda'!Y20 -> 0 | P46: ='LOOKUP telda'!Z20 -> 7 | Q46: =T46 -> 0.875 | R46: =U46 -> 1 | S46: =VLOOKUP(C46,Sheet3!$A$19:$G$81,7,FALSE) -> 1 | T46: =IFERROR(P46/(D46-F46-K46-I46),0) -> 0.875 | U46: =IFERROR(P46/(M46+N46+O46+P46),0) -> 1 | V46: =VLOOKUP(C46,Sheet5!$A$2:$J$270,8,FALSE) -> MADIUN
C47: NGANJUK | D47: ='LOOKUP telda'!E21 -> 20 | E47: ='LOOKUP telda'!F21+'LOOKUP telda'!G21+'LOOKUP telda'!H21 -> 0 | F47: ='LOOKUP telda'!I21 -> 0 | G47: ='LOOKUP telda'!AA21 -> 0 | H47: ='LOOKUP telda'!AE21-'LOOKUP telda'!AA21 -> 1 | I47: ='LOOKUP telda'!AF21 -> 2 | J47: ='LOOKUP telda'!J21 -> 1 | K47: ='LOOKUP telda'!K21 -> 5 | L47: ='LOOKUP telda'!L21 -> 0 | M47: ='LOOKUP telda'!P21 -> 1 | N47: ='LOOKUP telda'!X21 -> 0 | O47: ='LOOKUP telda'!Y21 -> 1 | P47: ='LOOKUP telda'!Z21 -> 9 | Q47: =T47 -> 0.69230769 | R47: =U47 -> 0.81818182 | S47: =VLOOKUP(C47,Sheet3!$A$19:$G$81,7,FALSE) -> 1 | T47: =IFERROR(P47/(D47-F47-K47-I47),0) -> 0.69230769 | U47: =IFERROR(P47/(M47+N47+O47+P47),0) -> 0.81818182 | V47: =VLOOKUP(C47,Sheet5!$A$2:$J$270,8,FALSE) -> NGANJUK
C48: NGAWI | D48: ='LOOKUP telda'!E22 -> 8 | E48: ='LOOKUP telda'!F22+'LOOKUP telda'!G22+'LOOKUP telda'!H22 -> 0 | F48: ='LOOKUP telda'!I22 -> 0 | G48: ='LOOKUP telda'!AA22 -> 0 | H48: ='LOOKUP telda'!AE22-'LOOKUP telda'!AA22 -> 0 | I48: ='LOOKUP telda'!AF22 -> 0 | J48: ='LOOKUP telda'!J22 -> 1 | K48: ='LOOKUP telda'!K22 -> 0 | L48: ='LOOKUP telda'!L22 -> 0 | M48: ='LOOKUP telda'!P22 -> 0 | N48: ='LOOKUP telda'!X22 -> 1 | O48: ='LOOKUP telda'!Y22 -> 0 | P48: ='LOOKUP telda'!Z22 -> 6 | Q48: =T48 -> 0.75 | R48: =U48 -> 0.85714286 | S48: =VLOOKUP(C48,Sheet3!$A$19:$G$81,7,FALSE) -> #N/A | T48: =IFERROR(P48/(D48-F48-K48-I48),0) -> 0.75 | U48: =IFERROR(P48/(M48+N48+O48+P48),0) -> 0.85714286 | V48: =VLOOKUP(C48,Sheet5!$A$2:$J$270,8,FALSE) -> MADIUN
C49: PONOROGO | D49: ='LOOKUP telda'!E23 -> 21 | E49: ='LOOKUP telda'!F23+'LOOKUP telda'!G23+'LOOKUP telda'!H23 -> 0 | F49: ='LOOKUP telda'!I23 -> 0 | G49: ='LOOKUP telda'!AA23 -> 0 | H49: ='LOOKUP telda'!AE23-'LOOKUP telda'!AA23 -> 1 | I49: ='LOOKUP telda'!AF23 -> 2 | J49: ='LOOKUP telda'!J23 -> 2 | K49: ='LOOKUP telda'!K23 -> 1 | L49: ='LOOKUP telda'!L23 -> 0 | M49: ='LOOKUP telda'!P23 -> 0 | N49: ='LOOKUP telda'!X23 -> 0 | O49: ='LOOKUP telda'!Y23 -> 0 | P49: ='LOOKUP telda'!Z23 -> 15 | Q49: =T49 -> 0.83333333 | R49: =U49 -> 1 | S49: =VLOOKUP(C49,Sheet3!$A$19:$G$81,7,FALSE) -> 0.95238095 | T49: =IFERROR(P49/(D49-F49-K49-I49),0) -> 0.83333333 | U49: =IFERROR(P49/(M49+N49+O49+P49),0) -> 1 | V49: =VLOOKUP(C49,Sheet5!$A$2:$J$270,8,FALSE) -> PONOROGO
C50: TRENGGALEK | D50: ='LOOKUP telda'!E24 -> 8 | E50: ='LOOKUP telda'!F24+'LOOKUP telda'!G24+'LOOKUP telda'!H24 -> 0 | F50: ='LOOKUP telda'!I24 -> 0 | G50: ='LOOKUP telda'!AA24 -> 2 | H50: ='LOOKUP telda'!AE24-'LOOKUP telda'!AA24 -> 0 | I50: ='LOOKUP telda'!AF24 -> 0 | J50: ='LOOKUP telda'!J24 -> 0 | K50: ='LOOKUP telda'!K24 -> 0 | L50: ='LOOKUP telda'!L24 -> 0 | M50: ='LOOKUP telda'!P24 -> 0 | N50: ='LOOKUP telda'!X24 -> 0 | O50: ='LOOKUP telda'!Y24 -> 0 | P50: ='LOOKUP telda'!Z24 -> 6 | Q50: =T50 -> 0.75 | R50: =U50 -> 1 | S50: =VLOOKUP(C50,Sheet3!$A$19:$G$81,7,FALSE) -> #N/A | T50: =IFERROR(P50/(D50-F50-K50-I50),0) -> 0.75 | U50: =IFERROR(P50/(M50+N50+O50+P50),0) -> 1 | V50: =VLOOKUP(C50,Sheet5!$A$2:$J$270,8,FALSE) -> PONOROGO
C51: TUBAN | D51: ='LOOKUP telda'!E25 -> 22 | E51: ='LOOKUP telda'!F25+'LOOKUP telda'!G25+'LOOKUP telda'!H25 -> 1 | F51: ='LOOKUP telda'!I25 -> 2 | G51: ='LOOKUP telda'!AA25 -> 1 | H51: ='LOOKUP telda'!AE25-'LOOKUP telda'!AA25 -> 1 | I51: ='LOOKUP telda'!AF25 -> 2 | J51: ='LOOKUP telda'!J25 -> 0 | K51: ='LOOKUP telda'!K25 -> 2 | L51: ='LOOKUP telda'!L25 -> 0 | M51: ='LOOKUP telda'!P25 -> 0 | N51: ='LOOKUP telda'!X25 -> 0 | O51: ='LOOKUP telda'!Y25 -> 0 | P51: ='LOOKUP telda'!Z25 -> 13 | Q51: =T51 -> 0.8125 | R51: =U51 -> 1 | S51: =VLOOKUP(C51,Sheet3!$A$19:$G$81,7,FALSE) -> #N/A | T51: =IFERROR(P51/(D51-F51-K51-I51),0) -> 0.8125 | U51: =IFERROR(P51/(M51+N51+O51+P51),0) -> 1 | V51: =VLOOKUP(C51,Sheet5!$A$2:$J$270,8,FALSE) -> BOJONEGORO
C52: TULUNGAGUNG | D52: ='LOOKUP telda'!E26 -> 13 | E52: ='LOOKUP telda'!F26+'LOOKUP telda'!G26+'LOOKUP telda'!H26 -> 0 | F52: ='LOOKUP telda'!I26 -> 2 | G52: ='LOOKUP telda'!AA26 -> 0 | H52: ='LOOKUP telda'!AE26-'LOOKUP telda'!AA26 -> 1 | I52: ='LOOKUP telda'!AF26 -> 0 | J52: ='LOOKUP telda'!J26 -> 2 | K52: ='LOOKUP telda'!K26 -> 0 | L52: ='LOOKUP telda'!L26 -> 0 | M52: ='LOOKUP telda'!P26 -> 0 | N52: ='LOOKUP telda'!X26 -> 0 | O52: ='LOOKUP telda'!Y26 -> 0 | P52: ='LOOKUP telda'!Z26 -> 8 | Q52: =T52 -> 0.72727273 | R52: =U52 -> 1 | S52: =VLOOKUP(C52,Sheet3!$A$19:$G$81,7,FALSE) -> #N/A | T52: =IFERROR(P52/(D52-F52-K52-I52),0) -> 0.72727273 | U52: =IFERROR(P52/(M52+N52+O52+P52),0) -> 1 | V52: =VLOOKUP(C52,Sheet5!$A$2:$J$270,8,FALSE) -> BLITAR
B53: JATIM TIMUR | C53: BANYUWANGI | D53: ='LOOKUP telda'!E27 -> 18 | E53: ='LOOKUP telda'!F27+'LOOKUP telda'!G27+'LOOKUP telda'!H27 -> 0 | F53: ='LOOKUP telda'!I27 -> 0 | G53: ='LOOKUP telda'!AA27 -> 1 | H53: ='LOOKUP telda'!AE27-'LOOKUP telda'!AA27 -> 2 | I53: ='LOOKUP telda'!AF27 -> 0 | J53: ='LOOKUP telda'!J27 -> 2 | K53: ='LOOKUP telda'!K27 -> 0 | L53: ='LOOKUP telda'!L27 -> 0 | M53: ='LOOKUP telda'!P27 -> 0 | N53: ='LOOKUP telda'!X27 -> 0 | O53: ='LOOKUP telda'!Y27 -> 0 | P53: ='LOOKUP telda'!Z27 -> 13 | Q53: =T53 -> 0.72222222 | R53: =U53 -> 1 | S53: =VLOOKUP(C53,Sheet3!$A$19:$G$81,7,FALSE) -> 1 | T53: =IFERROR(P53/(D53-F53-K53-I53),0) -> 0.72222222 | U53: =IFERROR(P53/(M53+N53+O53+P53),0) -> 1 | V53: =VLOOKUP(C53,Sheet5!$A$2:$J$270,8,FALSE) -> BANYUWANGI
C54: BONDOWOSO | D54: ='LOOKUP telda'!E28 -> 12 | E54: ='LOOKUP telda'!F28+'LOOKUP telda'!G28+'LOOKUP telda'!H28 -> 0 | F54: ='LOOKUP telda'!I28 -> 0 | G54: ='LOOKUP telda'!AA28 -> 0 | H54: ='LOOKUP telda'!AE28-'LOOKUP telda'!AA28 -> 1 | I54: ='LOOKUP telda'!AF28 -> 0 | J54: ='LOOKUP telda'!J28 -> 0 | K54: ='LOOKUP telda'!K28 -> 0 | L54: ='LOOKUP telda'!L28 -> 0 | M54: ='LOOKUP telda'!P28 -> 0 | N54: ='LOOKUP telda'!X28 -> 0 | O54: ='LOOKUP telda'!Y28 -> 0 | P54: ='LOOKUP telda'!Z28 -> 11 | Q54: =T54 -> 0.91666667 | R54: =U54 -> 1 | S54: =VLOOKUP(C54,Sheet3!$A$19:$G$81,7,FALSE) -> #N/A | T54: =IFERROR(P54/(D54-F54-K54-I54),0) -> 0.91666667 | U54: =IFERROR(P54/(M54+N54+O54+P54),0) -> 1 | V54: =VLOOKUP(C54,Sheet5!$A$2:$J$270,8,FALSE) -> JEMBER
C55: INNER - JATIM TIMUR | D55: ='LOOKUP telda'!E29 -> 32 | E55: ='LOOKUP telda'!F29+'LOOKUP telda'!G29+'LOOKUP telda'!H29 -> 0 | F55: ='LOOKUP telda'!I29 -> 0 | G55: ='LOOKUP telda'!AA29 -> 1 | H55: ='LOOKUP telda'!AE29-'LOOKUP telda'!AA29 -> 2 | I55: ='LOOKUP telda'!AF29 -> 3 | J55: ='LOOKUP telda'!J29 -> 0 | K55: ='LOOKUP telda'!K29 -> 1 | L55: ='LOOKUP telda'!L29 -> 0 | M55: ='LOOKUP telda'!P29 -> 0 | N55: ='LOOKUP telda'!X29 -> 0 | O55: ='LOOKUP telda'!Y29 -> 1 | P55: ='LOOKUP telda'!Z29 -> 24 | Q55: =T55 -> 0.85714286 | R55: =U55 -> 0.96 | S55: =VLOOKUP(C55,Sheet3!$A$19:$G$81,7,FALSE) -> #N/A | T55: =IFERROR(P55/(D55-F55-K55-I55),0) -> 0.85714286 | U55: =IFERROR(P55/(M55+N55+O55+P55),0) -> 0.96 | V55: =VLOOKUP(C55,Sheet5!$A$2:$J$270,8,FALSE) -> SIDOARJO
C56: JEMBER | D56: ='LOOKUP telda'!E30 -> 10 | E56: ='LOOKUP telda'!F30+'LOOKUP telda'!G30+'LOOKUP telda'!H30 -> 0 | F56: ='LOOKUP telda'!I30 -> 0 | G56: ='LOOKUP telda'!AA30 -> 0 | H56: ='LOOKUP telda'!AE30-'LOOKUP telda'!AA30 -> 0 | I56: ='LOOKUP telda'!AF30 -> 0 | J56: ='LOOKUP telda'!J30 -> 0 | K56: ='LOOKUP telda'!K30 -> 0 | L56: ='LOOKUP telda'!L30 -> 0 | M56: ='LOOKUP telda'!P30 -> 0 | N56: ='LOOKUP telda'!X30 -> 0 | O56: ='LOOKUP telda'!Y30 -> 1 | P56: ='LOOKUP telda'!Z30 -> 9 | Q56: =T56 -> 0.9 | R56: =U56 -> 0.9 | S56: =VLOOKUP(C56,Sheet3!$A$19:$G$81,7,FALSE) -> 1 | T56: =IFERROR(P56/(D56-F56-K56-I56),0) -> 0.9 | U56: =IFERROR(P56/(M56+N56+O56+P56),0) -> 0.9 | V56: =VLOOKUP(C56,Sheet5!$A$2:$J$270,8,FALSE) -> JEMBER
C57: JOMBANG | D57: ='LOOKUP telda'!E31 -> 21 | E57: ='LOOKUP telda'!F31+'LOOKUP telda'!G31+'LOOKUP telda'!H31 -> 0 | F57: ='LOOKUP telda'!I31 -> 0 | G57: ='LOOKUP telda'!AA31 -> 0 | H57: ='LOOKUP telda'!AE31-'LOOKUP telda'!AA31 -> 1 | I57: ='LOOKUP telda'!AF31 -> 3 | J57: ='LOOKUP telda'!J31 -> 0 | K57: ='LOOKUP telda'!K31 -> 1 | L57: ='LOOKUP telda'!L31 -> 0 | M57: ='LOOKUP telda'!P31 -> 0 | N57: ='LOOKUP telda'!X31 -> 0 | O57: ='LOOKUP telda'!Y31 -> 2 | P57: ='LOOKUP telda'!Z31 -> 14 | Q57: =T57 -> 0.82352941 | R57: =U57 -> 0.875 | S57: =VLOOKUP(C57,Sheet3!$A$19:$G$81,7,FALSE) -> #N/A | T57: =IFERROR(P57/(D57-F57-K57-I57),0) -> 0.82352941 | U57: =IFERROR(P57/(M57+N57+O57+P57),0) -> 0.875 | V57: =VLOOKUP(C57,Sheet5!$A$2:$J$270,8,FALSE) -> MOJOKERTO
C58: LUMAJANG | D58: ='LOOKUP telda'!E32 -> 8 | E58: ='LOOKUP telda'!F32+'LOOKUP telda'!G32+'LOOKUP telda'!H32 -> 0 | F58: ='LOOKUP telda'!I32 -> 0 | G58: ='LOOKUP telda'!AA32 -> 0 | H58: ='LOOKUP telda'!AE32-'LOOKUP telda'!AA32 -> 0 | I58: ='LOOKUP telda'!AF32 -> 0 | J58: ='LOOKUP telda'!J32 -> 0 | K58: ='LOOKUP telda'!K32 -> 0 | L58: ='LOOKUP telda'!L32 -> 0 | M58: ='LOOKUP telda'!P32 -> 0 | N58: ='LOOKUP telda'!X32 -> 2 | O58: ='LOOKUP telda'!Y32 -> 0 | P58: ='LOOKUP telda'!Z32 -> 6 | Q58: =T58 -> 0.75 | R58: =U58 -> 0.75 | S58: =VLOOKUP(C58,Sheet3!$A$19:$G$81,7,FALSE) -> #N/A | T58: =IFERROR(P58/(D58-F58-K58-I58),0) -> 0.75 | U58: =IFERROR(P58/(M58+N58+O58+P58),0) -> 0.75 | V58: =VLOOKUP(C58,Sheet5!$A$2:$J$270,8,FALSE) -> PROBOLINGGO
C59: MOJOKERTO | D59: ='LOOKUP telda'!E33 -> 30 | E59: ='LOOKUP telda'!F33+'LOOKUP telda'!G33+'LOOKUP telda'!H33 -> 2 | F59: ='LOOKUP telda'!I33 -> 1 | G59: ='LOOKUP telda'!AA33 -> 0 | H59: ='LOOKUP telda'!AE33-'LOOKUP telda'!AA33 -> 0 | I59: ='LOOKUP telda'!AF33 -> 3 | J59: ='LOOKUP telda'!J33 -> 2 | K59: ='LOOKUP telda'!K33 -> 0 | L59: ='LOOKUP telda'!L33 -> 0 | M59: ='LOOKUP telda'!P33 -> 0 | N59: ='LOOKUP telda'!X33 -> 0 | O59: ='LOOKUP telda'!Y33 -> 0 | P59: ='LOOKUP telda'!Z33 -> 22 | Q59: =T59 -> 0.84615385 | R59: =U59 -> 1 | S59: =VLOOKUP(C59,Sheet3!$A$19:$G$81,7,FALSE) -> 1 | T59: =IFERROR(P59/(D59-F59-K59-I59),0) -> 0.84615385 | U59: =IFERROR(P59/(M59+N59+O59+P59),0) -> 1 | V59: =VLOOKUP(C59,Sheet5!$A$2:$J$270,8,FALSE) -> MOJOKERTO
C60: PASURUAN | D60: ='LOOKUP telda'!E34 -> 23 | E60: ='LOOKUP telda'!F34+'LOOKUP telda'!G34+'LOOKUP telda'!H34 -> 2 | F60: ='LOOKUP telda'!I34 -> 1 | G60: ='LOOKUP telda'!AA34 -> 2 | H60: ='LOOKUP telda'!AE34-'LOOKUP telda'!AA34 -> 2 | I60: ='LOOKUP telda'!AF34 -> 0 | J60: ='LOOKUP telda'!J34 -> 0 | K60: ='LOOKUP telda'!K34 -> 0 | L60: ='LOOKUP telda'!L34 -> 0 | M60: ='LOOKUP telda'!P34 -> 0 | N60: ='LOOKUP telda'!X34 -> 0 | O60: ='LOOKUP telda'!Y34 -> 0 | P60: ='LOOKUP telda'!Z34 -> 16 | Q60: =T60 -> 0.72727273 | R60: =U60 -> 1 | S60: =VLOOKUP(C60,Sheet3!$A$19:$G$81,7,FALSE) -> 1 | T60: =IFERROR(P60/(D60-F60-K60-I60),0) -> 0.72727273 | U60: =IFERROR(P60/(M60+N60+O60+P60),0) -> 1 | V60: =VLOOKUP(C60,Sheet5!$A$2:$J$270,8,FALSE) -> PASURUAN
C61: PROBOLINGGO | D61: ='LOOKUP telda'!E35 -> 16 | E61: ='LOOKUP telda'!F35+'LOOKUP telda'!G35+'LOOKUP telda'!H35 -> 0 | F61: ='LOOKUP telda'!I35 -> 0 | G61: ='LOOKUP telda'!AA35 -> 1 | H61: ='LOOKUP telda'!AE35-'LOOKUP telda'!AA35 -> 0 | I61: ='LOOKUP telda'!AF35 -> 0 | J61: ='LOOKUP telda'!J35 -> 1 | K61: ='LOOKUP telda'!K35 -> 0 | L61: ='LOOKUP telda'!L35 -> 0 | M61: ='LOOKUP telda'!P35 -> 1 | N61: ='LOOKUP telda'!X35 -> 0 | O61: ='LOOKUP telda'!Y35 -> 1 | P61: ='LOOKUP telda'!Z35 -> 12 | Q61: =T61 -> 0.75 | R61: =U61 -> 0.85714286 | S61: =VLOOKUP(C61,Sheet3!$A$19:$G$81,7,FALSE) -> 1 | T61: =IFERROR(P61/(D61-F61-K61-I61),0) -> 0.75 | U61: =IFERROR(P61/(M61+N61+O61+P61),0) -> 0.85714286 | V61: =VLOOKUP(C61,Sheet5!$A$2:$J$270,8,FALSE) -> PROBOLINGGO
C62: SITUBONDO | D62: ='LOOKUP telda'!E36 -> 3 | E62: ='LOOKUP telda'!F36+'LOOKUP telda'!G36+'LOOKUP telda'!H36 -> 0 | F62: ='LOOKUP telda'!I36 -> 0 | G62: ='LOOKUP telda'!AA36 -> 0 | H62: ='LOOKUP telda'!AE36-'LOOKUP telda'!AA36 -> 0 | I62: ='LOOKUP telda'!AF36 -> 0 | J62: ='LOOKUP telda'!J36 -> 0 | K62: ='LOOKUP telda'!K36 -> 0 | L62: ='LOOKUP telda'!L36 -> 0 | M62: ='LOOKUP telda'!P36 -> 0 | N62: ='LOOKUP telda'!X36 -> 0 | O62: ='LOOKUP telda'!Y36 -> 0 | P62: ='LOOKUP telda'!Z36 -> 3 | Q62: =T62 -> 1 | R62: =U62 -> 1 | S62: =VLOOKUP(C62,Sheet3!$A$19:$G$81,7,FALSE) -> #N/A | T62: =IFERROR(P62/(D62-F62-K62-I62),0) -> 1 | U62: =IFERROR(P62/(M62+N62+O62+P62),0) -> 1 | V62: =VLOOKUP(C62,Sheet5!$A$2:$J$270,8,FALSE) -> BANYUWANGI
B63: NUSRA | C63: ATAMBUA | D63: ='LOOKUP telda'!E37 -> 2 | E63: ='LOOKUP telda'!F37+'LOOKUP telda'!G37+'LOOKUP telda'!H37 -> 1 | F63: ='LOOKUP telda'!I37 -> 0 | G63: ='LOOKUP telda'!AA37 -> 0 | H63: ='LOOKUP telda'!AE37-'LOOKUP telda'!AA37 -> 0 | I63: ='LOOKUP telda'!AF37 -> 0 | J63: ='LOOKUP telda'!J37 -> 0 | K63: ='LOOKUP telda'!K37 -> 0 | L63: ='LOOKUP telda'!L37 -> 0 | M63: ='LOOKUP telda'!P37 -> 0 | N63: ='LOOKUP telda'!X37 -> 0 | O63: ='LOOKUP telda'!Y37 -> 0 | P63: ='LOOKUP telda'!Z37 -> 1 | Q63: =T63 -> 0.5 | R63: =U63 -> 1 | S63: =VLOOKUP(C63,Sheet3!$A$19:$G$81,7,FALSE) -> 1 | T63: =IFERROR(P63/(D63-F63-K63-I63),0) -> 0.5 | U63: =IFERROR(P63/(M63+N63+O63+P63),0) -> 1 | V63: =VLOOKUP(C63,Sheet5!$A$2:$J$270,8,FALSE) -> ATAMBUA
C64: BIMA | D64: ='LOOKUP telda'!E38 -> 18 | E64: ='LOOKUP telda'!F38+'LOOKUP telda'!G38+'LOOKUP telda'!H38 -> 0 | F64: ='LOOKUP telda'!I38 -> 0 | G64: ='LOOKUP telda'!AA38 -> 0 | H64: ='LOOKUP telda'!AE38-'LOOKUP telda'!AA38 -> 0 | I64: ='LOOKUP telda'!AF38 -> 5 | J64: ='LOOKUP telda'!J38 -> 0 | K64: ='LOOKUP telda'!K38 -> 0 | L64: ='LOOKUP telda'!L38 -> 1 | M64: ='LOOKUP telda'!P38 -> 1 | N64: ='LOOKUP telda'!X38 -> 1 | O64: ='LOOKUP telda'!Y38 -> 1 | P64: ='LOOKUP telda'!Z38 -> 9 | Q64: =T64 -> 0.69230769 | R64: =U64 -> 0.75 | S64: =VLOOKUP(C64,Sheet3!$A$19:$G$81,7,FALSE) -> 0.55555556 | T64: =IFERROR(P64/(D64-F64-K64-I64),0) -> 0.69230769 | U64: =IFERROR(P64/(M64+N64+O64+P64),0) -> 0.75 | V64: =VLOOKUP(C64,Sheet5!$A$2:$J$270,8,FALSE) -> BIMA
C65: ENDE | D65: ='LOOKUP telda'!E39 -> 14 | E65: ='LOOKUP telda'!F39+'LOOKUP telda'!G39+'LOOKUP telda'!H39 -> 0 | F65: ='LOOKUP telda'!I39 -> 0 | G65: ='LOOKUP telda'!AA39 -> 0 | H65: ='LOOKUP telda'!AE39-'LOOKUP telda'!AA39 -> 0 | I65: ='LOOKUP telda'!AF39 -> 0 | J65: ='LOOKUP telda'!J39 -> 0 | K65: ='LOOKUP telda'!K39 -> 0 | L65: ='LOOKUP telda'!L39 -> 0 | M65: ='LOOKUP telda'!P39 -> 2 | N65: ='LOOKUP telda'!X39 -> 0 | O65: ='LOOKUP telda'!Y39 -> 0 | P65: ='LOOKUP telda'!Z39 -> 12 | Q65: =T65 -> 0.85714286 | R65: =U65 -> 0.85714286 | S65: =VLOOKUP(C65,Sheet3!$A$19:$G$81,7,FALSE) -> 0.75 | T65: =IFERROR(P65/(D65-F65-K65-I65),0) -> 0.85714286 | U65: =IFERROR(P65/(M65+N65+O65+P65),0) -> 0.85714286 | V65: =VLOOKUP(C65,Sheet5!$A$2:$J$270,8,FALSE) -> ENDE
C66: INNER - NUSA TENGGARA | D66: ='LOOKUP telda'!E40 -> 26 | E66: ='LOOKUP telda'!F40+'LOOKUP telda'!G40+'LOOKUP telda'!H40 -> 0 | F66: ='LOOKUP telda'!I40 -> 0 | G66: ='LOOKUP telda'!AA40 -> 1 | H66: ='LOOKUP telda'!AE40-'LOOKUP telda'!AA40 -> 0 | I66: ='LOOKUP telda'!AF40 -> 6 | J66: ='LOOKUP telda'!J40 -> 0 | K66: ='LOOKUP telda'!K40 -> 0 | L66: ='LOOKUP telda'!L40 -> 0 | M66: ='LOOKUP telda'!P40 -> 3 | N66: ='LOOKUP telda'!X40 -> 0 | O66: ='LOOKUP telda'!Y40 -> 0 | P66: ='LOOKUP telda'!Z40 -> 16 | Q66: =T66 -> 0.8 | R66: =U66 -> 0.84210526 | S66: =VLOOKUP(C66,Sheet3!$A$19:$G$81,7,FALSE) -> #N/A | T66: =IFERROR(P66/(D66-F66-K66-I66),0) -> 0.8 | U66: =IFERROR(P66/(M66+N66+O66+P66),0) -> 0.84210526 | V66: =VLOOKUP(C66,Sheet5!$A$2:$J$270,8,FALSE) -> MATARAM
C67: KUPANG | D67: ='LOOKUP telda'!E41 -> 24 | E67: ='LOOKUP telda'!F41+'LOOKUP telda'!G41+'LOOKUP telda'!H41 -> 0 | F67: ='LOOKUP telda'!I41 -> 1 | G67: ='LOOKUP telda'!AA41 -> 0 | H67: ='LOOKUP telda'!AE41-'LOOKUP telda'!AA41 -> 3 | I67: ='LOOKUP telda'!AF41 -> 0 | J67: ='LOOKUP telda'!J41 -> 2 | K67: ='LOOKUP telda'!K41 -> 2 | L67: ='LOOKUP telda'!L41 -> 0 | M67: ='LOOKUP telda'!P41 -> 6 | N67: ='LOOKUP telda'!X41 -> 0 | O67: ='LOOKUP telda'!Y41 -> 1 | P67: ='LOOKUP telda'!Z41 -> 10 | Q67: =T67 -> 0.47619048 | R67: =U67 -> 0.58823529 | S67: =VLOOKUP(C67,Sheet3!$A$19:$G$81,7,FALSE) -> 0.2 | T67: =IFERROR(P67/(D67-F67-K67-I67),0) -> 0.47619048 | U67: =IFERROR(P67/(M67+N67+O67+P67),0) -> 0.58823529 | V67: =VLOOKUP(C67,Sheet5!$A$2:$J$270,8,FALSE) -> KUPANG
C68: LABOAN BAJO | D68: ='LOOKUP telda'!E42 -> 9 | E68: ='LOOKUP telda'!F42+'LOOKUP telda'!G42+'LOOKUP telda'!H42 -> 0 | F68: ='LOOKUP telda'!I42 -> 0 | G68: ='LOOKUP telda'!AA42 -> 0 | H68: ='LOOKUP telda'!AE42-'LOOKUP telda'!AA42 -> 0 | I68: ='LOOKUP telda'!AF42 -> 0 | J68: ='LOOKUP telda'!J42 -> 0 | K68: ='LOOKUP telda'!K42 -> 2 | L68: ='LOOKUP telda'!L42 -> 0 | M68: ='LOOKUP telda'!P42 -> 1 | N68: ='LOOKUP telda'!X42 -> 0 | O68: ='LOOKUP telda'!Y42 -> 0 | P68: ='LOOKUP telda'!Z42 -> 6 | Q68: =T68 -> 0.85714286 | R68: =U68 -> 0.85714286 | S68: =VLOOKUP(C68,Sheet3!$A$19:$G$81,7,FALSE) -> 0.66666667 | T68: =IFERROR(P68/(D68-F68-K68-I68),0) -> 0.85714286 | U68: =IFERROR(P68/(M68+N68+O68+P68),0) -> 0.85714286 | V68: =VLOOKUP(C68,Sheet5!$A$2:$J$270,8,FALSE) -> LABOAN BAJO
C69: LOMBOK BARAT TENGAH | D69: ='LOOKUP telda'!E43 -> 32 | E69: ='LOOKUP telda'!F43+'LOOKUP telda'!G43+'LOOKUP telda'!H43 -> 1 | F69: ='LOOKUP telda'!I43 -> 1 | G69: ='LOOKUP telda'!AA43 -> 0 | H69: ='LOOKUP telda'!AE43-'LOOKUP telda'!AA43 -> 0 | I69: ='LOOKUP telda'!AF43 -> 4 | J69: ='LOOKUP telda'!J43 -> 2 | K69: ='LOOKUP telda'!K43 -> 1 | L69: ='LOOKUP telda'!L43 -> 0 | M69: ='LOOKUP telda'!P43 -> 2 | N69: ='LOOKUP telda'!X43 -> 2 | O69: ='LOOKUP telda'!Y43 -> 0 | P69: ='LOOKUP telda'!Z43 -> 19 | Q69: =T69 -> 0.73076923 | R69: =U69 -> 0.82608696 | S69: =VLOOKUP(C69,Sheet3!$A$19:$G$81,7,FALSE) -> #N/A | T69: =IFERROR(P69/(D69-F69-K69-I69),0) -> 0.73076923 | U69: =IFERROR(P69/(M69+N69+O69+P69),0) -> 0.82608696 | V69: =VLOOKUP(C69,Sheet5!$A$2:$J$270,8,FALSE) -> SELONG
C70: LOMBOK TIMUR UTARA | D70: ='LOOKUP telda'!E44 -> 32 | E70: ='LOOKUP telda'!F44+'LOOKUP telda'!G44+'LOOKUP telda'!H44 -> 1 | F70: ='LOOKUP telda'!I44 -> 1 | G70: ='LOOKUP telda'!AA44 -> 0 | H70: ='LOOKUP telda'!AE44-'LOOKUP telda'!AA44 -> 0 | I70: ='LOOKUP telda'!AF44 -> 6 | J70: ='LOOKUP telda'!J44 -> 2 | K70: ='LOOKUP telda'!K44 -> 0 | L70: ='LOOKUP telda'!L44 -> 0 | M70: ='LOOKUP telda'!P44 -> 1 | N70: ='LOOKUP telda'!X44 -> 1 | O70: ='LOOKUP telda'!Y44 -> 1 | P70: ='LOOKUP telda'!Z44 -> 19 | Q70: =T70 -> 0.76 | R70: =U70 -> 0.86363636 | S70: =VLOOKUP(C70,Sheet3!$A$19:$G$81,7,FALSE) -> #N/A | T70: =IFERROR(P70/(D70-F70-K70-I70),0) -> 0.76 | U70: =IFERROR(P70/(M70+N70+O70+P70),0) -> 0.86363636 | V70: =VLOOKUP(C70,Sheet5!$A$2:$J$270,8,FALSE) -> SELONG
C71: MAUMERE | D71: ='LOOKUP telda'!E45 -> 8 | E71: ='LOOKUP telda'!F45+'LOOKUP telda'!G45+'LOOKUP telda'!H45 -> 0 | F71: ='LOOKUP telda'!I45 -> 0 | G71: ='LOOKUP telda'!AA45 -> 0 | H71: ='LOOKUP telda'!AE45-'LOOKUP telda'!AA45 -> 0 | I71: ='LOOKUP telda'!AF45 -> 0 | J71: ='LOOKUP telda'!J45 -> 0 | K71: ='LOOKUP telda'!K45 -> 0 | L71: ='LOOKUP telda'!L45 -> 0 | M71: ='LOOKUP telda'!P45 -> 2 | N71: ='LOOKUP telda'!X45 -> 0 | O71: ='LOOKUP telda'!Y45 -> 2 | P71: ='LOOKUP telda'!Z45 -> 4 | Q71: =T71 -> 0.5 | R71: =U71 -> 0.5 | S71: =VLOOKUP(C71,Sheet3!$A$19:$G$81,7,FALSE) -> 0.25 | T71: =IFERROR(P71/(D71-F71-K71-I71),0) -> 0.5 | U71: =IFERROR(P71/(M71+N71+O71+P71),0) -> 0.5 | V71: =VLOOKUP(C71,Sheet5!$A$2:$J$270,8,FALSE) -> MAUMERE
C72: SUMBAWA | D72: ='LOOKUP telda'!E46 -> 38 | E72: ='LOOKUP telda'!F46+'LOOKUP telda'!G46+'LOOKUP telda'!H46 -> 3 | F72: ='LOOKUP telda'!I46 -> 0 | G72: ='LOOKUP telda'!AA46 -> 0 | H72: ='LOOKUP telda'!AE46-'LOOKUP telda'!AA46 -> 0 | I72: ='LOOKUP telda'!AF46 -> 10 | J72: ='LOOKUP telda'!J46 -> 3 | K72: ='LOOKUP telda'!K46 -> 0 | L72: ='LOOKUP telda'!L46 -> 0 | M72: ='LOOKUP telda'!P46 -> 1 | N72: ='LOOKUP telda'!X46 -> 1 | O72: ='LOOKUP telda'!Y46 -> 0 | P72: ='LOOKUP telda'!Z46 -> 20 | Q72: =T72 -> 0.71428571 | R72: =U72 -> 0.90909091 | S72: =VLOOKUP(C72,Sheet3!$A$19:$G$81,7,FALSE) -> 0.9 | T72: =IFERROR(P72/(D72-F72-K72-I72),0) -> 0.71428571 | U72: =IFERROR(P72/(M72+N72+O72+P72),0) -> 0.90909091 | V72: =VLOOKUP(C72,Sheet5!$A$2:$J$270,8,FALSE) -> SUMBAWA
C73: WAIKABUBAK | D73: ='LOOKUP telda'!E47 -> 2 | E73: ='LOOKUP telda'!F47+'LOOKUP telda'!G47+'LOOKUP telda'!H47 -> 0 | F73: ='LOOKUP telda'!I47 -> 0 | G73: ='LOOKUP telda'!AA47 -> 1 | H73: ='LOOKUP telda'!AE47-'LOOKUP telda'!AA47 -> 0 | I73: ='LOOKUP telda'!AF47 -> 0 | J73: ='LOOKUP telda'!J47 -> 0 | K73: ='LOOKUP telda'!K47 -> 0 | L73: ='LOOKUP telda'!L47 -> 0 | M73: ='LOOKUP telda'!P47 -> 0 | N73: ='LOOKUP telda'!X47 -> 0 | O73: ='LOOKUP telda'!Y47 -> 0 | P73: ='LOOKUP telda'!Z47 -> 1 | Q73: =T73 -> 0.5 | R73: =U73 -> 1 | S73: =VLOOKUP(C73,Sheet3!$A$19:$G$81,7,FALSE) -> #N/A | T73: =IFERROR(P73/(D73-F73-K73-I73),0) -> 0.5 | U73: =IFERROR(P73/(M73+N73+O73+P73),0) -> 1 | V73: =VLOOKUP(C73,Sheet5!$A$2:$J$270,8,FALSE) -> WAINGAPU
C74: WAINGAPU | D74: ='LOOKUP telda'!E48 -> 5 | E74: ='LOOKUP telda'!F48+'LOOKUP telda'!G48+'LOOKUP telda'!H48 -> 0 | F74: ='LOOKUP telda'!I48 -> 1 | G74: ='LOOKUP telda'!AA48 -> 0 | H74: ='LOOKUP telda'!AE48-'LOOKUP telda'!AA48 -> 0 | I74: ='LOOKUP telda'!AF48 -> 0 | J74: ='LOOKUP telda'!J48 -> 0 | K74: ='LOOKUP telda'!K48 -> 0 | L74: ='LOOKUP telda'!L48 -> 0 | M74: ='LOOKUP telda'!P48 -> 0 | N74: ='LOOKUP telda'!X48 -> 0 | O74: ='LOOKUP telda'!Y48 -> 0 | P74: ='LOOKUP telda'!Z48 -> 4 | Q74: =T74 -> 1 | R74: =U74 -> 1 | S74: =VLOOKUP(C74,Sheet3!$A$19:$G$81,7,FALSE) -> 0.8 | T74: =IFERROR(P74/(D74-F74-K74-I74),0) -> 1 | U74: =IFERROR(P74/(M74+N74+O74+P74),0) -> 1 | V74: =VLOOKUP(C74,Sheet5!$A$2:$J$270,8,FALSE) -> WAINGAPU
B75: SURAMADU | C75: BANGKALAN | D75: ='LOOKUP telda'!E49 -> 23 | E75: ='LOOKUP telda'!F49+'LOOKUP telda'!G49+'LOOKUP telda'!H49 -> 3 | F75: ='LOOKUP telda'!I49 -> 0 | G75: ='LOOKUP telda'!AA49 -> 0 | H75: ='LOOKUP telda'!AE49-'LOOKUP telda'!AA49 -> 0 | I75: ='LOOKUP telda'!AF49 -> 5 | J75: ='LOOKUP telda'!J49 -> 1 | K75: ='LOOKUP telda'!K49 -> 0 | L75: ='LOOKUP telda'!L49 -> 0 | M75: ='LOOKUP telda'!P49 -> 0 | N75: ='LOOKUP telda'!X49 -> 0 | O75: ='LOOKUP telda'!Y49 -> 0 | P75: ='LOOKUP telda'!Z49 -> 14 | Q75: =T75 -> 0.77777778 | R75: =U75 -> 1 | S75: =VLOOKUP(C75,Sheet3!$A$19:$G$81,7,FALSE) -> #N/A | T75: =IFERROR(P75/(D75-F75-K75-I75),0) -> 0.77777778 | U75: =IFERROR(P75/(M75+N75+O75+P75),0) -> 1 | V75: =VLOOKUP(C75,Sheet5!$A$2:$J$270,8,FALSE) -> MADURA
C76: GRESIK | D76: ='LOOKUP telda'!E50 -> 44 | E76: ='LOOKUP telda'!F50+'LOOKUP telda'!G50+'LOOKUP telda'!H50 -> 0 | F76: ='LOOKUP telda'!I50 -> 1 | G76: ='LOOKUP telda'!AA50 -> 0 | H76: ='LOOKUP telda'!AE50-'LOOKUP telda'!AA50 -> 0 | I76: ='LOOKUP telda'!AF50 -> 11 | J76: ='LOOKUP telda'!J50 -> 3 | K76: ='LOOKUP telda'!K50 -> 0 | L76: ='LOOKUP telda'!L50 -> 1 | M76: ='LOOKUP telda'!P50 -> 0 | N76: ='LOOKUP telda'!X50 -> 1 | O76: ='LOOKUP telda'!Y50 -> 2 | P76: ='LOOKUP telda'!Z50 -> 25 | Q76: =T76 -> 0.78125 | R76: =U76 -> 0.89285714 | S76: =VLOOKUP(C76,Sheet3!$A$19:$G$81,7,FALSE) -> 0.97727273 | T76: =IFERROR(P76/(D76-F76-K76-I76),0) -> 0.78125 | U76: =IFERROR(P76/(M76+N76+O76+P76),0) -> 0.89285714 | V76: =VLOOKUP(C76,Sheet5!$A$2:$J$270,8,FALSE) -> GRESIK
C77: KENJERAN | D77: ='LOOKUP telda'!E51 -> 22 | E77: ='LOOKUP telda'!F51+'LOOKUP telda'!G51+'LOOKUP telda'!H51 -> 0 | F77: ='LOOKUP telda'!I51 -> 1 | G77: ='LOOKUP telda'!AA51 -> 0 | H77: ='LOOKUP telda'!AE51-'LOOKUP telda'!AA51 -> 0 | I77: ='LOOKUP telda'!AF51 -> 4 | J77: ='LOOKUP telda'!J51 -> 2 | K77: ='LOOKUP telda'!K51 -> 0 | L77: ='LOOKUP telda'!L51 -> 0 | M77: ='LOOKUP telda'!P51 -> 0 | N77: ='LOOKUP telda'!X51 -> 0 | O77: ='LOOKUP telda'!Y51 -> 1 | P77: ='LOOKUP telda'!Z51 -> 14 | Q77: =T77 -> 0.82352941 | R77: =U77 -> 0.93333333 | S77: =VLOOKUP(C77,Sheet3!$A$19:$G$81,7,FALSE) -> #N/A | T77: =IFERROR(P77/(D77-F77-K77-I77),0) -> 0.82352941 | U77: =IFERROR(P77/(M77+N77+O77+P77),0) -> 0.93333333 | V77: =VLOOKUP(C77,Sheet5!$A$2:$J$270,8,FALSE) -> SURABAYA UTARA
C78: KETINTANG | D78: ='LOOKUP telda'!E52 -> 37 | E78: ='LOOKUP telda'!F52+'LOOKUP telda'!G52+'LOOKUP telda'!H52 -> 2 | F78: ='LOOKUP telda'!I52 -> 1 | G78: ='LOOKUP telda'!AA52 -> 0 | H78: ='LOOKUP telda'!AE52-'LOOKUP telda'!AA52 -> 0 | I78: ='LOOKUP telda'!AF52 -> 8 | J78: ='LOOKUP telda'!J52 -> 3 | K78: ='LOOKUP telda'!K52 -> 0 | L78: ='LOOKUP telda'!L52 -> 0 | M78: ='LOOKUP telda'!P52 -> 0 | N78: ='LOOKUP telda'!X52 -> 1 | O78: ='LOOKUP telda'!Y52 -> 0 | P78: ='LOOKUP telda'!Z52 -> 22 | Q78: =T78 -> 0.78571429 | R78: =U78 -> 0.95652174 | S78: =VLOOKUP(C78,Sheet3!$A$19:$G$81,7,FALSE) -> #N/A | T78: =IFERROR(P78/(D78-F78-K78-I78),0) -> 0.78571429 | U78: =IFERROR(P78/(M78+N78+O78+P78),0) -> 0.95652174 | V78: =VLOOKUP(C78,Sheet5!$A$2:$J$270,8,FALSE) -> SURABAYA SELATAN
C79: LAMONGAN | D79: ='LOOKUP telda'!E53 -> 32 | E79: ='LOOKUP telda'!F53+'LOOKUP telda'!G53+'LOOKUP telda'!H53 -> 2 | F79: ='LOOKUP telda'!I53 -> 1 | G79: ='LOOKUP telda'!AA53 -> 0 | H79: ='LOOKUP telda'!AE53-'LOOKUP telda'!AA53 -> 1 | I79: ='LOOKUP telda'!AF53 -> 1 | J79: ='LOOKUP telda'!J53 -> 3 | K79: ='LOOKUP telda'!K53 -> 1 | L79: ='LOOKUP telda'!L53 -> 0 | M79: ='LOOKUP telda'!P53 -> 1 | N79: ='LOOKUP telda'!X53 -> 3 | O79: ='LOOKUP telda'!Y53 -> 0 | P79: ='LOOKUP telda'!Z53 -> 19 | Q79: =T79 -> 0.65517241 | R79: =U79 -> 0.82608696 | S79: =VLOOKUP(C79,Sheet3!$A$19:$G$81,7,FALSE) -> #N/A | T79: =IFERROR(P79/(D79-F79-K79-I79),0) -> 0.65517241 | U79: =IFERROR(P79/(M79+N79+O79+P79),0) -> 0.82608696 | V79: =VLOOKUP(C79,Sheet5!$A$2:$J$270,8,FALSE) -> GRESIK
C80: MANYAR | D80: ='LOOKUP telda'!E54 -> 35 | E80: ='LOOKUP telda'!F54+'LOOKUP telda'!G54+'LOOKUP telda'!H54 -> 1 | F80: ='LOOKUP telda'!I54 -> 0 | G80: ='LOOKUP telda'!AA54 -> 1 | H80: ='LOOKUP telda'!AE54-'LOOKUP telda'!AA54 -> 0 | I80: ='LOOKUP telda'!AF54 -> 4 | J80: ='LOOKUP telda'!J54 -> 5 | K80: ='LOOKUP telda'!K54 -> 0 | L80: ='LOOKUP telda'!L54 -> 0 | M80: ='LOOKUP telda'!P54 -> 0 | N80: ='LOOKUP telda'!X54 -> 0 | O80: ='LOOKUP telda'!Y54 -> 1 | P80: ='LOOKUP telda'!Z54 -> 23 | Q80: =T80 -> 0.74193548 | R80: =U80 -> 0.95833333 | S80: =VLOOKUP(C80,Sheet3!$A$19:$G$81,7,FALSE) -> #N/A | T80: =IFERROR(P80/(D80-F80-K80-I80),0) -> 0.74193548 | U80: =IFERROR(P80/(M80+N80+O80+P80),0) -> 0.95833333 | V80: =VLOOKUP(C80,Sheet5!$A$2:$J$270,8,FALSE) -> SURABAYA SELATAN
C81: PAMEKASAN | D81: ='LOOKUP telda'!E55 -> 38 | E81: ='LOOKUP telda'!F55+'LOOKUP telda'!G55+'LOOKUP telda'!H55 -> 1 | F81: ='LOOKUP telda'!I55 -> 0 | G81: ='LOOKUP telda'!AA55 -> 0 | H81: ='LOOKUP telda'!AE55-'LOOKUP telda'!AA55 -> 1 | I81: ='LOOKUP telda'!AF55 -> 6 | J81: ='LOOKUP telda'!J55 -> 3 | K81: ='LOOKUP telda'!K55 -> 0 | L81: ='LOOKUP telda'!L55 -> 0 | M81: ='LOOKUP telda'!P55 -> 0 | N81: ='LOOKUP telda'!X55 -> 0 | O81: ='LOOKUP telda'!Y55 -> 0 | P81: ='LOOKUP telda'!Z55 -> 27 | Q81: =T81 -> 0.84375 | R81: =U81 -> 1 | S81: =VLOOKUP(C81,Sheet3!$A$19:$G$81,7,FALSE) -> #N/A | T81: =IFERROR(P81/(D81-F81-K81-I81),0) -> 0.84375 | U81: =IFERROR(P81/(M81+N81+O81+P81),0) -> 1 | V81: =VLOOKUP(C81,Sheet5!$A$2:$J$270,8,FALSE) -> MADURA
C82: TANDES | D82: ='LOOKUP telda'!E56 -> 43 | E82: ='LOOKUP telda'!F56+'LOOKUP telda'!G56+'LOOKUP telda'!H56 -> 2 | F82: ='LOOKUP telda'!I56 -> 2 | G82: ='LOOKUP telda'!AA56 -> 0 | H82: ='LOOKUP telda'!AE56-'LOOKUP telda'!AA56 -> 1 | I82: ='LOOKUP telda'!AF56 -> 8 | J82: ='LOOKUP telda'!J56 -> 9 | K82: ='LOOKUP telda'!K56 -> 1 | L82: ='LOOKUP telda'!L56 -> 0 | M82: ='LOOKUP telda'!P56 -> 0 | N82: ='LOOKUP telda'!X56 -> 0 | O82: ='LOOKUP telda'!Y56 -> 0 | P82: ='LOOKUP telda'!Z56 -> 20 | Q82: =T82 -> 0.625 | R82: =U82 -> 1 | S82: =VLOOKUP(C82,Sheet3!$A$19:$G$81,7,FALSE) -> #N/A | T82: =IFERROR(P82/(D82-F82-K82-I82),0) -> 0.625 | U82: =IFERROR(P82/(M82+N82+O82+P82),0) -> 1 | V82: =VLOOKUP(C82,Sheet5!$A$2:$J$270,8,FALSE) -> SURABAYA UTARA
B83: TOTAL | D83: =SUM(D33:D82) -> 1014 | E83: =SUM(E33:E82) -> 27 | F83: =SUM(F33:F82) -> 24 | G83: =SUM(G33:G82) -> 12 | H83: =SUM(H33:H82) -> 33 | I83: =SUM(I33:I82) -> 114 | J83: =SUM(J33:J82) -> 62 | K83: =SUM(K33:K82) -> 27 | ... P83: =SUM(P33:P82) -> 644 | Q83: =T83 -> 0.75853946 | R83: =U83 -> 0.90322581 | S83: =S15 -> 0.9378882 | T83: =P83/(D83-F83-K83-I83) -> 0.75853946 | U83: =P83/(M83+N83+O83+P83) -> 0.90322581 | V83: =VLOOKUP(C83,Sheet5!$A$2:$J$270,8,FALSE) -> #N/A

Sheet Sheet1
A1: =LAPORAN!C1 -> PROVISIONING NEW SALES INDIBIZ TR3 JBN MTD H-1 2026-10-15
A2: =LAPORAN!C2 -> PERIODE ORDER & PS : 2026-10-01 to 2026-10-15
A3: =LAPORAN!C3 -> Last update proses : 16-10-2026 08:34:07 WIB (Source: ETL XPRO)
A5: WITEL | B5: (RE) | C5: REVOKE | D5: JML COMP (PS) | E5: REVOKE % | F5: PS/RE (%) (Target 80%) | G5: PS/PI (%) (Target 88%) | H5: TTI COMPLY 1X 24 (%) (Target 85%)
A6: =HARIAN!C10 -> BALI | B6: =HARIAN!D10 -> 126 | C6: =HARIAN!I10 -> 14 | D6: =HARIAN!P10 -> 60 | E6: =C6/B6 -> 0.11111111 | F6: =HARIAN!Q10 -> 0.63157895 | G6: =HARIAN!R10 -> 0.77922078 | H6: =HARIAN!S10 -> 0.91666667
A7: =HARIAN!C11 -> JATIM BARAT | B7: =HARIAN!D11 -> 231 | C7: =HARIAN!I11 -> 13 | D7: =HARIAN!P11 -> 169 | E7: =C7/B7 -> 0.056277056 | F7: =HARIAN!Q11 -> 0.82439024 | G7: =HARIAN!R11 -> 0.97126437 | H7: =HARIAN!S11 -> 0.98224852
A8: =HARIAN!C12 -> JATIM TIMUR | B8: =HARIAN!D12 -> 173 | C8: =HARIAN!I12 -> 9 | D8: =HARIAN!P12 -> 130 | E8: =C8/B8 -> 0.052023121 | F8: =HARIAN!Q12 -> 0.8125 | G8: =HARIAN!R12 -> 0.94202899 | H8: =HARIAN!S12 -> 1
A9: =HARIAN!C13 -> NUSA TENGGARA | B9: =HARIAN!D13 -> 210 | C9: =HARIAN!I13 -> 31 | D9: =HARIAN!P13 -> 121 | E9: =C9/B9 -> 0.14761905 | F9: =HARIAN!Q13 -> 0.71176471 | G9: =HARIAN!R13 -> 0.80666667 | H9: =HARIAN!S13 -> 0.76033058
A10: =HARIAN!C14 -> SURAMADU | B10: =HARIAN!D14 -> 274 | C10: =HARIAN!I14 -> 47 | D10: =HARIAN!P14 -> 164 | E10: =C10/B10 -> 0.17153285 | F10: =HARIAN!Q14 -> 0.74885845 | G10: =HARIAN!R14 -> 0.94252874 | H10: =HARIAN!S14 -> 0.98170732
A11: =HARIAN!C15 -> TOTAL | B11: =HARIAN!D15 -> 1014 | C11: =HARIAN!I15 -> 114 | D11: =HARIAN!P15 -> 644 | E11: =C11/B11 -> 0.11242604 | F11: =HARIAN!Q15 -> 0.75853946 | G11: =HARIAN!R15 -> 0.90322581 | H11: =HARIAN!S15 -> 0.9378882

Sheet LAPORAN
C1: ="PROVISIONING NEW SALES INDIBIZ TR3 JBN MTD H-1 "&TEXT(TODAY()-1,"YYYY-MM-DD ") -> PROVISIONING NEW SALES INDIBIZ TR3 JBN MTD H-1 2026-10-15
C2: ="PERIODE ORDER & PS : 2026-10-01 to "&TEXT(TODAY()-1,"YYYY-MM-DD ") -> PERIODE ORDER & PS : 2026-10-01 to 2026-10-15
C3: Last update proses : 16-10-2026 08:34:07 WIB (Source: ETL XPRO)
C5: WITEL | D5: (RE) | E5: INPROGRESS SC+QC1+FCC | F5: CANCEL | I5: REVOKE | J5: SURVEY NEW MANJA | K5: UN-SC | L5: OGP | P5: JML COMP (PS) | Q5: PS/RE (%) (Target 80%) | R5: PS/PI (%) (Target 94%) | S5: TTI COMPLY 1X 24 (%) (Target 94%)
F8: BY FCC | G8: KNDL PLGN | H8: KNDL NON PLGN | L8: PRE PI | M8: PI | N8: FALLOUT | O8: ACT COMP (QC2)
C9: BALI | D9: =HARIAN!D10 -> 126 | E9: =HARIAN!E10 -> 1 | F9: =HARIAN!F10 -> 7 | G9: =HARIAN!G10 -> 1 | H9: =HARIAN!H10 -> 11 | I9: =HARIAN!I10 -> 14 | J9: =HARIAN!J10 -> 5 | K9: =HARIAN!K10 -> 10 | ... S9: =HARIAN!S10 -> 0.91666667
C10: JATIM BARAT | D10: =HARIAN!D11 -> 231 | E10: =HARIAN!E11 -> 5 | F10: =HARIAN!F11 -> 5 | G10: =HARIAN!G11 -> 3 | H10: =HARIAN!H11 -> 8 | I10: =HARIAN!I11 -> 13 | J10: =HARIAN!J11 -> 14 | K10: =HARIAN!K11 -> 8 | ... S10: =HARIAN!S11 -> 0.98224852
C11: JATIM TIMUR | D11: =HARIAN!D12 -> 173 | E11: =HARIAN!E12 -> 4 | F11: =HARIAN!F12 -> 2 | G11: =HARIAN!G12 -> 5 | H11: =HARIAN!H12 -> 8 | I11: =HARIAN!I12 -> 9 | J11: =HARIAN!J12 -> 5 | K11: =HARIAN!K12 -> 2 | ... S11: =HARIAN!S12 -> 1
C12: NUSA TENGGARA | D12: =HARIAN!D13 -> 210 | E12: =HARIAN!E13 -> 6 | F12: =HARIAN!F13 -> 4 | G12: =HARIAN!G13 -> 2 | H12: =HARIAN!H13 -> 3 | I12: =HARIAN!I13 -> 31 | J12: =HARIAN!J13 -> 9 | K12: =HARIAN!K13 -> 5 | ... S12: =HARIAN!S13 -> 0.76033058
C13: SURAMADU | D13: =HARIAN!D14 -> 274 | E13: =HARIAN!E14 -> 11 | F13: =HARIAN!F14 -> 6 | G13: =HARIAN!G14 -> 1 | H13: =HARIAN!H14 -> 3 | I13: =HARIAN!I14 -> 47 | J13: =HARIAN!J14 -> 29 | K13: =HARIAN!K14 -> 2 | ... S13: =HARIAN!S14 -> 0.98170732
C14: TOTAL | D14: =SUM(D9:D13) -> 1014 | E14: =SUM(E9:E13) -> 27 | F14: =SUM(F9:F13) -> 24 | G14: =SUM(G9:G13) -> 12 | H14: =SUM(H9:H13) -> 33 | I14: =SUM(I9:I13) -> 114 | J14: =SUM(J9:J13) -> 62 | K14: =SUM(K9:K13) -> 27 | ... P14: =SUM(P9:P13) -> 644 | Q14: =HARIAN!Q15 -> 0.75853946 | R14: =HARIAN!R15 -> 0.90322581 | S14: =HARIAN!S15 -> 0.9378882
C16: Keterangan | D16: UIC | G16: * Target PS/PI Sesuai dengan Draft SLA MSA 2025 | L16: FORMULA
D17: Inputer, DIT, FCC | G17: 1. Time To Install (TTI) Comply Indibiz | 1x24 jam | L17: PI/RE : (Total PI + Total Fallout + Act Comp + Jumlah PS + Total Cancel) / Registered
D18: Order Cancel & Revoke | G18: 2. Fulfillment Guarantee (FFG) Indibiz | 60 hari | L18: PS/RE : PS / (Registered - Cancel by FCC - UNSC - Revoke)
D19: TA, BGESOPS, DAMAN, DIT | G19: 3. TTR Fulfillment Guarantee Indibiz | 3 jam | L19: PS/PI : PS / (Total PI + Total Fallout + Act Comp + Jumlah PS)
D20: Completed (PS) | G20: 4. PS to PI Ratio Indibiz Q3 88 % (Incremental)
D21: Performansi | G21: 5. Underspec warranty Indibiz | <= -25dBm
B23: =C1 -> PROVISIONING NEW SALES INDIBIZ TR3 JBN MTD H-1 2026-10-15
B24: =C2 -> PERIODE ORDER & PS : 2026-10-01 to 2026-10-15
B25: =C3 -> Last update proses : 16-10-2026 08:34:07 WIB (Source: ETL XPRO)
B28: WITEL | C28: TELDA | D28: (RE) | E28: INPROGRESS SC+QC1+FCC | F28: CANCEL | I28: REVOKE | J28: SURVEY NEW MANJA | K28: UN-SC | L28: OGP | P28: JML COMP (PS) | Q28: PS/RE (%) (Target 80%) | R28: PS/PI (%) (Target 94%) | S28: TTI COMPLY 1X 24 (%) (Target 94%)
F31: BY FCC | G31: KNDL PLGN | H31: KNDL NON PLGN | L31: PRE PI | M31: PI | N31: FALLOUT | O31: ACT COMP (QC2)
B32: BALI | C32: GIANYAR | D32: =HARIAN!D33 -> 12 | E32: =HARIAN!E33 -> 0 | F32: =HARIAN!F33 -> 0 | G32: =HARIAN!G33 -> 0 | H32: =HARIAN!H33 -> 0 | I32: =HARIAN!I33 -> 3 | J32: =HARIAN!J33 -> 0 | K32: =HARIAN!K33 -> 0 | ... P32: =HARIAN!P33 -> 9 | Q32: =T32 -> 1 | R32: =U32 -> 1 | S32: =VLOOKUP(C32,Sheet3!$A$19:$G$81,7,FALSE) -> 0.66666667 | T32: =P32/(D32-F32-K32-I32) -> 1 | U32: =P32/(M32+N32+O32+P32) -> 1
C33: TABANAN | D33: =HARIAN!D34+HARIAN!D39 -> 49 | E33: =HARIAN!E34+HARIAN!E39 -> 1 | F33: =HARIAN!F34+HARIAN!F39 -> 2 | G33: =HARIAN!G34+HARIAN!G39 -> 0 | H33: =HARIAN!H34+HARIAN!H39 -> 11 | I33: =HARIAN!I34+HARIAN!I39 -> 3 | J33: =HARIAN!J34+HARIAN!J39 -> 1 | K33: =HARIAN!K34+HARIAN!K39 -> 10 | ... P33: =HARIAN!P34+HARIAN!P39 -> 16 | Q33: =T33 -> 0.47058824 | R33: =U33 -> 0.76190476 | S33: =VLOOKUP(C33,Sheet3!$A$19:$G$81,7,FALSE) -> 0.93333333 | T33: =P33/(D33-F33-K33-I33) -> 0.47058824 | U33: =P33/(M33+N33+O33+P33) -> 0.76190476
C34: JIMBARAN | D34: =HARIAN!D35 -> 15 | E34: =HARIAN!E35 -> 0 | F34: =HARIAN!F35 -> 3 | G34: =HARIAN!G35 -> 0 | H34: =HARIAN!H35 -> 0 | I34: =HARIAN!I35 -> 2 | J34: =HARIAN!J35 -> 1 | K34: =HARIAN!K35 -> 0 | ... P34: =HARIAN!P35 -> 5 | Q34: =T34 -> 0.5 | R34: =U34 -> 0.55555556 | S34: =VLOOKUP(C34,Sheet3!$A$19:$G$81,7,FALSE) -> 0.8 | T34: =P34/(D34-F34-K34-I34) -> 0.5 | U34: =P34/(M34+N34+O34+P34) -> 0.55555556
C35: KLUNGKUNG | D35: =HARIAN!D36 -> 11 | E35: =HARIAN!E36 -> 0 | F35: =HARIAN!F36 -> 1 | G35: =HARIAN!G36 -> 0 | H35: =HARIAN!H36 -> 0 | I35: =HARIAN!I36 -> 1 | J35: =HARIAN!J36 -> 2 | K35: =HARIAN!K36 -> 0 | ... P35: =HARIAN!P36 -> 6 | Q35: =T35 -> 0.66666667 | R35: =U35 -> 0.85714286 | S35: =VLOOKUP(C35,Sheet3!$A$19:$G$81,7,FALSE) -> 1 | T35: =P35/(D35-F35-K35-I35) -> 0.66666667 | U35: =P35/(M35+N35+O35+P35) -> 0.85714286
C36: SANUR | D36: =HARIAN!D37 -> 14 | E36: =HARIAN!E37 -> 0 | F36: =HARIAN!F37 -> 1 | G36: =HARIAN!G37 -> 0 | H36: =HARIAN!H37 -> 0 | I36: =HARIAN!I37 -> 1 | J36: =HARIAN!J37 -> 1 | K36: =HARIAN!K37 -> 0 | ... P36: =HARIAN!P37 -> 10 | Q36: =T36 -> 0.83333333 | R36: =U36 -> 0.90909091 | S36: =VLOOKUP(C36,Sheet3!$A$19:$G$81,7,FALSE) -> 1 | T36: =P36/(D36-F36-K36-I36) -> 0.83333333 | U36: =P36/(M36+N36+O36+P36) -> 0.90909091
C37: SINGARAJA | D37: =HARIAN!D38 -> 7 | E37: =HARIAN!E38 -> 0 | F37: =HARIAN!F38 -> 0 | G37: =HARIAN!G38 -> 0 | H37: =HARIAN!H38 -> 0 | I37: =HARIAN!I38 -> 1 | J37: =HARIAN!J38 -> 0 | K37: =HARIAN!K38 -> 0 | ... P37: =HARIAN!P38 -> 5 | Q37: =T37 -> 0.83333333 | R37: =U37 -> 0.83333333 | S37: =VLOOKUP(C37,Sheet3!$A$19:$G$81,7,FALSE) -> 1 | T37: =P37/(D37-F37-K37-I37) -> 0.83333333 | U37: =P37/(M37+N37+O37+P37) -> 0.83333333
C38: UBUNG | D38: =HARIAN!D40 -> 18 | E38: =HARIAN!E40 -> 0 | F38: =HARIAN!F40 -> 0 | G38: =HARIAN!G40 -> 1 | H38: =HARIAN!H40 -> 0 | I38: =HARIAN!I40 -> 3 | J38: =HARIAN!J40 -> 0 | K38: =HARIAN!K40 -> 0 | ... P38: =HARIAN!P40 -> 9 | Q38: =T38 -> 0.6 | R38: =U38 -> 0.64285714 | S38: =VLOOKUP(C38,Sheet3!$A$19:$G$81,7,FALSE) -> 1 | T38: =P38/(D38-F38-K38-I38) -> 0.6 | U38: =P38/(M38+N38+O38+P38) -> 0.64285714
B39: JATIM BARAT | C39: BATU | D39: =HARIAN!D41 -> 31 | E39: =HARIAN!E41 -> 3 | F39: =HARIAN!F41 -> 0 | G39: =HARIAN!G41 -> 0 | H39: =HARIAN!H41 -> 3 | I39: =HARIAN!I41 -> 1 | J39: =HARIAN!J41 -> 8 | K39: =HARIAN!K41 -> 0 | ... P39: =HARIAN!P41 -> 16 | Q39: =T39 -> 0.53333333 | R39: =U39 -> 1 | S39: =VLOOKUP(C39,Sheet3!$A$19:$G$81,7,FALSE) -> 1 | T39: =P39/(D39-F39-K39-I39) -> 0.53333333 | U39: =P39/(M39+N39+O39+P39) -> 1
C40: BLITAR | D40: =HARIAN!D42+HARIAN!D52 -> 25 | E40: =HARIAN!E42+HARIAN!E52 -> 0 | F40: =HARIAN!F42+HARIAN!F52 -> 2 | G40: =HARIAN!G42+HARIAN!G52 -> 0 | H40: =HARIAN!H42+HARIAN!H52 -> 1 | I40: =HARIAN!I42+HARIAN!I52 -> 0 | J40: =HARIAN!J42+HARIAN!J52 -> 2 | K40: =HARIAN!K42+HARIAN!K52 -> 0 | ... P40: =HARIAN!P42+HARIAN!P52 -> 20 | Q40: =T40 -> 0.86956522 | R40: =U40 -> 1 | S40: =VLOOKUP(C40,Sheet3!$A$19:$G$81,7,FALSE) -> 1 | T40: =P40/(D40-F40-K40-I40) -> 0.86956522 | U40: =P40/(M40+N40+O40+P40) -> 1
C41: BOJONEGORO | D41: =HARIAN!D43+HARIAN!D51 -> 43 | E41: =HARIAN!E43+HARIAN!E51 -> 1 | F41: =HARIAN!F43+HARIAN!F51 -> 3 | G41: =HARIAN!G43+HARIAN!G51 -> 1 | H41: =HARIAN!H43+HARIAN!H51 -> 1 | I41: =HARIAN!I43+HARIAN!I51 -> 5 | J41: =HARIAN!J43+HARIAN!J51 -> 0 | K41: =HARIAN!K43+HARIAN!K51 -> 2 | ... P41: =HARIAN!P43+HARIAN!P51 -> 29 | Q41: =T41 -> 0.87878788 | R41: =U41 -> 0.96666667 | S41: =VLOOKUP(C41,Sheet3!$A$19:$G$81,7,FALSE) -> 1 | T41: =P41/(D41-F41-K41-I41) -> 0.87878788 | U41: =P41/(M41+N41+O41+P41) -> 0.96666667
C42: KEDIRI | D42: =HARIAN!D44 -> 33 | E42: =HARIAN!E44 -> 1 | F42: =HARIAN!F44 -> 0 | G42: =HARIAN!G44 -> 0 | H42: =HARIAN!H44 -> 1 | I42: =HARIAN!I44 -> 0 | J42: =HARIAN!J44 -> 0 | K42: =HARIAN!K44 -> 0 | ... P42: =HARIAN!P44 -> 30 | Q42: =T42 -> 0.90909091 | R42: =U42 -> 0.96774194 | S42: =VLOOKUP(C42,Sheet3!$A$19:$G$81,7,FALSE) -> 0.93333333 | T42: =P42/(D42-F42-K42-I42) -> 0.90909091 | U42: =P42/(M42+N42+O42+P42) -> 0.96774194
C43: MALANG | D43: =HARIAN!D45 -> 34 | E43: =HARIAN!E45 -> 0 | F43: =HARIAN!F45 -> 0 | G43: =HARIAN!G45 -> 0 | H43: =HARIAN!H45 -> 0 | I43: =HARIAN!I45 -> 3 | J43: =HARIAN!J45 -> 0 | K43: =HARIAN!K45 -> 0 | ... P43: =HARIAN!P45 -> 31 | Q43: =T43 -> 1 | R43: =U43 -> 1 | S43: =VLOOKUP(C43,Sheet3!$A$19:$G$81,7,FALSE) -> 1 | T43: =P43/(D43-F43-K43-I43) -> 1 | U43: =P43/(M43+N43+O43+P43) -> 1
C44: MADIUN | D44: =HARIAN!D46 -> 8 | E44: =HARIAN!E46 -> 0 | F44: =HARIAN!F46 -> 0 | G44: =HARIAN!G46 -> 0 | H44: =HARIAN!H46 -> 0 | I44: =HARIAN!I46 -> 0 | J44: =HARIAN!J46 -> 0 | K44: =HARIAN!K46 -> 0 | ... P44: =HARIAN!P46 -> 7 | Q44: =T44 -> 0.875 | R44: =U44 -> 1 | S44: =VLOOKUP(C44,Sheet3!$A$19:$G$81,7,FALSE) -> 1 | T44: =P44/(D44-F44-K44-I44) -> 0.875 | U44: =P44/(M44+N44+O44+P44) -> 1
C45: NGANJUK | D45: =HARIAN!D47 -> 20 | E45: =HARIAN!E47 -> 0 | F45: =HARIAN!F47 -> 0 | G45: =HARIAN!G47 -> 0 | H45: =HARIAN!H47 -> 1 | I45: =HARIAN!I47 -> 2 | J45: =HARIAN!J47 -> 1 | K45: =HARIAN!K47 -> 5 | ... P45: =HARIAN!P47 -> 9 | Q45: =T45 -> 0.69230769 | R45: =U45 -> 0.81818182 | S45: =VLOOKUP(C45,Sheet3!$A$19:$G$81,7,FALSE) -> 1 | T45: =P45/(D45-F45-K45-I45) -> 0.69230769 | U45: =P45/(M45+N45+O45+P45) -> 0.81818182
C46: MADIUN | D46: =HARIAN!D48 -> 8 | E46: =HARIAN!E48 -> 0 | F46: =HARIAN!F48 -> 0 | G46: =HARIAN!G48 -> 0 | H46: =HARIAN!H48 -> 0 | I46: =HARIAN!I48 -> 0 | J46: =HARIAN!J48 -> 1 | K46: =HARIAN!K48 -> 0 | ... P46: =HARIAN!P48 -> 6 | Q46: =T46 -> 0.75 | R46: =U46 -> 0.85714286 | S46: =VLOOKUP(C46,Sheet3!$A$19:$G$81,7,FALSE) -> 1 | T46: =P46/(D46-F46-K46-I46) -> 0.75 | U46: =P46/(M46+N46+O46+P46) -> 0.85714286
C47: PONOROGO | D47: =HARIAN!D49+HARIAN!D50 -> 29 | E47: =HARIAN!E49+HARIAN!E50 -> 0 | F47: =HARIAN!F49+HARIAN!F50 -> 0 | G47: =HARIAN!G49+HARIAN!G50 -> 2 | H47: =HARIAN!H49+HARIAN!H50 -> 1 | I47: =HARIAN!I49+HARIAN!I50 -> 2 | J47: =HARIAN!J49+HARIAN!J50 -> 2 | K47: =HARIAN!K49+HARIAN!K50 -> 1 | ... P47: =HARIAN!P49+HARIAN!P50 -> 21 | Q47: =T47 -> 0.80769231 | R47: =U47 -> 1 | S47: =VLOOKUP(C47,Sheet3!$A$19:$G$81,7,FALSE) -> 0.95238095 | T47: =P47/(D47-F47-K47-I47) -> 0.80769231 | U47: =P47/(M47+N47+O47+P47) -> 1
B48: JATIM TIMUR | C48: BANYUWANGI | D48: =HARIAN!D53+HARIAN!D62 -> 21 | E48: =HARIAN!E53+HARIAN!E62 -> 0 | F48: =HARIAN!F53+HARIAN!F62 -> 0 | G48: =HARIAN!G53+HARIAN!G62 -> 1 | H48: =HARIAN!H53+HARIAN!H62 -> 2 | I48: =HARIAN!I53+HARIAN!I62 -> 0 | J48: =HARIAN!J53+HARIAN!J62 -> 2 | K48: =HARIAN!K53+HARIAN!K62 -> 0 | ... P48: =HARIAN!P53+HARIAN!P62 -> 16 | Q48: =T48 -> 0.76190476 | R48: =U48 -> 1 | S48: =VLOOKUP(C48,Sheet3!$A$19:$G$81,7,FALSE) -> 1 | T48: =P48/(D48-F48-K48-I48) -> 0.76190476 | U48: =P48/(M48+N48+O48+P48) -> 1
C49: JEMBER | D49: =HARIAN!D54+HARIAN!D56 -> 22 | E49: =HARIAN!E54+HARIAN!E56 -> 0 | F49: =HARIAN!F54+HARIAN!F56 -> 0 | G49: =HARIAN!G54+HARIAN!G56 -> 0 | H49: =HARIAN!H54+HARIAN!H56 -> 1 | I49: =HARIAN!I54+HARIAN!I56 -> 0 | J49: =HARIAN!J54+HARIAN!J56 -> 0 | K49: =HARIAN!K54+HARIAN!K56 -> 0 | ... P49: =HARIAN!P54+HARIAN!P56 -> 20 | Q49: =T49 -> 0.90909091 | R49: =U49 -> 0.95238095 | S49: =VLOOKUP(C49,Sheet3!$A$19:$G$81,7,FALSE) -> 1 | T49: =P49/(D49-F49-K49-I49) -> 0.90909091 | U49: =P49/(M49+N49+O49+P49) -> 0.95238095
C50: SIDOARJO | D50: =HARIAN!D55 -> 32 | E50: =HARIAN!E55 -> 0 | F50: =HARIAN!F55 -> 0 | G50: =HARIAN!G55 -> 1 | H50: =HARIAN!H55 -> 2 | I50: =HARIAN!I55 -> 3 | J50: =HARIAN!J55 -> 0 | K50: =HARIAN!K55 -> 1 | ... P50: =HARIAN!P55 -> 24 | Q50: =T50 -> 0.85714286 | R50: =U50 -> 0.96 | S50: =VLOOKUP(C50,Sheet3!$A$19:$G$81,7,FALSE) -> 1 | T50: =P50/(D50-F50-K50-I50) -> 0.85714286 | U50: =P50/(M50+N50+O50+P50) -> 0.96
C51: MOJOKERTO | D51: =HARIAN!D57+HARIAN!D59 -> 51 | E51: =HARIAN!E57+HARIAN!E59 -> 2 | F51: =HARIAN!F57+HARIAN!F59 -> 1 | G51: =HARIAN!G57+HARIAN!G59 -> 0 | H51: =HARIAN!H57+HARIAN!H59 -> 1 | I51: =HARIAN!I57+HARIAN!I59 -> 6 | J51: =HARIAN!J57+HARIAN!J59 -> 2 | K51: =HARIAN!K57+HARIAN!K59 -> 1 | ... P51: =HARIAN!P57+HARIAN!P59 -> 36 | Q51: =T51 -> 0.8372093 | R51: =U51 -> 0.94736842 | S51: =VLOOKUP(C51,Sheet3!$A$19:$G$81,7,FALSE) -> 1 | T51: =P51/(D51-F51-K51-I51) -> 0.8372093 | U51: =P51/(M51+N51+O51+P51) -> 0.94736842
C52: PASURUAN | D52: =HARIAN!D60 -> 23 | E52: =HARIAN!E60 -> 2 | F52: =HARIAN!F60 -> 1 | G52: =HARIAN!G60 -> 2 | H52: =HARIAN!H60 -> 2 | I52: =HARIAN!I60 -> 0 | J52: =HARIAN!J60 -> 0 | K52: =HARIAN!K60 -> 0 | ... P52: =HARIAN!P60 -> 16 | Q52: =T52 -> 0.72727273 | R52: =U52 -> 1 | S52: =VLOOKUP(C52,Sheet3!$A$19:$G$81,7,FALSE) -> 1 | T52: =P52/(D52-F52-K52-I52) -> 0.72727273 | U52: =P52/(M52+N52+O52+P52) -> 1
C53: PROBOLINGGO | D53: =HARIAN!D61+HARIAN!D58 -> 24 | E53: =HARIAN!E61+HARIAN!E58 -> 0 | F53: =HARIAN!F61+HARIAN!F58 -> 0 | G53: =HARIAN!G61+HARIAN!G58 -> 1 | H53: =HARIAN!H61+HARIAN!H58 -> 0 | I53: =HARIAN!I61+HARIAN!I58 -> 0 | J53: =HARIAN!J61+HARIAN!J58 -> 1 | K53: =HARIAN!K61+HARIAN!K58 -> 0 | ... P53: =HARIAN!P61+HARIAN!P58 -> 18 | Q53: =T53 -> 0.75 | R53: =U53 -> 0.81818182 | S53: =VLOOKUP(C53,Sheet3!$A$19:$G$81,7,FALSE) -> 1 | T53: =P53/(D53-F53-K53-I53) -> 0.75 | U53: =P53/(M53+N53+O53+P53) -> 0.81818182
B54: NUSRA | C54: ATAMBUA | D54: =HARIAN!D63 -> 2 | E54: =HARIAN!E63 -> 1 | F54: =HARIAN!F63 -> 0 | G54: =HARIAN!G63 -> 0 | H54: =HARIAN!H63 -> 0 | I54: =HARIAN!I63 -> 0 | J54: =HARIAN!J63 -> 0 | K54: =HARIAN!K63 -> 0 | ... P54: =HARIAN!P63 -> 1 | Q54: =T54 -> 0.5 | R54: =U54 -> 1 | S54: =VLOOKUP(C54,Sheet3!$A$19:$G$81,7,FALSE) -> 1 | T54: =P54/(D54-F54-K54-I54) -> 0.5 | U54: =P54/(M54+N54+O54+P54) -> 1
C55: BIMA | D55: =HARIAN!D64 -> 18 | E55: =HARIAN!E64 -> 0 | F55: =HARIAN!F64 -> 0 | G55: =HARIAN!G64 -> 0 | H55: =HARIAN!H64 -> 0 | I55: =HARIAN!I64 -> 5 | J55: =HARIAN!J64 -> 0 | K55: =HARIAN!K64 -> 0 | ... P55: =HARIAN!P64 -> 9 | Q55: =T55 -> 0.69230769 | R55: =U55 -> 0.75 | S55: =VLOOKUP(C55,Sheet3!$A$19:$G$81,7,FALSE) -> 0.55555556 | T55: =P55/(D55-F55-K55-I55) -> 0.69230769 | U55: =P55/(M55+N55+O55+P55) -> 0.75
C56: ENDE | D56: =HARIAN!D65 -> 14 | E56: =HARIAN!E65 -> 0 | F56: =HARIAN!F65 -> 0 | G56: =HARIAN!G65 -> 0 | H56: =HARIAN!H65 -> 0 | I56: =HARIAN!I65 -> 0 | J56: =HARIAN!J65 -> 0 | K56: =HARIAN!K65 -> 0 | ... P56: =HARIAN!P65 -> 12 | Q56: =T56 -> 0.85714286 | R56: =U56 -> 0.85714286 | S56: =VLOOKUP(C56,Sheet3!$A$19:$G$81,7,FALSE) -> 0.75 | T56: =P56/(D56-F56-K56-I56) -> 0.85714286 | U56: =P56/(M56+N56+O56+P56) -> 0.85714286
C57: MATARAM | D57: =HARIAN!D66 -> 26 | E57: =HARIAN!E66 -> 0 | F57: =HARIAN!F66 -> 0 | G57: =HARIAN!G66 -> 1 | H57: =HARIAN!H66 -> 0 | I57: =HARIAN!I66 -> 6 | J57: =HARIAN!J66 -> 0 | K57: =HARIAN!K66 -> 0 | ... P57: =HARIAN!P66 -> 16 | Q57: =T57 -> 0.8 | R57: =U57 -> 0.84210526 | S57: =VLOOKUP(C57,Sheet3!$A$19:$G$81,7,FALSE) -> 0.75 | T57: =P57/(D57-F57-K57-I57) -> 0.8 | U57: =P57/(M57+N57+O57+P57) -> 0.84210526
C58: KUPANG | D58: =HARIAN!D67 -> 24 | E58: =HARIAN!E67 -> 0 | F58: =HARIAN!F67 -> 1 | G58: =HARIAN!G67 -> 0 | H58: =HARIAN!H67 -> 3 | I58: =HARIAN!I67 -> 0 | J58: =HARIAN!J67 -> 2 | K58: =HARIAN!K67 -> 2 | ... P58: =HARIAN!P67 -> 10 | Q58: =T58 -> 0.47619048 | R58: =U58 -> 0.58823529 | S58: =VLOOKUP(C58,Sheet3!$A$19:$G$81,7,FALSE) -> 0.2 | T58: =P58/(D58-F58-K58-I58) -> 0.47619048 | U58: =P58/(M58+N58+O58+P58) -> 0.58823529
C59: LABOAN BAJO | D59: =HARIAN!D68 -> 9 | E59: =HARIAN!E68 -> 0 | F59: =HARIAN!F68 -> 0 | G59: =HARIAN!G68 -> 0 | H59: =HARIAN!H68 -> 0 | I59: =HARIAN!I68 -> 0 | J59: =HARIAN!J68 -> 0 | K59: =HARIAN!K68 -> 2 | ... P59: =HARIAN!P68 -> 6 | Q59: =T59 -> 0.85714286 | R59: =U59 -> 0.85714286 | S59: =VLOOKUP(C59,Sheet3!$A$19:$G$81,7,FALSE) -> 0.66666667 | T59: =P59/(D59-F59-K59-I59) -> 0.85714286 | U59: =P59/(M59+N59+O59+P59) -> 0.85714286
C60: SELONG | D60: =HARIAN!D69+HARIAN!D70 -> 64 | E60: =HARIAN!E69+HARIAN!E70 -> 2 | F60: =HARIAN!F69+HARIAN!F70 -> 2 | G60: =HARIAN!G69+HARIAN!G70 -> 0 | H60: =HARIAN!H69+HARIAN!H70 -> 0 | I60: =HARIAN!I69+HARIAN!I70 -> 10 | J60: =HARIAN!J69+HARIAN!J70 -> 4 | K60: =HARIAN!K69+HARIAN!K70 -> 1 | ... P60: =HARIAN!P69+HARIAN!P70 -> 38 | Q60: =T60 -> 0.74509804 | R60: =U60 -> 0.84444444 | S60: =VLOOKUP(C60,Sheet3!$A$19:$G$81,7,FALSE) -> 0.94736842 | T60: =P60/(D60-F60-K60-I60) -> 0.74509804 | U60: =P60/(M60+N60+O60+P60) -> 0.84444444
C61: MAUMERE | D61: =HARIAN!D71 -> 8 | E61: =HARIAN!E71 -> 0 | F61: =HARIAN!F71 -> 0 | G61: =HARIAN!G71 -> 0 | H61: =HARIAN!H71 -> 0 | I61: =HARIAN!I71 -> 0 | J61: =HARIAN!J71 -> 0 | K61: =HARIAN!K71 -> 0 | ... P61: =HARIAN!P71 -> 4 | Q61: =T61 -> 0.5 | R61: =U61 -> 0.5 | S61: =VLOOKUP(C61,Sheet3!$A$19:$G$81,7,FALSE) -> 0.25 | T61: =P61/(D61-F61-K61-I61) -> 0.5 | U61: =P61/(M61+N61+O61+P61) -> 0.5
C62: SUMBAWA | D62: =HARIAN!D72 -> 38 | E62: =HARIAN!E72 -> 3 | F62: =HARIAN!F72 -> 0 | G62: =HARIAN!G72 -> 0 | H62: =HARIAN!H72 -> 0 | I62: =HARIAN!I72 -> 10 | J62: =HARIAN!J72 -> 3 | K62: =HARIAN!K72 -> 0 | ... P62: =HARIAN!P72 -> 20 | Q62: =T62 -> 0.71428571 | R62: =U62 -> 0.90909091 | S62: =VLOOKUP(C62,Sheet3!$A$19:$G$81,7,FALSE) -> 0.9 | T62: =P62/(D62-F62-K62-I62) -> 0.71428571 | U62: =P62/(M62+N62+O62+P62) -> 0.90909091
C63: WAINGAPU | D63: =HARIAN!D73+HARIAN!D74 -> 7 | E63: =HARIAN!E73+HARIAN!E74 -> 0 | F63: =HARIAN!F73+HARIAN!F74 -> 1 | G63: =HARIAN!G73+HARIAN!G74 -> 1 | H63: =HARIAN!H73+HARIAN!H74 -> 0 | I63: =HARIAN!I73+HARIAN!I74 -> 0 | J63: =HARIAN!J73+HARIAN!J74 -> 0 | K63: =HARIAN!K73+HARIAN!K74 -> 0 | ... P63: =HARIAN!P73+HARIAN!P74 -> 5 | Q63: =T63 -> 0.83333333 | R63: =U63 -> 1 | S63: =VLOOKUP(C63,Sheet3!$A$19:$G$81,7,FALSE) -> 0.8 | T63: =P63/(D63-F63-K63-I63) -> 0.83333333 | U63: =P63/(M63+N63+O63+P63) -> 1
B64: SURAMADU | C64: MADURA | D64: =HARIAN!D75+HARIAN!D81 -> 61 | E64: =HARIAN!E75+HARIAN!E81 -> 4 | F64: =HARIAN!F75+HARIAN!F81 -> 0 | G64: =HARIAN!G75+HARIAN!G81 -> 0 | H64: =HARIAN!H75+HARIAN!H81 -> 1 | I64: =HARIAN!I75+HARIAN!I81 -> 11 | J64: =HARIAN!J75+HARIAN!J81 -> 4 | K64: =HARIAN!K75+HARIAN!K81 -> 0 | ... P64: =HARIAN!P75+HARIAN!P81 -> 41 | Q64: =T64 -> 0.82 | R64: =U64 -> 1 | S64: =VLOOKUP(C64,Sheet3!$A$19:$G$81,7,FALSE) -> 1 | T64: =P64/(D64-F64-K64-I64) -> 0.82 | U64: =P64/(M64+N64+O64+P64) -> 1
C65: GRESIK | D65: =HARIAN!D76+HARIAN!D79 -> 76 | E65: =HARIAN!E76+HARIAN!E79 -> 2 | F65: =HARIAN!F76+HARIAN!F79 -> 2 | G65: =HARIAN!G76+HARIAN!G79 -> 0 | H65: =HARIAN!H76+HARIAN!H79 -> 1 | I65: =HARIAN!I76+HARIAN!I79 -> 12 | J65: =HARIAN!J76+HARIAN!J79 -> 6 | K65: =HARIAN!K76+HARIAN!K79 -> 1 | ... P65: =HARIAN!P76+HARIAN!P79 -> 44 | Q65: =T65 -> 0.72131148 | R65: =U65 -> 0.8627451 | S65: =VLOOKUP(C65,Sheet3!$A$19:$G$81,7,FALSE) -> 0.97727273 | T65: =P65/(D65-F65-K65-I65) -> 0.72131148 | U65: =P65/(M65+N65+O65+P65) -> 0.8627451
C66: SURABAYA UTARA | D66: =HARIAN!D77+HARIAN!D82 -> 65 | E66: =HARIAN!E77+HARIAN!E82 -> 2 | F66: =HARIAN!F77+HARIAN!F82 -> 3 | G66: =HARIAN!G77+HARIAN!G82 -> 0 | H66: =HARIAN!H77+HARIAN!H82 -> 1 | I66: =HARIAN!I77+HARIAN!I82 -> 12 | J66: =HARIAN!J77+HARIAN!J82 -> 11 | K66: =HARIAN!K77+HARIAN!K82 -> 1 | ... P66: =HARIAN!P77+HARIAN!P82 -> 34 | Q66: =T66 -> 0.69387755 | R66: =U66 -> 0.97142857 | S66: =VLOOKUP(C66,Sheet3!$A$19:$G$81,7,FALSE) -> 1 | T66: =P66/(D66-F66-K66-I66) -> 0.69387755 | U66: =P66/(M66+N66+O66+P66) -> 0.97142857
C67: SURABAYA SELATAN | D67: =HARIAN!D78+HARIAN!D80 -> 72 | E67: =HARIAN!E78+HARIAN!E80 -> 3 | F67: =HARIAN!F78+HARIAN!F80 -> 1 | G67: =HARIAN!G78+HARIAN!G80 -> 1 | H67: =HARIAN!H78+HARIAN!H80 -> 0 | I67: =HARIAN!I78+HARIAN!I80 -> 12 | J67: =HARIAN!J78+HARIAN!J80 -> 8 | K67: =HARIAN!K78+HARIAN!K80 -> 0 | ... P67: =HARIAN!P78+HARIAN!P80 -> 45 | Q67: =T67 -> 0.76271186 | R67: =U67 -> 0.95744681 | S67: =VLOOKUP(C67,Sheet3!$A$19:$G$81,7,FALSE) -> 0.95555556 | T67: =P67/(D67-F67-K67-I67) -> 0.76271186 | U67: =P67/(M67+N67+O67+P67) -> 0.95744681
B68: TOTAL | D68: =SUM(D32:D67) -> 1014 | E68: =SUM(E32:E67) -> 27 | F68: =SUM(F32:F67) -> 24 | G68: =SUM(G32:G67) -> 12 | H68: =SUM(H32:H67) -> 33 | I68: =SUM(I32:I67) -> 114 | J68: =SUM(J32:J67) -> 62 | K68: =SUM(K32:K67) -> 27 | ... P68: =SUM(P32:P67) -> 644 | Q68: =Q14 -> 0.75853946 | R68: =R14 -> 0.90322581 | S68: =S14 -> 0.9378882

Sheet Sheet4
C1: PROVISIONING NEW SALES INDIBIZ TR3 JBN MTD H-1
C2: =LAPORAN!C2 -> PERIODE ORDER & PS : 2026-10-01 to 2026-10-15
C3: =LAPORAN!C3 -> Last update proses : 16-10-2026 08:34:07 WIB (Source: ETL XPRO)
C5: WITEL | D5: REGISTER (RE) | E5: SURVEY NEW MANJA | F5: UN-SC | G5: PRE PI | H5: PI | I5: TOTAL FALLOUT | J5: QC2 | K5: PS | L5: PS/RE (%) (Target 80%) | M5: PS/PI (%) (Target 94%) | N5: TTI COMPLY 1X 24 (%) (Target 94%)
C6: =[1]LAPORAN!C9 -> BALI | D6: =LAPORAN!D9 -> 126 | E6: =LAPORAN!J9 -> 5 | F6: =LAPORAN!K9 -> 10 | G6: =LAPORAN!L9 -> 0 | H6: =LAPORAN!M9 -> 12 | I6: =LAPORAN!N9 -> 4 | J6: =LAPORAN!O9 -> 1 | K6: =LAPORAN!P9 -> 60 | L6: =LAPORAN!Q9 -> 0.63157895 | ... N6: =LAPORAN!S9 -> 0.91666667
C7: =[1]LAPORAN!C10 -> JATIM BARAT | D7: =LAPORAN!D10 -> 231 | E7: =LAPORAN!J10 -> 14 | F7: =LAPORAN!K10 -> 8 | G7: =LAPORAN!L10 -> 0 | H7: =LAPORAN!M10 -> 1 | I7: =LAPORAN!N10 -> 1 | J7: =LAPORAN!O10 -> 3 | K7: =LAPORAN!P10 -> 169 | L7: =LAPORAN!Q10 -> 0.82439024 | ... N7: =LAPORAN!S10 -> 0.98224852
C8: =[1]LAPORAN!C11 -> JATIM TIMUR | D8: =LAPORAN!D11 -> 173 | E8: =LAPORAN!J11 -> 5 | F8: =LAPORAN!K11 -> 2 | G8: =LAPORAN!L11 -> 0 | H8: =LAPORAN!M11 -> 1 | I8: =LAPORAN!N11 -> 2 | J8: =LAPORAN!O11 -> 5 | K8: =LAPORAN!P11 -> 130 | L8: =LAPORAN!Q11 -> 0.8125 | ... N8: =LAPORAN!S11 -> 1
C9: =[1]LAPORAN!C12 -> NUSA TENGGARA | D9: =LAPORAN!D12 -> 210 | E9: =LAPORAN!J12 -> 9 | F9: =LAPORAN!K12 -> 5 | G9: =LAPORAN!L12 -> 1 | H9: =LAPORAN!M12 -> 19 | I9: =LAPORAN!N12 -> 5 | J9: =LAPORAN!O12 -> 5 | K9: =LAPORAN!P12 -> 121 | L9: =LAPORAN!Q12 -> 0.71176471 | ... N9: =LAPORAN!S12 -> 0.76033058
C10: =[1]LAPORAN!C13 -> SURAMADU | D10: =LAPORAN!D13 -> 274 | E10: =LAPORAN!J13 -> 29 | F10: =LAPORAN!K13 -> 2 | G10: =LAPORAN!L13 -> 1 | H10: =LAPORAN!M13 -> 1 | I10: =LAPORAN!N13 -> 5 | J10: =LAPORAN!O13 -> 4 | K10: =LAPORAN!P13 -> 164 | L10: =LAPORAN!Q13 -> 0.74885845 | ... N10: =LAPORAN!S13 -> 0.98170732
C11: =[1]LAPORAN!C14 -> TOTAL | D11: =LAPORAN!D14 -> 1014 | E11: =LAPORAN!J14 -> 62 | F11: =LAPORAN!K14 -> 27 | G11: =LAPORAN!L14 -> 2 | H11: =LAPORAN!M14 -> 34 | I11: =LAPORAN!N14 -> 17 | J11: =LAPORAN!O14 -> 18 | K11: =LAPORAN!P14 -> 644 | L11: =LAPORAN!Q14 -> 0.75853946 | ... N11: =LAPORAN!S14 -> 0.9378882

Sheet LOOKUP  telda
C1: HARIAN
C3: WITEL | D3: PRE PI | E3: REGISTERED (RE) | F3: INPROGRESS SC | G3: QC1 | H3: FCC | I3: CANCEL BY FCC | J3: SURVEY NEW MANJA | K3: UN-SC | L3: OGP | Z3: JML COMP (PS) | AA3: CANCEL | AE3: TOTAL CANCEL | AF3: REVOKE | AG3: PI/RE (%) | AH3: PS/RE (%) | AI3: PS/PI (%)
L4: PRE PI | M4: PI | P4: TOTAL PI | Q4: FALLOUT | X4: TOTAL FALLOUT | Y4: ACT COMP (QC2)
Q5: WFM | U5: UIM | V5: ASP | W5: OSM
M6: < 1 HARI | N6: 1 - 3 HARI | O6: > 3 HARI | Q6: KNDL PLGN | R6: KNDL TEKNIS | S6: KNDL SYS | T6: OTHERS | AA6: KNDL PLGN | AB6: KNDL TEKNIS | AC6: KNDL SYS | AD6: OTHERS
B7: BALI | C7: GIANYAR | D7: =IFERROR(VLOOKUP(C7,'COPY DATA XPRO'!$C$7:$AI$58,2,FALSE),0) -> 0 | E7: =IFERROR(VLOOKUP(C7,'COPY DATA XPRO'!$C$7:$AI$58,3,FALSE),0) -> 12 | F7: =IFERROR(VLOOKUP(C7,'COPY DATA XPRO'!$C$7:$AI$58,4,FALSE),0) -> 0 | G7: =IFERROR(VLOOKUP(C7,'COPY DATA XPRO'!$C$7:$AI$58,5,FALSE),0) -> 0 | H7: =IFERROR(VLOOKUP(C7,'COPY DATA XPRO'!$C$7:$AI$58,6,FALSE),0) -> 0 | I7: =IFERROR(VLOOKUP(C7,'COPY DATA XPRO'!$C$7:$AI$58,7,FALSE),0) -> 0 | J7: =IFERROR(VLOOKUP(C7,'COPY DATA XPRO'!$C$7:$AI$58,8,FALSE),0) -> 0 | K7: =IFERROR(VLOOKUP(C7,'COPY DATA XPRO'!$C$7:$AI$58,9,FALSE),0) -> 0 | L7: =IFERROR(VLOOKUP(C7,'COPY DATA XPRO'!$C$7:$AI$58,10,FALSE),0) -> 0 | M7: =IFERROR(VLOOKUP(C7,'COPY DATA XPRO'!$C$7:$AI$58,11,FALSE),0) -> 0 | N7: =IFERROR(VLOOKUP(C7,'COPY DATA XPRO'!$C$7:$AI$58,12,FALSE),0) -> 0 | O7: =IFERROR(VLOOKUP(C7,'COPY DATA XPRO'!$C$7:$AI$58,13,FALSE),0) -> 0 | P7: =IFERROR(VLOOKUP(C7,'COPY DATA XPRO'!$C$7:$AI$58,14,FALSE),0) -> 0 | Q7: =IFERROR(VLOOKUP(C7,'COPY DATA XPRO'!$C$7:$AI$58,15,FALSE),0) -> 0 | R7: =IFERROR(VLOOKUP(C7,'COPY DATA XPRO'!$C$7:$AI$58,16,FALSE),0) -> 0 | S7: =IFERROR(VLOOKUP(C7,'COPY DATA XPRO'!$C$7:$AI$58,17,FALSE),0) -> 0 | T7: =IFERROR(VLOOKUP(C7,'COPY DATA XPRO'!$C$7:$AI$58,18,FALSE),0) -> 0 | U7: =IFERROR(VLOOKUP(C7,'COPY DATA XPRO'!$C$7:$AI$58,19,FALSE),0) -> 0 | V7: =IFERROR(VLOOKUP(C7,'COPY DATA XPRO'!$C$7:$AI$58,20,FALSE),0) -> 0 | W7: =IFERROR(VLOOKUP(C7,'COPY DATA XPRO'!$C$7:$AI$58,21,FALSE),0) -> 0 | X7: =IFERROR(VLOOKUP(C7,'COPY DATA XPRO'!$C$7:$AI$58,22,FALSE),0) -> 0 | Y7: =IFERROR(VLOOKUP(C7,'COPY DATA XPRO'!$C$7:$AI$58,23,FALSE),0) -> 0 | Z7: =IFERROR(VLOOKUP(C7,'COPY DATA XPRO'!$C$7:$AI$58,24,FALSE),0) -> 9 | AA7: =IFERROR(VLOOKUP(C7,'COPY DATA XPRO'!$C$7:$AI$58,25,FALSE),0) -> 0 | AB7: =IFERROR(VLOOKUP(C7,'COPY DATA XPRO'!$C$7:$AI$58,26,FALSE),0) -> 0 | AC7: =IFERROR(VLOOKUP(C7,'COPY DATA XPRO'!$C$7:$AI$58,27,FALSE),0) -> 0 | AD7: =IFERROR(VLOOKUP(C7,'COPY DATA XPRO'!$C$7:$AI$58,28,FALSE),0) -> 0 | AE7: =IFERROR(VLOOKUP(C7,'COPY DATA XPRO'!$C$7:$AI$58,29,FALSE),0) -> 0 | AF7: =IFERROR(VLOOKUP(C7,'COPY DATA XPRO'!$C$7:$AI$58,30,FALSE),0) -> 3 | AG7: =IFERROR(VLOOKUP(C7,'COPY DATA XPRO'!$C$7:$AI$58,31,FALSE),0) -> 75 | AH7: =IFERROR(VLOOKUP(C7,'COPY DATA XPRO'!$C$7:$AI$58,32,FALSE),0) -> 100 | AI7: =IFERROR(VLOOKUP(C7,'COPY DATA XPRO'!$C$7:$AI$58,33,FALSE),0) -> 100
C8: JEMBRANA | D8: =IFERROR(VLOOKUP(C8,'COPY DATA XPRO'!$C$7:$AI$58, 2, FALSE), 0) -> 0 | E8: =IFERROR(VLOOKUP(C8,'COPY DATA XPRO'!$C$7:$AI$58,3,FALSE),0) -> 1 | F8: =IFERROR(VLOOKUP(C8,'COPY DATA XPRO'!$C$7:$AI$58,4,FALSE),0) -> 0 | G8: =IFERROR(VLOOKUP(C8,'COPY DATA XPRO'!$C$7:$AI$58,5,FALSE),0) -> 0 | H8: =IFERROR(VLOOKUP(C8,'COPY DATA XPRO'!$C$7:$AI$58,6,FALSE),0) -> 0 | I8: =IFERROR(VLOOKUP(C8,'COPY DATA XPRO'!$C$7:$AI$58,7,FALSE),0) -> 0 | J8: =IFERROR(VLOOKUP(C8,'COPY DATA XPRO'!$C$7:$AI$58,8,FALSE),0) -> 0 | K8: =IFERROR(VLOOKUP(C8,'COPY DATA XPRO'!$C$7:$AI$58,9,FALSE),0) -> 0 | L8: =IFERROR(VLOOKUP(C8,'COPY DATA XPRO'!$C$7:$AI$58,10,FALSE),0) -> 0 | M8: =IFERROR(VLOOKUP(C8,'COPY DATA XPRO'!$C$7:$AI$58,11,FALSE),0) -> 0 | N8: =IFERROR(VLOOKUP(C8,'COPY DATA XPRO'!$C$7:$AI$58,12,FALSE),0) -> 0 | O8: =IFERROR(VLOOKUP(C8,'COPY DATA XPRO'!$C$7:$AI$58,13,FALSE),0) -> 0 | P8: =IFERROR(VLOOKUP(C8,'COPY DATA XPRO'!$C$7:$AI$58,14,FALSE),0) -> 0 | Q8: =IFERROR(VLOOKUP(C8,'COPY DATA XPRO'!$C$7:$AI$58,15,FALSE),0) -> 0 | R8: =IFERROR(VLOOKUP(C8,'COPY DATA XPRO'!$C$7:$AI$58,16,FALSE),0) -> 0 | S8: =IFERROR(VLOOKUP(C8,'COPY DATA XPRO'!$C$7:$AI$58,17,FALSE),0) -> 0 | T8: =IFERROR(VLOOKUP(C8,'COPY DATA XPRO'!$C$7:$AI$58,18,FALSE),0) -> 0 | U8: =IFERROR(VLOOKUP(C8,'COPY DATA XPRO'!$C$7:$AI$58,19,FALSE),0) -> 0 | V8: =IFERROR(VLOOKUP(C8,'COPY DATA XPRO'!$C$7:$AI$58,20,FALSE),0) -> 0 | W8: =IFERROR(VLOOKUP(C8,'COPY DATA XPRO'!$C$7:$AI$58,21,FALSE),0) -> 0 | X8: =IFERROR(VLOOKUP(C8,'COPY DATA XPRO'!$C$7:$AI$58,22,FALSE),0) -> 0 | Y8: =IFERROR(VLOOKUP(C8,'COPY DATA XPRO'!$C$7:$AI$58,23,FALSE),0) -> 0 | Z8: =IFERROR(VLOOKUP(C8,'COPY DATA XPRO'!$C$7:$AI$58,24,FALSE),0) -> 1 | AA8: =IFERROR(VLOOKUP(C8,'COPY DATA XPRO'!$C$7:$AI$58,25,FALSE),0) -> 0 | AB8: =IFERROR(VLOOKUP(C8,'COPY DATA XPRO'!$C$7:$AI$58,26,FALSE),0) -> 0 | AC8: =IFERROR(VLOOKUP(C8,'COPY DATA XPRO'!$C$7:$AI$58,27,FALSE),0) -> 0 | AD8: =IFERROR(VLOOKUP(C8,'COPY DATA XPRO'!$C$7:$AI$58,28,FALSE),0) -> 0 | AE8: =IFERROR(VLOOKUP(C8,'COPY DATA XPRO'!$C$7:$AI$58,29,FALSE),0) -> 0 | AF8: =IFERROR(VLOOKUP(C8,'COPY DATA XPRO'!$C$7:$AI$58,30,FALSE),0) -> 0 | AG8: =IFERROR(VLOOKUP(C8,'COPY DATA XPRO'!$C$7:$AI$58,31,FALSE),0) -> 100 | AH8: =IFERROR(VLOOKUP(C8,'COPY DATA XPRO'!$C$7:$AI$58,32,FALSE),0) -> 100 | AI8: =IFERROR(VLOOKUP(C8,'COPY DATA XPRO'!$C$7:$AI$58,33,FALSE),0) -> 100
C9: JIMBARAN | D9: =IFERROR(VLOOKUP(C9,'COPY DATA XPRO'!$C$7:$AI$58,2,FALSE),0) -> 0 | E9: =IFERROR(VLOOKUP(C9,'COPY DATA XPRO'!$C$7:$AI$58,3,FALSE),0) -> 15 | F9: =IFERROR(VLOOKUP(C9,'COPY DATA XPRO'!$C$7:$AI$58,4,FALSE),0) -> 0 | G9: =IFERROR(VLOOKUP(C9,'COPY DATA XPRO'!$C$7:$AI$58,5,FALSE),0) -> 0 | H9: =IFERROR(VLOOKUP(C9,'COPY DATA XPRO'!$C$7:$AI$58,6,FALSE),0) -> 0 | I9: =IFERROR(VLOOKUP(C9,'COPY DATA XPRO'!$C$7:$AI$58,7,FALSE),0) -> 3 | J9: =IFERROR(VLOOKUP(C9,'COPY DATA XPRO'!$C$7:$AI$58,8,FALSE),0) -> 1 | K9: =IFERROR(VLOOKUP(C9,'COPY DATA XPRO'!$C$7:$AI$58,9,FALSE),0) -> 0 | L9: =IFERROR(VLOOKUP(C9,'COPY DATA XPRO'!$C$7:$AI$58,10,FALSE),0) -> 0 | M9: =IFERROR(VLOOKUP(C9,'COPY DATA XPRO'!$C$7:$AI$58,11,FALSE),0) -> 0 | N9: =IFERROR(VLOOKUP(C9,'COPY DATA XPRO'!$C$7:$AI$58,12,FALSE),0) -> 0 | O9: =IFERROR(VLOOKUP(C9,'COPY DATA XPRO'!$C$7:$AI$58,13,FALSE),0) -> 3 | P9: =IFERROR(VLOOKUP(C9,'COPY DATA XPRO'!$C$7:$AI$58,14,FALSE),0) -> 3 | Q9: =IFERROR(VLOOKUP(C9,'COPY DATA XPRO'!$C$7:$AI$58,15,FALSE),0) -> 1 | R9: =IFERROR(VLOOKUP(C9,'COPY DATA XPRO'!$C$7:$AI$58,16,FALSE),0) -> 0 | S9: =IFERROR(VLOOKUP(C9,'COPY DATA XPRO'!$C$7:$AI$58,17,FALSE),0) -> 0 | T9: =IFERROR(VLOOKUP(C9,'COPY DATA XPRO'!$C$7:$AI$58,18,FALSE),0) -> 0 | U9: =IFERROR(VLOOKUP(C9,'COPY DATA XPRO'!$C$7:$AI$58,19,FALSE),0) -> 0 | V9: =IFERROR(VLOOKUP(C9,'COPY DATA XPRO'!$C$7:$AI$58,20,FALSE),0) -> 0 | W9: =IFERROR(VLOOKUP(C9,'COPY DATA XPRO'!$C$7:$AI$58,21,FALSE),0) -> 0 | X9: =IFERROR(VLOOKUP(C9,'COPY DATA XPRO'!$C$7:$AI$58,22,FALSE),0) -> 1 | Y9: =IFERROR(VLOOKUP(C9,'COPY DATA XPRO'!$C$7:$AI$58,23,FALSE),0) -> 0 | Z9: =IFERROR(VLOOKUP(C9,'COPY DATA XPRO'!$C$7:$AI$58,24,FALSE),0) -> 5 | AA9: =IFERROR(VLOOKUP(C9,'COPY DATA XPRO'!$C$7:$AI$58,25,FALSE),0) -> 0 | AB9: =IFERROR(VLOOKUP(C9,'COPY DATA XPRO'!$C$7:$AI$58,26,FALSE),0) -> 0 | AC9: =IFERROR(VLOOKUP(C9,'COPY DATA XPRO'!$C$7:$AI$58,27,FALSE),0) -> 0 | AD9: =IFERROR(VLOOKUP(C9,'COPY DATA XPRO'!$C$7:$AI$58,28,FALSE),0) -> 0 | AE9: =IFERROR(VLOOKUP(C9,'COPY DATA XPRO'!$C$7:$AI$58,29,FALSE),0) -> 0 | AF9: =IFERROR(VLOOKUP(C9,'COPY DATA XPRO'!$C$7:$AI$58,30,FALSE),0) -> 2 | AG9: =IFERROR(VLOOKUP(C9,'COPY DATA XPRO'!$C$7:$AI$58,31,FALSE),0) -> 60 | AH9: =IFERROR(VLOOKUP(C9,'COPY DATA XPRO'!$C$7:$AI$58,32,FALSE),0) -> 50 | AI9: =IFERROR(VLOOKUP(C9,'COPY DATA XPRO'!$C$7:$AI$58,33,FALSE),0) -> 55.56
C10: KLUNGKUNG | D10: =IFERROR(VLOOKUP(C10,'COPY DATA XPRO'!$C$7:$AI$58,2,FALSE),0) -> 0 | E10: =IFERROR(VLOOKUP(C10,'COPY DATA XPRO'!$C$7:$AI$58,3,FALSE),0) -> 11 | F10: =IFERROR(VLOOKUP(C10,'COPY DATA XPRO'!$C$7:$AI$58,4,FALSE),0) -> 0 | G10: =IFERROR(VLOOKUP(C10,'COPY DATA XPRO'!$C$7:$AI$58,5,FALSE),0) -> 0 | H10: =IFERROR(VLOOKUP(C10,'COPY DATA XPRO'!$C$7:$AI$58,6,FALSE),0) -> 0 | I10: =IFERROR(VLOOKUP(C10,'COPY DATA XPRO'!$C$7:$AI$58,7,FALSE),0) -> 1 | J10: =IFERROR(VLOOKUP(C10,'COPY DATA XPRO'!$C$7:$AI$58,8,FALSE),0) -> 2 | K10: =IFERROR(VLOOKUP(C10,'COPY DATA XPRO'!$C$7:$AI$58,9,FALSE),0) -> 0 | L10: =IFERROR(VLOOKUP(C10,'COPY DATA XPRO'!$C$7:$AI$58,10,FALSE),0) -> 0 | M10: =IFERROR(VLOOKUP(C10,'COPY DATA XPRO'!$C$7:$AI$58,11,FALSE),0) -> 0 | N10: =IFERROR(VLOOKUP(C10,'COPY DATA XPRO'!$C$7:$AI$58,12,FALSE),0) -> 1 | O10: =IFERROR(VLOOKUP(C10,'COPY DATA XPRO'!$C$7:$AI$58,13,FALSE),0) -> 0 | P10: =IFERROR(VLOOKUP(C10,'COPY DATA XPRO'!$C$7:$AI$58,14,FALSE),0) -> 1 | Q10: =IFERROR(VLOOKUP(C10,'COPY DATA XPRO'!$C$7:$AI$58,15,FALSE),0) -> 0 | R10: =IFERROR(VLOOKUP(C10,'COPY DATA XPRO'!$C$7:$AI$58,16,FALSE),0) -> 0 | S10: =IFERROR(VLOOKUP(C10,'COPY DATA XPRO'!$C$7:$AI$58,17,FALSE),0) -> 0 | T10: =IFERROR(VLOOKUP(C10,'COPY DATA XPRO'!$C$7:$AI$58,18,FALSE),0) -> 0 | U10: =IFERROR(VLOOKUP(C10,'COPY DATA XPRO'!$C$7:$AI$58,19,FALSE),0) -> 0 | V10: =IFERROR(VLOOKUP(C10,'COPY DATA XPRO'!$C$7:$AI$58,20,FALSE),0) -> 0 | W10: =IFERROR(VLOOKUP(C10,'COPY DATA XPRO'!$C$7:$AI$58,21,FALSE),0) -> 0 | X10: =IFERROR(VLOOKUP(C10,'COPY DATA XPRO'!$C$7:$AI$58,22,FALSE),0) -> 0 | Y10: =IFERROR(VLOOKUP(C10,'COPY DATA XPRO'!$C$7:$AI$58,23,FALSE),0) -> 0 | Z10: =IFERROR(VLOOKUP(C10,'COPY DATA XPRO'!$C$7:$AI$58,24,FALSE),0) -> 6 | AA10: =IFERROR(VLOOKUP(C10,'COPY DATA XPRO'!$C$7:$AI$58,25,FALSE),0) -> 0 | AB10: =IFERROR(VLOOKUP(C10,'COPY DATA XPRO'!$C$7:$AI$58,26,FALSE),0) -> 0 | AC10: =IFERROR(VLOOKUP(C10,'COPY DATA XPRO'!$C$7:$AI$58,27,FALSE),0) -> 0 | AD10: =IFERROR(VLOOKUP(C10,'COPY DATA XPRO'!$C$7:$AI$58,28,FALSE),0) -> 0 | AE10: =IFERROR(VLOOKUP(C10,'COPY DATA XPRO'!$C$7:$AI$58,29,FALSE),0) -> 0 | AF10: =IFERROR(VLOOKUP(C10,'COPY DATA XPRO'!$C$7:$AI$58,30,FALSE),0) -> 1 | AG10: =IFERROR(VLOOKUP(C10,'COPY DATA XPRO'!$C$7:$AI$58,31,FALSE),0) -> 63.64 | AH10: =IFERROR(VLOOKUP(C10,'COPY DATA XPRO'!$C$7:$AI$58,32,FALSE),0) -> 66.67 | AI10: =IFERROR(VLOOKUP(C10,'COPY DATA XPRO'!$C$7:$AI$58,33,FALSE),0) -> 85.71
C11: SANUR | D11: =IFERROR(VLOOKUP(C11,'COPY DATA XPRO'!$C$7:$AI$58,2,FALSE),0) -> 0 | E11: =IFERROR(VLOOKUP(C11,'COPY DATA XPRO'!$C$7:$AI$58,3,FALSE),0) -> 14 | F11: =IFERROR(VLOOKUP(C11,'COPY DATA XPRO'!$C$7:$AI$58,4,FALSE),0) -> 0 | G11: =IFERROR(VLOOKUP(C11,'COPY DATA XPRO'!$C$7:$AI$58,5,FALSE),0) -> 0 | H11: =IFERROR(VLOOKUP(C11,'COPY DATA XPRO'!$C$7:$AI$58,6,FALSE),0) -> 0 | I11: =IFERROR(VLOOKUP(C11,'COPY DATA XPRO'!$C$7:$AI$58,7,FALSE),0) -> 1 | J11: =IFERROR(VLOOKUP(C11,'COPY DATA XPRO'!$C$7:$AI$58,8,FALSE),0) -> 1 | K11: =IFERROR(VLOOKUP(C11,'COPY DATA XPRO'!$C$7:$AI$58,9,FALSE),0) -> 0 | L11: =IFERROR(VLOOKUP(C11,'COPY DATA XPRO'!$C$7:$AI$58,10,FALSE),0) -> 0 | M11: =IFERROR(VLOOKUP(C11,'COPY DATA XPRO'!$C$7:$AI$58,11,FALSE),0) -> 0 | N11: =IFERROR(VLOOKUP(C11,'COPY DATA XPRO'!$C$7:$AI$58,12,FALSE),0) -> 0 | O11: =IFERROR(VLOOKUP(C11,'COPY DATA XPRO'!$C$7:$AI$58,13,FALSE),0) -> 0 | P11: =IFERROR(VLOOKUP(C11,'COPY DATA XPRO'!$C$7:$AI$58,14,FALSE),0) -> 0 | Q11: =IFERROR(VLOOKUP(C11,'COPY DATA XPRO'!$C$7:$AI$58,15,FALSE),0) -> 0 | R11: =IFERROR(VLOOKUP(C11,'COPY DATA XPRO'!$C$7:$AI$58,16,FALSE),0) -> 0 | S11: =IFERROR(VLOOKUP(C11,'COPY DATA XPRO'!$C$7:$AI$58,17,FALSE),0) -> 0 | T11: =IFERROR(VLOOKUP(C11,'COPY DATA XPRO'!$C$7:$AI$58,18,FALSE),0) -> 0 | U11: =IFERROR(VLOOKUP(C11,'COPY DATA XPRO'!$C$7:$AI$58,19,FALSE),0) -> 0 | V11: =IFERROR(VLOOKUP(C11,'COPY DATA XPRO'!$C$7:$AI$58,20,FALSE),0) -> 0 | W11: =IFERROR(VLOOKUP(C11,'COPY DATA XPRO'!$C$7:$AI$58,21,FALSE),0) -> 0 | X11: =IFERROR(VLOOKUP(C11,'COPY DATA XPRO'!$C$7:$AI$58,22,FALSE),0) -> 0 | Y11: =IFERROR(VLOOKUP(C11,'COPY DATA XPRO'!$C$7:$AI$58,23,FALSE),0) -> 1 | Z11: =IFERROR(VLOOKUP(C11,'COPY DATA XPRO'!$C$7:$AI$58,24,FALSE),0) -> 10 | AA11: =IFERROR(VLOOKUP(C11,'COPY DATA XPRO'!$C$7:$AI$58,25,FALSE),0) -> 0 | AB11: =IFERROR(VLOOKUP(C11,'COPY DATA XPRO'!$C$7:$AI$58,26,FALSE),0) -> 0 | AC11: =IFERROR(VLOOKUP(C11,'COPY DATA XPRO'!$C$7:$AI$58,27,FALSE),0) -> 0 | AD11: =IFERROR(VLOOKUP(C11,'COPY DATA XPRO'!$C$7:$AI$58,28,FALSE),0) -> 0 | AE11: =IFERROR(VLOOKUP(C11,'COPY DATA XPRO'!$C$7:$AI$58,29,FALSE),0) -> 0 | AF11: =IFERROR(VLOOKUP(C11,'COPY DATA XPRO'!$C$7:$AI$58,30,FALSE),0) -> 1 | AG11: =IFERROR(VLOOKUP(C11,'COPY DATA XPRO'!$C$7:$AI$58,31,FALSE),0) -> 78.57 | AH11: =IFERROR(VLOOKUP(C11,'COPY DATA XPRO'!$C$7:$AI$58,32,FALSE),0) -> 83.33 | AI11: =IFERROR(VLOOKUP(C11,'COPY DATA XPRO'!$C$7:$AI$58,33,FALSE),0) -> 90.91
C12: SINGARAJA | D12: =IFERROR(VLOOKUP(C12,'COPY DATA XPRO'!$C$7:$AI$58,2,FALSE),0) -> 0 | E12: =IFERROR(VLOOKUP(C12,'COPY DATA XPRO'!$C$7:$AI$58,3,FALSE),0) -> 7 | F12: =IFERROR(VLOOKUP(C12,'COPY DATA XPRO'!$C$7:$AI$58,4,FALSE),0) -> 0 | G12: =IFERROR(VLOOKUP(C12,'COPY DATA XPRO'!$C$7:$AI$58,5,FALSE),0) -> 0 | H12: =IFERROR(VLOOKUP(C12,'COPY DATA XPRO'!$C$7:$AI$58,6,FALSE),0) -> 0 | I12: =IFERROR(VLOOKUP(C12,'COPY DATA XPRO'!$C$7:$AI$58,7,FALSE),0) -> 0 | J12: =IFERROR(VLOOKUP(C12,'COPY DATA XPRO'!$C$7:$AI$58,8,FALSE),0) -> 0 | K12: =IFERROR(VLOOKUP(C12,'COPY DATA XPRO'!$C$7:$AI$58,9,FALSE),0) -> 0 | L12: =IFERROR(VLOOKUP(C12,'COPY DATA XPRO'!$C$7:$AI$58,10,FALSE),0) -> 0 | M12: =IFERROR(VLOOKUP(C12,'COPY DATA XPRO'!$C$7:$AI$58,11,FALSE),0) -> 0 | N12: =IFERROR(VLOOKUP(C12,'COPY DATA XPRO'!$C$7:$AI$58,12,FALSE),0) -> 0 | O12: =IFERROR(VLOOKUP(C12,'COPY DATA XPRO'!$C$7:$AI$58,13,FALSE),0) -> 1 | P12: =IFERROR(VLOOKUP(C12,'COPY DATA XPRO'!$C$7:$AI$58,14,FALSE),0) -> 1 | Q12: =IFERROR(VLOOKUP(C12,'COPY DATA XPRO'!$C$7:$AI$58,15,FALSE),0) -> 0 | R12: =IFERROR(VLOOKUP(C12,'COPY DATA XPRO'!$C$7:$AI$58,16,FALSE),0) -> 0 | S12: =IFERROR(VLOOKUP(C12,'COPY DATA XPRO'!$C$7:$AI$58,17,FALSE),0) -> 0 | T12: =IFERROR(VLOOKUP(C12,'COPY DATA XPRO'!$C$7:$AI$58,18,FALSE),0) -> 0 | U12: =IFERROR(VLOOKUP(C12,'COPY DATA XPRO'!$C$7:$AI$58,19,FALSE),0) -> 0 | V12: =IFERROR(VLOOKUP(C12,'COPY DATA XPRO'!$C$7:$AI$58,20,FALSE),0) -> 0 | W12: =IFERROR(VLOOKUP(C12,'COPY DATA XPRO'!$C$7:$AI$58,21,FALSE),0) -> 0 | X12: =IFERROR(VLOOKUP(C12,'COPY DATA XPRO'!$C$7:$AI$58,22,FALSE),0) -> 0 | Y12: =IFERROR(VLOOKUP(C12,'COPY DATA XPRO'!$C$7:$AI$58,23,FALSE),0) -> 0 | Z12: =IFERROR(VLOOKUP(C12,'COPY DATA XPRO'!$C$7:$AI$58,24,FALSE),0) -> 5 | AA12: =IFERROR(VLOOKUP(C12,'COPY DATA XPRO'!$C$7:$AI$58,25,FALSE),0) -> 0 | AB12: =IFERROR(VLOOKUP(C12,'COPY DATA XPRO'!$C$7:$AI$58,26,FALSE),0) -> 0 | AC12: =IFERROR(VLOOKUP(C12,'COPY DATA XPRO'!$C$7:$AI$58,27,FALSE),0) -> 0 | AD12: =IFERROR(VLOOKUP(C12,'COPY DATA XPRO'!$C$7:$AI$58,28,FALSE),0) -> 0 | AE12: =IFERROR(VLOOKUP(C12,'COPY DATA XPRO'!$C$7:$AI$58,29,FALSE),0) -> 0 | AF12: =IFERROR(VLOOKUP(C12,'COPY DATA XPRO'!$C$7:$AI$58,30,FALSE),0) -> 1 | AG12: =IFERROR(VLOOKUP(C12,'COPY DATA XPRO'!$C$7:$AI$58,31,FALSE),0) -> 85.71 | AH12: =IFERROR(VLOOKUP(C12,'COPY DATA XPRO'!$C$7:$AI$58,32,FALSE),0) -> 83.33 | AI12: =IFERROR(VLOOKUP(C12,'COPY DATA XPRO'!$C$7:$AI$58,33,FALSE),0) -> 83.33
C13: TABANAN | D13: =IFERROR(VLOOKUP(C13,'COPY DATA XPRO'!$C$7:$AI$58,2,FALSE),0) -> 0 | E13: =IFERROR(VLOOKUP(C13,'COPY DATA XPRO'!$C$7:$AI$58,3,FALSE),0) -> 48 | F13: =IFERROR(VLOOKUP(C13,'COPY DATA XPRO'!$C$7:$AI$58,4,FALSE),0) -> 1 | G13: =IFERROR(VLOOKUP(C13,'COPY DATA XPRO'!$C$7:$AI$58,5,FALSE),0) -> 0 | H13: =IFERROR(VLOOKUP(C13,'COPY DATA XPRO'!$C$7:$AI$58,6,FALSE),0) -> 0 | I13: =IFERROR(VLOOKUP(C13,'COPY DATA XPRO'!$C$7:$AI$58,7,FALSE),0) -> 2 | J13: =IFERROR(VLOOKUP(C13,'COPY DATA XPRO'!$C$7:$AI$58,8,FALSE),0) -> 1 | K13: =IFERROR(VLOOKUP(C13,'COPY DATA XPRO'!$C$7:$AI$58,9,FALSE),0) -> 10 | L13: =IFERROR(VLOOKUP(C13,'COPY DATA XPRO'!$C$7:$AI$58,10,FALSE),0) -> 0 | M13: =IFERROR(VLOOKUP(C13,'COPY DATA XPRO'!$C$7:$AI$58,11,FALSE),0) -> 0 | N13: =IFERROR(VLOOKUP(C13,'COPY DATA XPRO'!$C$7:$AI$58,12,FALSE),0) -> 2 | O13: =IFERROR(VLOOKUP(C13,'COPY DATA XPRO'!$C$7:$AI$58,13,FALSE),0) -> 1 | P13: =IFERROR(VLOOKUP(C13,'COPY DATA XPRO'!$C$7:$AI$58,14,FALSE),0) -> 3 | Q13: =IFERROR(VLOOKUP(C13,'COPY DATA XPRO'!$C$7:$AI$58,15,FALSE),0) -> 0 | R13: =IFERROR(VLOOKUP(C13,'COPY DATA XPRO'!$C$7:$AI$58,16,FALSE),0) -> 2 | S13: =IFERROR(VLOOKUP(C13,'COPY DATA XPRO'!$C$7:$AI$58,17,FALSE),0) -> 0 | T13: =IFERROR(VLOOKUP(C13,'COPY DATA XPRO'!$C$7:$AI$58,18,FALSE),0) -> 0 | U13: =IFERROR(VLOOKUP(C13,'COPY DATA XPRO'!$C$7:$AI$58,19,FALSE),0) -> 0 | V13: =IFERROR(VLOOKUP(C13,'COPY DATA XPRO'!$C$7:$AI$58,20,FALSE),0) -> 0 | W13: =IFERROR(VLOOKUP(C13,'COPY DATA XPRO'!$C$7:$AI$58,21,FALSE),0) -> 0 | X13: =IFERROR(VLOOKUP(C13,'COPY DATA XPRO'!$C$7:$AI$58,22,FALSE),0) -> 2 | Y13: =IFERROR(VLOOKUP(C13,'COPY DATA XPRO'!$C$7:$AI$58,23,FALSE),0) -> 0 | Z13: =IFERROR(VLOOKUP(C13,'COPY DATA XPRO'!$C$7:$AI$58,24,FALSE),0) -> 15 | AA13: =IFERROR(VLOOKUP(C13,'COPY DATA XPRO'!$C$7:$AI$58,25,FALSE),0) -> 0 | AB13: =IFERROR(VLOOKUP(C13,'COPY DATA XPRO'!$C$7:$AI$58,26,FALSE),0) -> 11 | AC13: =IFERROR(VLOOKUP(C13,'COPY DATA XPRO'!$C$7:$AI$58,27,FALSE),0) -> 0 | AD13: =IFERROR(VLOOKUP(C13,'COPY DATA XPRO'!$C$7:$AI$58,28,FALSE),0) -> 0 | AE13: =IFERROR(VLOOKUP(C13,'COPY DATA XPRO'!$C$7:$AI$58,29,FALSE),0) -> 11 | AF13: =IFERROR(VLOOKUP(C13,'COPY DATA XPRO'!$C$7:$AI$58,30,FALSE),0) -> 3 | AG13: =IFERROR(VLOOKUP(C13,'COPY DATA XPRO'!$C$7:$AI$58,31,FALSE),0) -> 64.58 | AH13: =IFERROR(VLOOKUP(C13,'COPY DATA XPRO'!$C$7:$AI$58,32,FALSE),0) -> 45.45 | AI13: =IFERROR(VLOOKUP(C13,'COPY DATA XPRO'!$C$7:$AI$58,33,FALSE),0) -> 75
C14: UBUNG | D14: =IFERROR(VLOOKUP(C14,'COPY DATA XPRO'!$C$7:$AI$58,2,FALSE),0) -> 0 | E14: =IFERROR(VLOOKUP(C14,'COPY DATA XPRO'!$C$7:$AI$58,3,FALSE),0) -> 18 | F14: =IFERROR(VLOOKUP(C14,'COPY DATA XPRO'!$C$7:$AI$58,4,FALSE),0) -> 0 | G14: =IFERROR(VLOOKUP(C14,'COPY DATA XPRO'!$C$7:$AI$58,5,FALSE),0) -> 0 | H14: =IFERROR(VLOOKUP(C14,'COPY DATA XPRO'!$C$7:$AI$58,6,FALSE),0) -> 0 | I14: =IFERROR(VLOOKUP(C14,'COPY DATA XPRO'!$C$7:$AI$58,7,FALSE),0) -> 0 | J14: =IFERROR(VLOOKUP(C14,'COPY DATA XPRO'!$C$7:$AI$58,8,FALSE),0) -> 0 | K14: =IFERROR(VLOOKUP(C14,'COPY DATA XPRO'!$C$7:$AI$58,9,FALSE),0) -> 0 | L14: =IFERROR(VLOOKUP(C14,'COPY DATA XPRO'!$C$7:$AI$58,10,FALSE),0) -> 0 | M14: =IFERROR(VLOOKUP(C14,'COPY DATA XPRO'!$C$7:$AI$58,11,FALSE),0) -> 0 | N14: =IFERROR(VLOOKUP(C14,'COPY DATA XPRO'!$C$7:$AI$58,12,FALSE),0) -> 2 | O14: =IFERROR(VLOOKUP(C14,'COPY DATA XPRO'!$C$7:$AI$58,13,FALSE),0) -> 2 | P14: =IFERROR(VLOOKUP(C14,'COPY DATA XPRO'!$C$7:$AI$58,14,FALSE),0) -> 4 | Q14: =IFERROR(VLOOKUP(C14,'COPY DATA XPRO'!$C$7:$AI$58,15,FALSE),0) -> 0 | R14: =IFERROR(VLOOKUP(C14,'COPY DATA XPRO'!$C$7:$AI$58,16,FALSE),0) -> 1 | S14: =IFERROR(VLOOKUP(C14,'COPY DATA XPRO'!$C$7:$AI$58,17,FALSE),0) -> 0 | T14: =IFERROR(VLOOKUP(C14,'COPY DATA XPRO'!$C$7:$AI$58,18,FALSE),0) -> 0 | U14: =IFERROR(VLOOKUP(C14,'COPY DATA XPRO'!$C$7:$AI$58,19,FALSE),0) -> 0 | V14: =IFERROR(VLOOKUP(C14,'COPY DATA XPRO'!$C$7:$AI$58,20,FALSE),0) -> 0 | W14: =IFERROR(VLOOKUP(C14,'COPY DATA XPRO'!$C$7:$AI$58,21,FALSE),0) -> 0 | X14: =IFERROR(VLOOKUP(C14,'COPY DATA XPRO'!$C$7:$AI$58,22,FALSE),0) -> 1 | Y14: =IFERROR(VLOOKUP(C14,'COPY DATA XPRO'!$C$7:$AI$58,23,FALSE),0) -> 0 | Z14: =IFERROR(VLOOKUP(C14,'COPY DATA XPRO'!$C$7:$AI$58,24,FALSE),0) -> 9 | AA14: =IFERROR(VLOOKUP(C14,'COPY DATA XPRO'!$C$7:$AI$58,25,FALSE),0) -> 1 | AB14: =IFERROR(VLOOKUP(C14,'COPY DATA XPRO'!$C$7:$AI$58,26,FALSE),0) -> 0 | AC14: =IFERROR(VLOOKUP(C14,'COPY DATA XPRO'!$C$7:$AI$58,27,FALSE),0) -> 0 | AD14: =IFERROR(VLOOKUP(C14,'COPY DATA XPRO'!$C$7:$AI$58,28,FALSE),0) -> 0 | AE14: =IFERROR(VLOOKUP(C14,'COPY DATA XPRO'!$C$7:$AI$58,29,FALSE),0) -> 1 | AF14: =IFERROR(VLOOKUP(C14,'COPY DATA XPRO'!$C$7:$AI$58,30,FALSE),0) -> 3 | AG14: =IFERROR(VLOOKUP(C14,'COPY DATA XPRO'!$C$7:$AI$58,31,FALSE),0) -> 83.33 | AH14: =IFERROR(VLOOKUP(C14,'COPY DATA XPRO'!$C$7:$AI$58,32,FALSE),0) -> 60 | AI14: =IFERROR(VLOOKUP(C14,'COPY DATA XPRO'!$C$7:$AI$58,33,FALSE),0) -> 64.29
B15: JATIM BARAT | C15: BATU | D15: =IFERROR(VLOOKUP(C15,'COPY DATA XPRO'!$C$7:$AI$58,2,FALSE),0) -> 0 | E15: =IFERROR(VLOOKUP(C15,'COPY DATA XPRO'!$C$7:$AI$58,3,FALSE),0) -> 31 | F15: =IFERROR(VLOOKUP(C15,'COPY DATA XPRO'!$C$7:$AI$58,4,FALSE),0) -> 0 | G15: =IFERROR(VLOOKUP(C15,'COPY DATA XPRO'!$C$7:$AI$58,5,FALSE),0) -> 1 | H15: =IFERROR(VLOOKUP(C15,'COPY DATA XPRO'!$C$7:$AI$58,6,FALSE),0) -> 2 | I15: =IFERROR(VLOOKUP(C15,'COPY DATA XPRO'!$C$7:$AI$58,7,FALSE),0) -> 0 | J15: =IFERROR(VLOOKUP(C15,'COPY DATA XPRO'!$C$7:$AI$58,8,FALSE),0) -> 8 | K15: =IFERROR(VLOOKUP(C15,'COPY DATA XPRO'!$C$7:$AI$58,9,FALSE),0) -> 0 | L15: =IFERROR(VLOOKUP(C15,'COPY DATA XPRO'!$C$7:$AI$58,10,FALSE),0) -> 0 | M15: =IFERROR(VLOOKUP(C15,'COPY DATA XPRO'!$C$7:$AI$58,11,FALSE),0) -> 0 | N15: =IFERROR(VLOOKUP(C15,'COPY DATA XPRO'!$C$7:$AI$58,12,FALSE),0) -> 0 | O15: =IFERROR(VLOOKUP(C15,'COPY DATA XPRO'!$C$7:$AI$58,13,FALSE),0) -> 0 | P15: =IFERROR(VLOOKUP(C15,'COPY DATA XPRO'!$C$7:$AI$58,14,FALSE),0) -> 0 | Q15: =IFERROR(VLOOKUP(C15,'COPY DATA XPRO'!$C$7:$AI$58,15,FALSE),0) -> 0 | R15: =IFERROR(VLOOKUP(C15,'COPY DATA XPRO'!$C$7:$AI$58,16,FALSE),0) -> 0 | S15: =IFERROR(VLOOKUP(C15,'COPY DATA XPRO'!$C$7:$AI$58,17,FALSE),0) -> 0 | T15: =IFERROR(VLOOKUP(C15,'COPY DATA XPRO'!$C$7:$AI$58,18,FALSE),0) -> 0 | U15: =IFERROR(VLOOKUP(C15,'COPY DATA XPRO'!$C$7:$AI$58,19,FALSE),0) -> 0 | V15: =IFERROR(VLOOKUP(C15,'COPY DATA XPRO'!$C$7:$AI$58,20,FALSE),0) -> 0 | W15: =IFERROR(VLOOKUP(C15,'COPY DATA XPRO'!$C$7:$AI$58,21,FALSE),0) -> 0 | X15: =IFERROR(VLOOKUP(C15,'COPY DATA XPRO'!$C$7:$AI$58,22,FALSE),0) -> 0 | Y15: =IFERROR(VLOOKUP(C15,'COPY DATA XPRO'!$C$7:$AI$58,23,FALSE),0) -> 0 | Z15: =IFERROR(VLOOKUP(C15,'COPY DATA XPRO'!$C$7:$AI$58,24,FALSE),0) -> 16 | AA15: =IFERROR(VLOOKUP(C15,'COPY DATA XPRO'!$C$7:$AI$58,25,FALSE),0) -> 0 | AB15: =IFERROR(VLOOKUP(C15,'COPY DATA XPRO'!$C$7:$AI$58,26,FALSE),0) -> 0 | AC15: =IFERROR(VLOOKUP(C15,'COPY DATA XPRO'!$C$7:$AI$58,27,FALSE),0) -> 0 | AD15: =IFERROR(VLOOKUP(C15,'COPY DATA XPRO'!$C$7:$AI$58,28,FALSE),0) -> 3 | AE15: =IFERROR(VLOOKUP(C15,'COPY DATA XPRO'!$C$7:$AI$58,29,FALSE),0) -> 3 | AF15: =IFERROR(VLOOKUP(C15,'COPY DATA XPRO'!$C$7:$AI$58,30,FALSE),0) -> 1 | AG15: =IFERROR(VLOOKUP(C15,'COPY DATA XPRO'!$C$7:$AI$58,31,FALSE),0) -> 61.29 | AH15: =IFERROR(VLOOKUP(C15,'COPY DATA XPRO'!$C$7:$AI$58,32,FALSE),0) -> 53.33 | AI15: =IFERROR(VLOOKUP(C15,'COPY DATA XPRO'!$C$7:$AI$58,33,FALSE),0) -> 100
C16: BLITAR | D16: =IFERROR(VLOOKUP(C16,'COPY DATA XPRO'!$C$7:$AI$58,2,FALSE),0) -> 0 | E16: =IFERROR(VLOOKUP(C16,'COPY DATA XPRO'!$C$7:$AI$58,3,FALSE),0) -> 12 | F16: =IFERROR(VLOOKUP(C16,'COPY DATA XPRO'!$C$7:$AI$58,4,FALSE),0) -> 0 | G16: =IFERROR(VLOOKUP(C16,'COPY DATA XPRO'!$C$7:$AI$58,5,FALSE),0) -> 0 | H16: =IFERROR(VLOOKUP(C16,'COPY DATA XPRO'!$C$7:$AI$58,6,FALSE),0) -> 0 | I16: =IFERROR(VLOOKUP(C16,'COPY DATA XPRO'!$C$7:$AI$58,7,FALSE),0) -> 0 | J16: =IFERROR(VLOOKUP(C16,'COPY DATA XPRO'!$C$7:$AI$58,8,FALSE),0) -> 0 | K16: =IFERROR(VLOOKUP(C16,'COPY DATA XPRO'!$C$7:$AI$58,9,FALSE),0) -> 0 | L16: =IFERROR(VLOOKUP(C16,'COPY DATA XPRO'!$C$7:$AI$58,10,FALSE),0) -> 0 | M16: =IFERROR(VLOOKUP(C16,'COPY DATA XPRO'!$C$7:$AI$58,11,FALSE),0) -> 0 | N16: =IFERROR(VLOOKUP(C16,'COPY DATA XPRO'!$C$7:$AI$58,12,FALSE),0) -> 0 | O16: =IFERROR(VLOOKUP(C16,'COPY DATA XPRO'!$C$7:$AI$58,13,FALSE),0) -> 0 | P16: =IFERROR(VLOOKUP(C16,'COPY DATA XPRO'!$C$7:$AI$58,14,FALSE),0) -> 0 | Q16: =IFERROR(VLOOKUP(C16,'COPY DATA XPRO'!$C$7:$AI$58,15,FALSE),0) -> 0 | R16: =IFERROR(VLOOKUP(C16,'COPY DATA XPRO'!$C$7:$AI$58,16,FALSE),0) -> 0 | S16: =IFERROR(VLOOKUP(C16,'COPY DATA XPRO'!$C$7:$AI$58,17,FALSE),0) -> 0 | T16: =IFERROR(VLOOKUP(C16,'COPY DATA XPRO'!$C$7:$AI$58,18,FALSE),0) -> 0 | U16: =IFERROR(VLOOKUP(C16,'COPY DATA XPRO'!$C$7:$AI$58,19,FALSE),0) -> 0 | V16: =IFERROR(VLOOKUP(C16,'COPY DATA XPRO'!$C$7:$AI$58,20,FALSE),0) -> 0 | W16: =IFERROR(VLOOKUP(C16,'COPY DATA XPRO'!$C$7:$AI$58,21,FALSE),0) -> 0 | X16: =IFERROR(VLOOKUP(C16,'COPY DATA XPRO'!$C$7:$AI$58,22,FALSE),0) -> 0 | Y16: =IFERROR(VLOOKUP(C16,'COPY DATA XPRO'!$C$7:$AI$58,23,FALSE),0) -> 0 | Z16: =IFERROR(VLOOKUP(C16,'COPY DATA XPRO'!$C$7:$AI$58,24,FALSE),0) -> 12 | AA16: =IFERROR(VLOOKUP(C16,'COPY DATA XPRO'!$C$7:$AI$58,25,FALSE),0) -> 0 | AB16: =IFERROR(VLOOKUP(C16,'COPY DATA XPRO'!$C$7:$AI$58,26,FALSE),0) -> 0 | AC16: =IFERROR(VLOOKUP(C16,'COPY DATA XPRO'!$C$7:$AI$58,27,FALSE),0) -> 0 | AD16: =IFERROR(VLOOKUP(C16,'COPY DATA XPRO'!$C$7:$AI$58,28,FALSE),0) -> 0 | AE16: =IFERROR(VLOOKUP(C16,'COPY DATA XPRO'!$C$7:$AI$58,29,FALSE),0) -> 0 | AF16: =IFERROR(VLOOKUP(C16,'COPY DATA XPRO'!$C$7:$AI$58,30,FALSE),0) -> 0 | AG16: =IFERROR(VLOOKUP(C16,'COPY DATA XPRO'!$C$7:$AI$58,31,FALSE),0) -> 100 | AH16: =IFERROR(VLOOKUP(C16,'COPY DATA XPRO'!$C$7:$AI$58,32,FALSE),0) -> 100 | AI16: =IFERROR(VLOOKUP(C16,'COPY DATA XPRO'!$C$7:$AI$58,33,FALSE),0) -> 100
C17: BOJONEGORO | D17: =IFERROR(VLOOKUP(C17,'COPY DATA XPRO'!$C$7:$AI$58,2,FALSE),0) -> 0 | E17: =IFERROR(VLOOKUP(C17,'COPY DATA XPRO'!$C$7:$AI$58,3,FALSE),0) -> 21 | F17: =IFERROR(VLOOKUP(C17,'COPY DATA XPRO'!$C$7:$AI$58,4,FALSE),0) -> 0 | G17: =IFERROR(VLOOKUP(C17,'COPY DATA XPRO'!$C$7:$AI$58,5,FALSE),0) -> 0 | H17: =IFERROR(VLOOKUP(C17,'COPY DATA XPRO'!$C$7:$AI$58,6,FALSE),0) -> 0 | I17: =IFERROR(VLOOKUP(C17,'COPY DATA XPRO'!$C$7:$AI$58,7,FALSE),0) -> 1 | J17: =IFERROR(VLOOKUP(C17,'COPY DATA XPRO'!$C$7:$AI$58,8,FALSE),0) -> 0 | K17: =IFERROR(VLOOKUP(C17,'COPY DATA XPRO'!$C$7:$AI$58,9,FALSE),0) -> 0 | L17: =IFERROR(VLOOKUP(C17,'COPY DATA XPRO'!$C$7:$AI$58,10,FALSE),0) -> 0 | M17: =IFERROR(VLOOKUP(C17,'COPY DATA XPRO'!$C$7:$AI$58,11,FALSE),0) -> 0 | N17: =IFERROR(VLOOKUP(C17,'COPY DATA XPRO'!$C$7:$AI$58,12,FALSE),0) -> 0 | O17: =IFERROR(VLOOKUP(C17,'COPY DATA XPRO'!$C$7:$AI$58,13,FALSE),0) -> 0 | P17: =IFERROR(VLOOKUP(C17,'COPY DATA XPRO'!$C$7:$AI$58,14,FALSE),0) -> 0 | Q17: =IFERROR(VLOOKUP(C17,'COPY DATA XPRO'!$C$7:$AI$58,15,FALSE),0) -> 0 | R17: =IFERROR(VLOOKUP(C17,'COPY DATA XPRO'!$C$7:$AI$58,16,FALSE),0) -> 0 | S17: =IFERROR(VLOOKUP(C17,'COPY DATA XPRO'!$C$7:$AI$58,17,FALSE),0) -> 0 | T17: =IFERROR(VLOOKUP(C17,'COPY DATA XPRO'!$C$7:$AI$58,18,FALSE),0) -> 0 | U17: =IFERROR(VLOOKUP(C17,'COPY DATA XPRO'!$C$7:$AI$58,19,FALSE),0) -> 0 | V17: =IFERROR(VLOOKUP(C17,'COPY DATA XPRO'!$C$7:$AI$58,20,FALSE),0) -> 0 | W17: =IFERROR(VLOOKUP(C17,'COPY DATA XPRO'!$C$7:$AI$58,21,FALSE),0) -> 0 | X17: =IFERROR(VLOOKUP(C17,'COPY DATA XPRO'!$C$7:$AI$58,22,FALSE),0) -> 0 | Y17: =IFERROR(VLOOKUP(C17,'COPY DATA XPRO'!$C$7:$AI$58,23,FALSE),0) -> 1 | Z17: =IFERROR(VLOOKUP(C17,'COPY DATA XPRO'!$C$7:$AI$58,24,FALSE),0) -> 16 | AA17: =IFERROR(VLOOKUP(C17,'COPY DATA XPRO'!$C$7:$AI$58,25,FALSE),0) -> 0 | AB17: =IFERROR(VLOOKUP(C17,'COPY DATA XPRO'!$C$7:$AI$58,26,FALSE),0) -> 0 | AC17: =IFERROR(VLOOKUP(C17,'COPY DATA XPRO'!$C$7:$AI$58,27,FALSE),0) -> 0 | AD17: =IFERROR(VLOOKUP(C17,'COPY DATA XPRO'!$C$7:$AI$58,28,FALSE),0) -> 0 | AE17: =IFERROR(VLOOKUP(C17,'COPY DATA XPRO'!$C$7:$AI$58,29,FALSE),0) -> 0 | AF17: =IFERROR(VLOOKUP(C17,'COPY DATA XPRO'!$C$7:$AI$58,30,FALSE),0) -> 3 | AG17: =IFERROR(VLOOKUP(C17,'COPY DATA XPRO'!$C$7:$AI$58,31,FALSE),0) -> 80.95 | AH17: =IFERROR(VLOOKUP(C17,'COPY DATA XPRO'!$C$7:$AI$58,32,FALSE),0) -> 94.12 | AI17: =IFERROR(VLOOKUP(C17,'COPY DATA XPRO'!$C$7:$AI$58,33,FALSE),0) -> 94.12
C18: KEDIRI | D18: =IFERROR(VLOOKUP(C18,'COPY DATA XPRO'!$C$7:$AI$58,2,FALSE),0) -> 0 | E18: =IFERROR(VLOOKUP(C18,'COPY DATA XPRO'!$C$7:$AI$58,3,FALSE),0) -> 33 | F18: =IFERROR(VLOOKUP(C18,'COPY DATA XPRO'!$C$7:$AI$58,4,FALSE),0) -> 0 | G18: =IFERROR(VLOOKUP(C18,'COPY DATA XPRO'!$C$7:$AI$58,5,FALSE),0) -> 0 | H18: =IFERROR(VLOOKUP(C18,'COPY DATA XPRO'!$C$7:$AI$58,6,FALSE),0) -> 1 | I18: =IFERROR(VLOOKUP(C18,'COPY DATA XPRO'!$C$7:$AI$58,7,FALSE),0) -> 0 | J18: =IFERROR(VLOOKUP(C18,'COPY DATA XPRO'!$C$7:$AI$58,8,FALSE),0) -> 0 | K18: =IFERROR(VLOOKUP(C18,'COPY DATA XPRO'!$C$7:$AI$58,9,FALSE),0) -> 0 | L18: =IFERROR(VLOOKUP(C18,'COPY DATA XPRO'!$C$7:$AI$58,10,FALSE),0) -> 0 | M18: =IFERROR(VLOOKUP(C18,'COPY DATA XPRO'!$C$7:$AI$58,11,FALSE),0) -> 0 | N18: =IFERROR(VLOOKUP(C18,'COPY DATA XPRO'!$C$7:$AI$58,12,FALSE),0) -> 0 | O18: =IFERROR(VLOOKUP(C18,'COPY DATA XPRO'!$C$7:$AI$58,13,FALSE),0) -> 0 | P18: =IFERROR(VLOOKUP(C18,'COPY DATA XPRO'!$C$7:$AI$58,14,FALSE),0) -> 0 | Q18: =IFERROR(VLOOKUP(C18,'COPY DATA XPRO'!$C$7:$AI$58,15,FALSE),0) -> 0 | R18: =IFERROR(VLOOKUP(C18,'COPY DATA XPRO'!$C$7:$AI$58,16,FALSE),0) -> 0 | S18: =IFERROR(VLOOKUP(C18,'COPY DATA XPRO'!$C$7:$AI$58,17,FALSE),0) -> 0 | T18: =IFERROR(VLOOKUP(C18,'COPY DATA XPRO'!$C$7:$AI$58,18,FALSE),0) -> 0 | U18: =IFERROR(VLOOKUP(C18,'COPY DATA XPRO'!$C$7:$AI$58,19,FALSE),0) -> 0 | V18: =IFERROR(VLOOKUP(C18,'COPY DATA XPRO'!$C$7:$AI$58,20,FALSE),0) -> 0 | W18: =IFERROR(VLOOKUP(C18,'COPY DATA XPRO'!$C$7:$AI$58,21,FALSE),0) -> 0 | X18: =IFERROR(VLOOKUP(C18,'COPY DATA XPRO'!$C$7:$AI$58,22,FALSE),0) -> 0 | Y18: =IFERROR(VLOOKUP(C18,'COPY DATA XPRO'!$C$7:$AI$58,23,FALSE),0) -> 1 | Z18: =IFERROR(VLOOKUP(C18,'COPY DATA XPRO'!$C$7:$AI$58,24,FALSE),0) -> 30 | AA18: =IFERROR(VLOOKUP(C18,'COPY DATA XPRO'!$C$7:$AI$58,25,FALSE),0) -> 0 | AB18: =IFERROR(VLOOKUP(C18,'COPY DATA XPRO'!$C$7:$AI$58,26,FALSE),0) -> 0 | AC18: =IFERROR(VLOOKUP(C18,'COPY DATA XPRO'!$C$7:$AI$58,27,FALSE),0) -> 0 | AD18: =IFERROR(VLOOKUP(C18,'COPY DATA XPRO'!$C$7:$AI$58,28,FALSE),0) -> 1 | AE18: =IFERROR(VLOOKUP(C18,'COPY DATA XPRO'!$C$7:$AI$58,29,FALSE),0) -> 1 | AF18: =IFERROR(VLOOKUP(C18,'COPY DATA XPRO'!$C$7:$AI$58,30,FALSE),0) -> 0 | AG18: =IFERROR(VLOOKUP(C18,'COPY DATA XPRO'!$C$7:$AI$58,31,FALSE),0) -> 96.97 | AH18: =IFERROR(VLOOKUP(C18,'COPY DATA XPRO'!$C$7:$AI$58,32,FALSE),0) -> 90.91 | AI18: =IFERROR(VLOOKUP(C18,'COPY DATA XPRO'!$C$7:$AI$58,33,FALSE),0) -> 96.77
C19: KEPANJEN | D19: =IFERROR(VLOOKUP(C19,'COPY DATA XPRO'!$C$7:$AI$58,2,FALSE),0) -> 0 | E19: =IFERROR(VLOOKUP(C19,'COPY DATA XPRO'!$C$7:$AI$58,3,FALSE),0) -> 34 | F19: =IFERROR(VLOOKUP(C19,'COPY DATA XPRO'!$C$7:$AI$58,4,FALSE),0) -> 0 | G19: =IFERROR(VLOOKUP(C19,'COPY DATA XPRO'!$C$7:$AI$58,5,FALSE),0) -> 0 | H19: =IFERROR(VLOOKUP(C19,'COPY DATA XPRO'!$C$7:$AI$58,6,FALSE),0) -> 0 | I19: =IFERROR(VLOOKUP(C19,'COPY DATA XPRO'!$C$7:$AI$58,7,FALSE),0) -> 0 | J19: =IFERROR(VLOOKUP(C19,'COPY DATA XPRO'!$C$7:$AI$58,8,FALSE),0) -> 0 | K19: =IFERROR(VLOOKUP(C19,'COPY DATA XPRO'!$C$7:$AI$58,9,FALSE),0) -> 0 | L19: =IFERROR(VLOOKUP(C19,'COPY DATA XPRO'!$C$7:$AI$58,10,FALSE),0) -> 0 | M19: =IFERROR(VLOOKUP(C19,'COPY DATA XPRO'!$C$7:$AI$58,11,FALSE),0) -> 0 | N19: =IFERROR(VLOOKUP(C19,'COPY DATA XPRO'!$C$7:$AI$58,12,FALSE),0) -> 0 | O19: =IFERROR(VLOOKUP(C19,'COPY DATA XPRO'!$C$7:$AI$58,13,FALSE),0) -> 0 | P19: =IFERROR(VLOOKUP(C19,'COPY DATA XPRO'!$C$7:$AI$58,14,FALSE),0) -> 0 | Q19: =IFERROR(VLOOKUP(C19,'COPY DATA XPRO'!$C$7:$AI$58,15,FALSE),0) -> 0 | R19: =IFERROR(VLOOKUP(C19,'COPY DATA XPRO'!$C$7:$AI$58,16,FALSE),0) -> 0 | S19: =IFERROR(VLOOKUP(C19,'COPY DATA XPRO'!$C$7:$AI$58,17,FALSE),0) -> 0 | T19: =IFERROR(VLOOKUP(C19,'COPY DATA XPRO'!$C$7:$AI$58,18,FALSE),0) -> 0 | U19: =IFERROR(VLOOKUP(C19,'COPY DATA XPRO'!$C$7:$AI$58,19,FALSE),0) -> 0 | V19: =IFERROR(VLOOKUP(C19,'COPY DATA XPRO'!$C$7:$AI$58,20,FALSE),0) -> 0 | W19: =IFERROR(VLOOKUP(C19,'COPY DATA XPRO'!$C$7:$AI$58,21,FALSE),0) -> 0 | X19: =IFERROR(VLOOKUP(C19,'COPY DATA XPRO'!$C$7:$AI$58,22,FALSE),0) -> 0 | Y19: =IFERROR(VLOOKUP(C19,'COPY DATA XPRO'!$C$7:$AI$58,23,FALSE),0) -> 0 | Z19: =IFERROR(VLOOKUP(C19,'COPY DATA XPRO'!$C$7:$AI$58,24,FALSE),0) -> 31 | AA19: =IFERROR(VLOOKUP(C19,'COPY DATA XPRO'!$C$7:$AI$58,25,FALSE),0) -> 0 | AB19: =IFERROR(VLOOKUP(C19,'COPY DATA XPRO'!$C$7:$AI$58,26,FALSE),0) -> 0 | AC19: =IFERROR(VLOOKUP(C19,'COPY DATA XPRO'!$C$7:$AI$58,27,FALSE),0) -> 0 | AD19: =IFERROR(VLOOKUP(C19,'COPY DATA XPRO'!$C$7:$AI$58,28,FALSE),0) -> 0 | AE19: =IFERROR(VLOOKUP(C19,'COPY DATA XPRO'!$C$7:$AI$58,29,FALSE),0) -> 0 | AF19: =IFERROR(VLOOKUP(C19,'COPY DATA XPRO'!$C$7:$AI$58,30,FALSE),0) -> 3 | AG19: =IFERROR(VLOOKUP(C19,'COPY DATA XPRO'!$C$7:$AI$58,31,FALSE),0) -> 91.18 | AH19: =IFERROR(VLOOKUP(C19,'COPY DATA XPRO'!$C$7:$AI$58,32,FALSE),0) -> 100 | AI19: =IFERROR(VLOOKUP(C19,'COPY DATA XPRO'!$C$7:$AI$58,33,FALSE),0) -> 100
C20: MADIUN | D20: =IFERROR(VLOOKUP(C20,'COPY DATA XPRO'!$C$7:$AI$58,2,FALSE),0) -> 0 | E20: =IFERROR(VLOOKUP(C20,'COPY DATA XPRO'!$C$7:$AI$58,3,FALSE),0) -> 8 | F20: =IFERROR(VLOOKUP(C20,'COPY DATA XPRO'!$C$7:$AI$58,4,FALSE),0) -> 0 | G20: =IFERROR(VLOOKUP(C20,'COPY DATA XPRO'!$C$7:$AI$58,5,FALSE),0) -> 0 | H20: =IFERROR(VLOOKUP(C20,'COPY DATA XPRO'!$C$7:$AI$58,6,FALSE),0) -> 0 | I20: =IFERROR(VLOOKUP(C20,'COPY DATA XPRO'!$C$7:$AI$58,7,FALSE),0) -> 0 | J20: =IFERROR(VLOOKUP(C20,'COPY DATA XPRO'!$C$7:$AI$58,8,FALSE),0) -> 0 | K20: =IFERROR(VLOOKUP(C20,'COPY DATA XPRO'!$C$7:$AI$58,9,FALSE),0) -> 0 | L20: =IFERROR(VLOOKUP(C20,'COPY DATA XPRO'!$C$7:$AI$58,10,FALSE),0) -> 0 | M20: =IFERROR(VLOOKUP(C20,'COPY DATA XPRO'!$C$7:$AI$58,11,FALSE),0) -> 0 | N20: =IFERROR(VLOOKUP(C20,'COPY DATA XPRO'!$C$7:$AI$58,12,FALSE),0) -> 0 | O20: =IFERROR(VLOOKUP(C20,'COPY DATA XPRO'!$C$7:$AI$58,13,FALSE),0) -> 0 | P20: =IFERROR(VLOOKUP(C20,'COPY DATA XPRO'!$C$7:$AI$58,14,FALSE),0) -> 0 | Q20: =IFERROR(VLOOKUP(C20,'COPY DATA XPRO'!$C$7:$AI$58,15,FALSE),0) -> 0 | R20: =IFERROR(VLOOKUP(C20,'COPY DATA XPRO'!$C$7:$AI$58,16,FALSE),0) -> 0 | S20: =IFERROR(VLOOKUP(C20,'COPY DATA XPRO'!$C$7:$AI$58,17,FALSE),0) -> 0 | T20: =IFERROR(VLOOKUP(C20,'COPY DATA XPRO'!$C$7:$AI$58,18,FALSE),0) -> 0 | U20: =IFERROR(VLOOKUP(C20,'COPY DATA XPRO'!$C$7:$AI$58,19,FALSE),0) -> 0 | V20: =IFERROR(VLOOKUP(C20,'COPY DATA XPRO'!$C$7:$AI$58,20,FALSE),0) -> 0 | W20: =IFERROR(VLOOKUP(C20,'COPY DATA XPRO'!$C$7:$AI$58,21,FALSE),0) -> 0 | X20: =IFERROR(VLOOKUP(C20,'COPY DATA XPRO'!$C$7:$AI$58,22,FALSE),0) -> 0 | Y20: =IFERROR(VLOOKUP(C20,'COPY DATA XPRO'!$C$7:$AI$58,23,FALSE),0) -> 0 | Z20: =IFERROR(VLOOKUP(C20,'COPY DATA XPRO'!$C$7:$AI$58,24,FALSE),0) -> 7 | AA20: =IFERROR(VLOOKUP(C20,'COPY DATA XPRO'!$C$7:$AI$58,25,FALSE),0) -> 0 | AB20: =IFERROR(VLOOKUP(C20,'COPY DATA XPRO'!$C$7:$AI$58,26,FALSE),0) -> 0 | AC20: =IFERROR(VLOOKUP(C20,'COPY DATA XPRO'!$C$7:$AI$58,27,FALSE),0) -> 0 | AD20: =IFERROR(VLOOKUP(C20,'COPY DATA XPRO'!$C$7:$AI$58,28,FALSE),0) -> 0 | AE20: =IFERROR(VLOOKUP(C20,'COPY DATA XPRO'!$C$7:$AI$58,29,FALSE),0) -> 0 | AF20: =IFERROR(VLOOKUP(C20,'COPY DATA XPRO'!$C$7:$AI$58,30,FALSE),0) -> 0 | AG20: =IFERROR(VLOOKUP(C20,'COPY DATA XPRO'!$C$7:$AI$58,31,FALSE),0) -> 87.5 | AH20: =IFERROR(VLOOKUP(C20,'COPY DATA XPRO'!$C$7:$AI$58,32,FALSE),0) -> 87.5 | AI20: =IFERROR(VLOOKUP(C20,'COPY DATA XPRO'!$C$7:$AI$58,33,FALSE),0) -> 100
C21: NGANJUK | D21: =IFERROR(VLOOKUP(C21,'COPY DATA XPRO'!$C$7:$AI$58,2,FALSE),0) -> 0 | E21: =IFERROR(VLOOKUP(C21,'COPY DATA XPRO'!$C$7:$AI$58,3,FALSE),0) -> 20 | F21: =IFERROR(VLOOKUP(C21,'COPY DATA XPRO'!$C$7:$AI$58,4,FALSE),0) -> 0 | G21: =IFERROR(VLOOKUP(C21,'COPY DATA XPRO'!$C$7:$AI$58,5,FALSE),0) -> 0 | H21: =IFERROR(VLOOKUP(C21,'COPY DATA XPRO'!$C$7:$AI$58,6,FALSE),0) -> 0 | I21: =IFERROR(VLOOKUP(C21,'COPY DATA XPRO'!$C$7:$AI$58,7,FALSE),0) -> 0 | J21: =IFERROR(VLOOKUP(C21,'COPY DATA XPRO'!$C$7:$AI$58,8,FALSE),0) -> 1 | K21: =IFERROR(VLOOKUP(C21,'COPY DATA XPRO'!$C$7:$AI$58,9,FALSE),0) -> 5 | L21: =IFERROR(VLOOKUP(C21,'COPY DATA XPRO'!$C$7:$AI$58,10,FALSE),0) -> 0 | M21: =IFERROR(VLOOKUP(C21,'COPY DATA XPRO'!$C$7:$AI$58,11,FALSE),0) -> 0 | N21: =IFERROR(VLOOKUP(C21,'COPY DATA XPRO'!$C$7:$AI$58,12,FALSE),0) -> 1 | O21: =IFERROR(VLOOKUP(C21,'COPY DATA XPRO'!$C$7:$AI$58,13,FALSE),0) -> 0 | P21: =IFERROR(VLOOKUP(C21,'COPY DATA XPRO'!$C$7:$AI$58,14,FALSE),0) -> 1 | Q21: =IFERROR(VLOOKUP(C21,'COPY DATA XPRO'!$C$7:$AI$58,15,FALSE),0) -> 0 | R21: =IFERROR(VLOOKUP(C21,'COPY DATA XPRO'!$C$7:$AI$58,16,FALSE),0) -> 0 | S21: =IFERROR(VLOOKUP(C21,'COPY DATA XPRO'!$C$7:$AI$58,17,FALSE),0) -> 0 | T21: =IFERROR(VLOOKUP(C21,'COPY DATA XPRO'!$C$7:$AI$58,18,FALSE),0) -> 0 | U21: =IFERROR(VLOOKUP(C21,'COPY DATA XPRO'!$C$7:$AI$58,19,FALSE),0) -> 0 | V21: =IFERROR(VLOOKUP(C21,'COPY DATA XPRO'!$C$7:$AI$58,20,FALSE),0) -> 0 | W21: =IFERROR(VLOOKUP(C21,'COPY DATA XPRO'!$C$7:$AI$58,21,FALSE),0) -> 0 | X21: =IFERROR(VLOOKUP(C21,'COPY DATA XPRO'!$C$7:$AI$58,22,FALSE),0) -> 0 | Y21: =IFERROR(VLOOKUP(C21,'COPY DATA XPRO'!$C$7:$AI$58,23,FALSE),0) -> 1 | Z21: =IFERROR(VLOOKUP(C21,'COPY DATA XPRO'!$C$7:$AI$58,24,FALSE),0) -> 9 | AA21: =IFERROR(VLOOKUP(C21,'COPY DATA XPRO'!$C$7:$AI$58,25,FALSE),0) -> 0 | AB21: =IFERROR(VLOOKUP(C21,'COPY DATA XPRO'!$C$7:$AI$58,26,FALSE),0) -> 1 | AC21: =IFERROR(VLOOKUP(C21,'COPY DATA XPRO'!$C$7:$AI$58,27,FALSE),0) -> 0 | AD21: =IFERROR(VLOOKUP(C21,'COPY DATA XPRO'!$C$7:$AI$58,28,FALSE),0) -> 0 | AE21: =IFERROR(VLOOKUP(C21,'COPY DATA XPRO'!$C$7:$AI$58,29,FALSE),0) -> 1 | AF21: =IFERROR(VLOOKUP(C21,'COPY DATA XPRO'!$C$7:$AI$58,30,FALSE),0) -> 2 | AG21: =IFERROR(VLOOKUP(C21,'COPY DATA XPRO'!$C$7:$AI$58,31,FALSE),0) -> 60 | AH21: =IFERROR(VLOOKUP(C21,'COPY DATA XPRO'!$C$7:$AI$58,32,FALSE),0) -> 69.23 | AI21: =IFERROR(VLOOKUP(C21,'COPY DATA XPRO'!$C$7:$AI$58,33,FALSE),0) -> 81.82
C22: NGAWI | D22: =IFERROR(VLOOKUP(C22,'COPY DATA XPRO'!$C$7:$AI$58,2,FALSE),0) -> 0 | E22: =IFERROR(VLOOKUP(C22,'COPY DATA XPRO'!$C$7:$AI$58,3,FALSE),0) -> 8 | F22: =IFERROR(VLOOKUP(C22,'COPY DATA XPRO'!$C$7:$AI$58,4,FALSE),0) -> 0 | G22: =IFERROR(VLOOKUP(C22,'COPY DATA XPRO'!$C$7:$AI$58,5,FALSE),0) -> 0 | H22: =IFERROR(VLOOKUP(C22,'COPY DATA XPRO'!$C$7:$AI$58,6,FALSE),0) -> 0 | I22: =IFERROR(VLOOKUP(C22,'COPY DATA XPRO'!$C$7:$AI$58,7,FALSE),0) -> 0 | J22: =IFERROR(VLOOKUP(C22,'COPY DATA XPRO'!$C$7:$AI$58,8,FALSE),0) -> 1 | K22: =IFERROR(VLOOKUP(C22,'COPY DATA XPRO'!$C$7:$AI$58,9,FALSE),0) -> 0 | L22: =IFERROR(VLOOKUP(C22,'COPY DATA XPRO'!$C$7:$AI$58,10,FALSE),0) -> 0 | M22: =IFERROR(VLOOKUP(C22,'COPY DATA XPRO'!$C$7:$AI$58,11,FALSE),0) -> 0 | N22: =IFERROR(VLOOKUP(C22,'COPY DATA XPRO'!$C$7:$AI$58,12,FALSE),0) -> 0 | O22: =IFERROR(VLOOKUP(C22,'COPY DATA XPRO'!$C$7:$AI$58,13,FALSE),0) -> 0 | P22: =IFERROR(VLOOKUP(C22,'COPY DATA XPRO'!$C$7:$AI$58,14,FALSE),0) -> 0 | Q22: =IFERROR(VLOOKUP(C22,'COPY DATA XPRO'!$C$7:$AI$58,15,FALSE),0) -> 1 | R22: =IFERROR(VLOOKUP(C22,'COPY DATA XPRO'!$C$7:$AI$58,16,FALSE),0) -> 0 | S22: =IFERROR(VLOOKUP(C22,'COPY DATA XPRO'!$C$7:$AI$58,17,FALSE),0) -> 0 | T22: =IFERROR(VLOOKUP(C22,'COPY DATA XPRO'!$C$7:$AI$58,18,FALSE),0) -> 0 | U22: =IFERROR(VLOOKUP(C22,'COPY DATA XPRO'!$C$7:$AI$58,19,FALSE),0) -> 0 | V22: =IFERROR(VLOOKUP(C22,'COPY DATA XPRO'!$C$7:$AI$58,20,FALSE),0) -> 0 | W22: =IFERROR(VLOOKUP(C22,'COPY DATA XPRO'!$C$7:$AI$58,21,FALSE),0) -> 0 | X22: =IFERROR(VLOOKUP(C22,'COPY DATA XPRO'!$C$7:$AI$58,22,FALSE),0) -> 1 | Y22: =IFERROR(VLOOKUP(C22,'COPY DATA XPRO'!$C$7:$AI$58,23,FALSE),0) -> 0 | Z22: =IFERROR(VLOOKUP(C22,'COPY DATA XPRO'!$C$7:$AI$58,24,FALSE),0) -> 6 | AA22: =IFERROR(VLOOKUP(C22,'COPY DATA XPRO'!$C$7:$AI$58,25,FALSE),0) -> 0 | AB22: =IFERROR(VLOOKUP(C22,'COPY DATA XPRO'!$C$7:$AI$58,26,FALSE),0) -> 0 | AC22: =IFERROR(VLOOKUP(C22,'COPY DATA XPRO'!$C$7:$AI$58,27,FALSE),0) -> 0 | AD22: =IFERROR(VLOOKUP(C22,'COPY DATA XPRO'!$C$7:$AI$58,28,FALSE),0) -> 0 | AE22: =IFERROR(VLOOKUP(C22,'COPY DATA XPRO'!$C$7:$AI$58,29,FALSE),0) -> 0 | AF22: =IFERROR(VLOOKUP(C22,'COPY DATA XPRO'!$C$7:$AI$58,30,FALSE),0) -> 0 | AG22: =IFERROR(VLOOKUP(C22,'COPY DATA XPRO'!$C$7:$AI$58,31,FALSE),0) -> 87.5 | AH22: =IFERROR(VLOOKUP(C22,'COPY DATA XPRO'!$C$7:$AI$58,32,FALSE),0) -> 75 | AI22: =IFERROR(VLOOKUP(C22,'COPY DATA XPRO'!$C$7:$AI$58,33,FALSE),0) -> 85.71
C23: PONOROGO | D23: =IFERROR(VLOOKUP(C23,'COPY DATA XPRO'!$C$7:$AI$58,2,FALSE),0) -> 0 | E23: =IFERROR(VLOOKUP(C23,'COPY DATA XPRO'!$C$7:$AI$58,3,FALSE),0) -> 21 | F23: =IFERROR(VLOOKUP(C23,'COPY DATA XPRO'!$C$7:$AI$58,4,FALSE),0) -> 0 | G23: =IFERROR(VLOOKUP(C23,'COPY DATA XPRO'!$C$7:$AI$58,5,FALSE),0) -> 0 | H23: =IFERROR(VLOOKUP(C23,'COPY DATA XPRO'!$C$7:$AI$58,6,FALSE),0) -> 0 | I23: =IFERROR(VLOOKUP(C23,'COPY DATA XPRO'!$C$7:$AI$58,7,FALSE),0) -> 0 | J23: =IFERROR(VLOOKUP(C23,'COPY DATA XPRO'!$C$7:$AI$58,8,FALSE),0) -> 2 | K23: =IFERROR(VLOOKUP(C23,'COPY DATA XPRO'!$C$7:$AI$58,9,FALSE),0) -> 1 | L23: =IFERROR(VLOOKUP(C23,'COPY DATA XPRO'!$C$7:$AI$58,10,FALSE),0) -> 0 | M23: =IFERROR(VLOOKUP(C23,'COPY DATA XPRO'!$C$7:$AI$58,11,FALSE),0) -> 0 | N23: =IFERROR(VLOOKUP(C23,'COPY DATA XPRO'!$C$7:$AI$58,12,FALSE),0) -> 0 | O23: =IFERROR(VLOOKUP(C23,'COPY DATA XPRO'!$C$7:$AI$58,13,FALSE),0) -> 0 | P23: =IFERROR(VLOOKUP(C23,'COPY DATA XPRO'!$C$7:$AI$58,14,FALSE),0) -> 0 | Q23: =IFERROR(VLOOKUP(C23,'COPY DATA XPRO'!$C$7:$AI$58,15,FALSE),0) -> 0 | R23: =IFERROR(VLOOKUP(C23,'COPY DATA XPRO'!$C$7:$AI$58,16,FALSE),0) -> 0 | S23: =IFERROR(VLOOKUP(C23,'COPY DATA XPRO'!$C$7:$AI$58,17,FALSE),0) -> 0 | T23: =IFERROR(VLOOKUP(C23,'COPY DATA XPRO'!$C$7:$AI$58,18,FALSE),0) -> 0 | U23: =IFERROR(VLOOKUP(C23,'COPY DATA XPRO'!$C$7:$AI$58,19,FALSE),0) -> 0 | V23: =IFERROR(VLOOKUP(C23,'COPY DATA XPRO'!$C$7:$AI$58,20,FALSE),0) -> 0 | W23: =IFERROR(VLOOKUP(C23,'COPY DATA XPRO'!$C$7:$AI$58,21,FALSE),0) -> 0 | X23: =IFERROR(VLOOKUP(C23,'COPY DATA XPRO'!$C$7:$AI$58,22,FALSE),0) -> 0 | Y23: =IFERROR(VLOOKUP(C23,'COPY DATA XPRO'!$C$7:$AI$58,23,FALSE),0) -> 0 | Z23: =IFERROR(VLOOKUP(C23,'COPY DATA XPRO'!$C$7:$AI$58,24,FALSE),0) -> 15 | AA23: =IFERROR(VLOOKUP(C23,'COPY DATA XPRO'!$C$7:$AI$58,25,FALSE),0) -> 0 | AB23: =IFERROR(VLOOKUP(C23,'COPY DATA XPRO'!$C$7:$AI$58,26,FALSE),0) -> 1 | AC23: =IFERROR(VLOOKUP(C23,'COPY DATA XPRO'!$C$7:$AI$58,27,FALSE),0) -> 0 | AD23: =IFERROR(VLOOKUP(C23,'COPY DATA XPRO'!$C$7:$AI$58,28,FALSE),0) -> 0 | AE23: =IFERROR(VLOOKUP(C23,'COPY DATA XPRO'!$C$7:$AI$58,29,FALSE),0) -> 1 | AF23: =IFERROR(VLOOKUP(C23,'COPY DATA XPRO'!$C$7:$AI$58,30,FALSE),0) -> 2 | AG23: =IFERROR(VLOOKUP(C23,'COPY DATA XPRO'!$C$7:$AI$58,31,FALSE),0) -> 76.19 | AH23: =IFERROR(VLOOKUP(C23,'COPY DATA XPRO'!$C$7:$AI$58,32,FALSE),0) -> 83.33 | AI23: =IFERROR(VLOOKUP(C23,'COPY DATA XPRO'!$C$7:$AI$58,33,FALSE),0) -> 100
C24: TRENGGALEK | D24: =IFERROR(VLOOKUP(C24,'COPY DATA XPRO'!$C$7:$AI$58,2,FALSE),0) -> 0 | E24: =IFERROR(VLOOKUP(C24,'COPY DATA XPRO'!$C$7:$AI$58,3,FALSE),0) -> 8 | F24: =IFERROR(VLOOKUP(C24,'COPY DATA XPRO'!$C$7:$AI$58,4,FALSE),0) -> 0 | G24: =IFERROR(VLOOKUP(C24,'COPY DATA XPRO'!$C$7:$AI$58,5,FALSE),0) -> 0 | H24: =IFERROR(VLOOKUP(C24,'COPY DATA XPRO'!$C$7:$AI$58,6,FALSE),0) -> 0 | I24: =IFERROR(VLOOKUP(C24,'COPY DATA XPRO'!$C$7:$AI$58,7,FALSE),0) -> 0 | J24: =IFERROR(VLOOKUP(C24,'COPY DATA XPRO'!$C$7:$AI$58,8,FALSE),0) -> 0 | K24: =IFERROR(VLOOKUP(C24,'COPY DATA XPRO'!$C$7:$AI$58,9,FALSE),0) -> 0 | L24: =IFERROR(VLOOKUP(C24,'COPY DATA XPRO'!$C$7:$AI$58,10,FALSE),0) -> 0 | M24: =IFERROR(VLOOKUP(C24,'COPY DATA XPRO'!$C$7:$AI$58,11,FALSE),0) -> 0 | N24: =IFERROR(VLOOKUP(C24,'COPY DATA XPRO'!$C$7:$AI$58,12,FALSE),0) -> 0 | O24: =IFERROR(VLOOKUP(C24,'COPY DATA XPRO'!$C$7:$AI$58,13,FALSE),0) -> 0 | P24: =IFERROR(VLOOKUP(C24,'COPY DATA XPRO'!$C$7:$AI$58,14,FALSE),0) -> 0 | Q24: =IFERROR(VLOOKUP(C24,'COPY DATA XPRO'!$C$7:$AI$58,15,FALSE),0) -> 0 | R24: =IFERROR(VLOOKUP(C24,'COPY DATA XPRO'!$C$7:$AI$58,16,FALSE),0) -> 0 | S24: =IFERROR(VLOOKUP(C24,'COPY DATA XPRO'!$C$7:$AI$58,17,FALSE),0) -> 0 | T24: =IFERROR(VLOOKUP(C24,'COPY DATA XPRO'!$C$7:$AI$58,18,FALSE),0) -> 0 | U24: =IFERROR(VLOOKUP(C24,'COPY DATA XPRO'!$C$7:$AI$58,19,FALSE),0) -> 0 | V24: =IFERROR(VLOOKUP(C24,'COPY DATA XPRO'!$C$7:$AI$58,20,FALSE),0) -> 0 | W24: =IFERROR(VLOOKUP(C24,'COPY DATA XPRO'!$C$7:$AI$58,21,FALSE),0) -> 0 | X24: =IFERROR(VLOOKUP(C24,'COPY DATA XPRO'!$C$7:$AI$58,22,FALSE),0) -> 0 | Y24: =IFERROR(VLOOKUP(C24,'COPY DATA XPRO'!$C$7:$AI$58,23,FALSE),0) -> 0 | Z24: =IFERROR(VLOOKUP(C24,'COPY DATA XPRO'!$C$7:$AI$58,24,FALSE),0) -> 6 | AA24: =IFERROR(VLOOKUP(C24,'COPY DATA XPRO'!$C$7:$AI$58,25,FALSE),0) -> 2 | AB24: =IFERROR(VLOOKUP(C24,'COPY DATA XPRO'!$C$7:$AI$58,26,FALSE),0) -> 0 | AC24: =IFERROR(VLOOKUP(C24,'COPY DATA XPRO'!$C$7:$AI$58,27,FALSE),0) -> 0 | AD24: =IFERROR(VLOOKUP(C24,'COPY DATA XPRO'!$C$7:$AI$58,28,FALSE),0) -> 0 | AE24: =IFERROR(VLOOKUP(C24,'COPY DATA XPRO'!$C$7:$AI$58,29,FALSE),0) -> 2 | AF24: =IFERROR(VLOOKUP(C24,'COPY DATA XPRO'!$C$7:$AI$58,30,FALSE),0) -> 0 | AG24: =IFERROR(VLOOKUP(C24,'COPY DATA XPRO'!$C$7:$AI$58,31,FALSE),0) -> 100 | AH24: =IFERROR(VLOOKUP(C24,'COPY DATA XPRO'!$C$7:$AI$58,32,FALSE),0) -> 75 | AI24: =IFERROR(VLOOKUP(C24,'COPY DATA XPRO'!$C$7:$AI$58,33,FALSE),0) -> 100
C25: TUBAN | D25: =IFERROR(VLOOKUP(C25,'COPY DATA XPRO'!$C$7:$AI$58,2,FALSE),0) -> 0 | E25: =IFERROR(VLOOKUP(C25,'COPY DATA XPRO'!$C$7:$AI$58,3,FALSE),0) -> 22 | F25: =IFERROR(VLOOKUP(C25,'COPY DATA XPRO'!$C$7:$AI$58,4,FALSE),0) -> 1 | G25: =IFERROR(VLOOKUP(C25,'COPY DATA XPRO'!$C$7:$AI$58,5,FALSE),0) -> 0 | H25: =IFERROR(VLOOKUP(C25,'COPY DATA XPRO'!$C$7:$AI$58,6,FALSE),0) -> 0 | I25: =IFERROR(VLOOKUP(C25,'COPY DATA XPRO'!$C$7:$AI$58,7,FALSE),0) -> 2 | J25: =IFERROR(VLOOKUP(C25,'COPY DATA XPRO'!$C$7:$AI$58,8,FALSE),0) -> 0 | K25: =IFERROR(VLOOKUP(C25,'COPY DATA XPRO'!$C$7:$AI$58,9,FALSE),0) -> 2 | L25: =IFERROR(VLOOKUP(C25,'COPY DATA XPRO'!$C$7:$AI$58,10,FALSE),0) -> 0 | M25: =IFERROR(VLOOKUP(C25,'COPY DATA XPRO'!$C$7:$AI$58,11,FALSE),0) -> 0 | N25: =IFERROR(VLOOKUP(C25,'COPY DATA XPRO'!$C$7:$AI$58,12,FALSE),0) -> 0 | O25: =IFERROR(VLOOKUP(C25,'COPY DATA XPRO'!$C$7:$AI$58,13,FALSE),0) -> 0 | P25: =IFERROR(VLOOKUP(C25,'COPY DATA XPRO'!$C$7:$AI$58,14,FALSE),0) -> 0 | Q25: =IFERROR(VLOOKUP(C25,'COPY DATA XPRO'!$C$7:$AI$58,15,FALSE),0) -> 0 | R25: =IFERROR(VLOOKUP(C25,'COPY DATA XPRO'!$C$7:$AI$58,16,FALSE),0) -> 0 | S25: =IFERROR(VLOOKUP(C25,'COPY DATA XPRO'!$C$7:$AI$58,17,FALSE),0) -> 0 | T25: =IFERROR(VLOOKUP(C25,'COPY DATA XPRO'!$C$7:$AI$58,18,FALSE),0) -> 0 | U25: =IFERROR(VLOOKUP(C25,'COPY DATA XPRO'!$C$7:$AI$58,19,FALSE),0) -> 0 | V25: =IFERROR(VLOOKUP(C25,'COPY DATA XPRO'!$C$7:$AI$58,20,FALSE),0) -> 0 | W25: =IFERROR(VLOOKUP(C25,'COPY DATA XPRO'!$C$7:$AI$58,21,FALSE),0) -> 0 | X25: =IFERROR(VLOOKUP(C25,'COPY DATA XPRO'!$C$7:$AI$58,22,FALSE),0) -> 0 | Y25: =IFERROR(VLOOKUP(C25,'COPY DATA XPRO'!$C$7:$AI$58,23,FALSE),0) -> 0 | Z25: =IFERROR(VLOOKUP(C25,'COPY DATA XPRO'!$C$7:$AI$58,24,FALSE),0) -> 13 | AA25: =IFERROR(VLOOKUP(C25,'COPY DATA XPRO'!$C$7:$AI$58,25,FALSE),0) -> 1 | AB25: =IFERROR(VLOOKUP(C25,'COPY DATA XPRO'!$C$7:$AI$58,26,FALSE),0) -> 1 | AC25: =IFERROR(VLOOKUP(C25,'COPY DATA XPRO'!$C$7:$AI$58,27,FALSE),0) -> 0 | AD25: =IFERROR(VLOOKUP(C25,'COPY DATA XPRO'!$C$7:$AI$58,28,FALSE),0) -> 0 | AE25: =IFERROR(VLOOKUP(C25,'COPY DATA XPRO'!$C$7:$AI$58,29,FALSE),0) -> 2 | AF25: =IFERROR(VLOOKUP(C25,'COPY DATA XPRO'!$C$7:$AI$58,30,FALSE),0) -> 2 | AG25: =IFERROR(VLOOKUP(C25,'COPY DATA XPRO'!$C$7:$AI$58,31,FALSE),0) -> 68.18 | AH25: =IFERROR(VLOOKUP(C25,'COPY DATA XPRO'!$C$7:$AI$58,32,FALSE),0) -> 81.25 | AI25: =IFERROR(VLOOKUP(C25,'COPY DATA XPRO'!$C$7:$AI$58,33,FALSE),0) -> 100
C26: TULUNGAGUNG | D26: =IFERROR(VLOOKUP(C26,'COPY DATA XPRO'!$C$7:$AI$58,2,FALSE),0) -> 0 | E26: =IFERROR(VLOOKUP(C26,'COPY DATA XPRO'!$C$7:$AI$58,3,FALSE),0) -> 13 | F26: =IFERROR(VLOOKUP(C26,'COPY DATA XPRO'!$C$7:$AI$58,4,FALSE),0) -> 0 | G26: =IFERROR(VLOOKUP(C26,'COPY DATA XPRO'!$C$7:$AI$58,5,FALSE),0) -> 0 | H26: =IFERROR(VLOOKUP(C26,'COPY DATA XPRO'!$C$7:$AI$58,6,FALSE),0) -> 0 | I26: =IFERROR(VLOOKUP(C26,'COPY DATA XPRO'!$C$7:$AI$58,7,FALSE),0) -> 2 | J26: =IFERROR(VLOOKUP(C26,'COPY DATA XPRO'!$C$7:$AI$58,8,FALSE),0) -> 2 | K26: =IFERROR(VLOOKUP(C26,'COPY DATA XPRO'!$C$7:$AI$58,9,FALSE),0) -> 0 | L26: =IFERROR(VLOOKUP(C26,'COPY DATA XPRO'!$C$7:$AI$58,10,FALSE),0) -> 0 | M26: =IFERROR(VLOOKUP(C26,'COPY DATA XPRO'!$C$7:$AI$58,11,FALSE),0) -> 0 | N26: =IFERROR(VLOOKUP(C26,'COPY DATA XPRO'!$C$7:$AI$58,12,FALSE),0) -> 0 | O26: =IFERROR(VLOOKUP(C26,'COPY DATA XPRO'!$C$7:$AI$58,13,FALSE),0) -> 0 | P26: =IFERROR(VLOOKUP(C26,'COPY DATA XPRO'!$C$7:$AI$58,14,FALSE),0) -> 0 | Q26: =IFERROR(VLOOKUP(C26,'COPY DATA XPRO'!$C$7:$AI$58,15,FALSE),0) -> 0 | R26: =IFERROR(VLOOKUP(C26,'COPY DATA XPRO'!$C$7:$AI$58,16,FALSE),0) -> 0 | S26: =IFERROR(VLOOKUP(C26,'COPY DATA XPRO'!$C$7:$AI$58,17,FALSE),0) -> 0 | T26: =IFERROR(VLOOKUP(C26,'COPY DATA XPRO'!$C$7:$AI$58,18,FALSE),0) -> 0 | U26: =IFERROR(VLOOKUP(C26,'COPY DATA XPRO'!$C$7:$AI$58,19,FALSE),0) -> 0 | V26: =IFERROR(VLOOKUP(C26,'COPY DATA XPRO'!$C$7:$AI$58,20,FALSE),0) -> 0 | W26: =IFERROR(VLOOKUP(C26,'COPY DATA XPRO'!$C$7:$AI$58,21,FALSE),0) -> 0 | X26: =IFERROR(VLOOKUP(C26,'COPY DATA XPRO'!$C$7:$AI$58,22,FALSE),0) -> 0 | Y26: =IFERROR(VLOOKUP(C26,'COPY DATA XPRO'!$C$7:$AI$58,23,FALSE),0) -> 0 | Z26: =IFERROR(VLOOKUP(C26,'COPY DATA XPRO'!$C$7:$AI$58,24,FALSE),0) -> 8 | AA26: =IFERROR(VLOOKUP(C26,'COPY DATA XPRO'!$C$7:$AI$58,25,FALSE),0) -> 0 | AB26: =IFERROR(VLOOKUP(C26,'COPY DATA XPRO'!$C$7:$AI$58,26,FALSE),0) -> 0 | AC26: =IFERROR(VLOOKUP(C26,'COPY DATA XPRO'!$C$7:$AI$58,27,FALSE),0) -> 0 | AD26: =IFERROR(VLOOKUP(C26,'COPY DATA XPRO'!$C$7:$AI$58,28,FALSE),0) -> 1 | AE26: =IFERROR(VLOOKUP(C26,'COPY DATA XPRO'!$C$7:$AI$58,29,FALSE),0) -> 1 | AF26: =IFERROR(VLOOKUP(C26,'COPY DATA XPRO'!$C$7:$AI$58,30,FALSE),0) -> 0 | AG26: =IFERROR(VLOOKUP(C26,'COPY DATA XPRO'!$C$7:$AI$58,31,FALSE),0) -> 69.23 | AH26: =IFERROR(VLOOKUP(C26,'COPY DATA XPRO'!$C$7:$AI$58,32,FALSE),0) -> 72.73 | AI26: =IFERROR(VLOOKUP(C26,'COPY DATA XPRO'!$C$7:$AI$58,33,FALSE),0) -> 100
B27: JATIM TIMUR | C27: BANYUWANGI | D27: =IFERROR(VLOOKUP(C27,'COPY DATA XPRO'!$C$7:$AI$58,2,FALSE),0) -> 0 | E27: =IFERROR(VLOOKUP(C27,'COPY DATA XPRO'!$C$7:$AI$58,3,FALSE),0) -> 18 | F27: =IFERROR(VLOOKUP(C27,'COPY DATA XPRO'!$C$7:$AI$58,4,FALSE),0) -> 0 | G27: =IFERROR(VLOOKUP(C27,'COPY DATA XPRO'!$C$7:$AI$58,5,FALSE),0) -> 0 | H27: =IFERROR(VLOOKUP(C27,'COPY DATA XPRO'!$C$7:$AI$58,6,FALSE),0) -> 0 | I27: =IFERROR(VLOOKUP(C27,'COPY DATA XPRO'!$C$7:$AI$58,7,FALSE),0) -> 0 | J27: =IFERROR(VLOOKUP(C27,'COPY DATA XPRO'!$C$7:$AI$58,8,FALSE),0) -> 2 | K27: =IFERROR(VLOOKUP(C27,'COPY DATA XPRO'!$C$7:$AI$58,9,FALSE),0) -> 0 | L27: =IFERROR(VLOOKUP(C27,'COPY DATA XPRO'!$C$7:$AI$58,10,FALSE),0) -> 0 | M27: =IFERROR(VLOOKUP(C27,'COPY DATA XPRO'!$C$7:$AI$58,11,FALSE),0) -> 0 | N27: =IFERROR(VLOOKUP(C27,'COPY DATA XPRO'!$C$7:$AI$58,12,FALSE),0) -> 0 | O27: =IFERROR(VLOOKUP(C27,'COPY DATA XPRO'!$C$7:$AI$58,13,FALSE),0) -> 0 | P27: =IFERROR(VLOOKUP(C27,'COPY DATA XPRO'!$C$7:$AI$58,14,FALSE),0) -> 0 | Q27: =IFERROR(VLOOKUP(C27,'COPY DATA XPRO'!$C$7:$AI$58,15,FALSE),0) -> 0 | R27: =IFERROR(VLOOKUP(C27,'COPY DATA XPRO'!$C$7:$AI$58,16,FALSE),0) -> 0 | S27: =IFERROR(VLOOKUP(C27,'COPY DATA XPRO'!$C$7:$AI$58,17,FALSE),0) -> 0 | T27: =IFERROR(VLOOKUP(C27,'COPY DATA XPRO'!$C$7:$AI$58,18,FALSE),0) -> 0 | U27: =IFERROR(VLOOKUP(C27,'COPY DATA XPRO'!$C$7:$AI$58,19,FALSE),0) -> 0 | V27: =IFERROR(VLOOKUP(C27,'COPY DATA XPRO'!$C$7:$AI$58,20,FALSE),0) -> 0 | W27: =IFERROR(VLOOKUP(C27,'COPY DATA XPRO'!$C$7:$AI$58,21,FALSE),0) -> 0 | X27: =IFERROR(VLOOKUP(C27,'COPY DATA XPRO'!$C$7:$AI$58,22,FALSE),0) -> 0 | Y27: =IFERROR(VLOOKUP(C27,'COPY DATA XPRO'!$C$7:$AI$58,23,FALSE),0) -> 0 | Z27: =IFERROR(VLOOKUP(C27,'COPY DATA XPRO'!$C$7:$AI$58,24,FALSE),0) -> 13 | AA27: =IFERROR(VLOOKUP(C27,'COPY DATA XPRO'!$C$7:$AI$58,25,FALSE),0) -> 1 | AB27: =IFERROR(VLOOKUP(C27,'COPY DATA XPRO'!$C$7:$AI$58,26,FALSE),0) -> 0 | AC27: =IFERROR(VLOOKUP(C27,'COPY DATA XPRO'!$C$7:$AI$58,27,FALSE),0) -> 0 | AD27: =IFERROR(VLOOKUP(C27,'COPY DATA XPRO'!$C$7:$AI$58,28,FALSE),0) -> 2 | AE27: =IFERROR(VLOOKUP(C27,'COPY DATA XPRO'!$C$7:$AI$58,29,FALSE),0) -> 3 | AF27: =IFERROR(VLOOKUP(C27,'COPY DATA XPRO'!$C$7:$AI$58,30,FALSE),0) -> 0 | AG27: =IFERROR(VLOOKUP(C27,'COPY DATA XPRO'!$C$7:$AI$58,31,FALSE),0) -> 88.89 | AH27: =IFERROR(VLOOKUP(C27,'COPY DATA XPRO'!$C$7:$AI$58,32,FALSE),0) -> 72.22 | AI27: =IFERROR(VLOOKUP(C27,'COPY DATA XPRO'!$C$7:$AI$58,33,FALSE),0) -> 100
C28: BONDOWOSO | D28: =IFERROR(VLOOKUP(C28,'COPY DATA XPRO'!$C$7:$AI$58,2,FALSE),0) -> 0 | E28: =IFERROR(VLOOKUP(C28,'COPY DATA XPRO'!$C$7:$AI$58,3,FALSE),0) -> 12 | F28: =IFERROR(VLOOKUP(C28,'COPY DATA XPRO'!$C$7:$AI$58,4,FALSE),0) -> 0 | G28: =IFERROR(VLOOKUP(C28,'COPY DATA XPRO'!$C$7:$AI$58,5,FALSE),0) -> 0 | H28: =IFERROR(VLOOKUP(C28,'COPY DATA XPRO'!$C$7:$AI$58,6,FALSE),0) -> 0 | I28: =IFERROR(VLOOKUP(C28,'COPY DATA XPRO'!$C$7:$AI$58,7,FALSE),0) -> 0 | J28: =IFERROR(VLOOKUP(C28,'COPY DATA XPRO'!$C$7:$AI$58,8,FALSE),0) -> 0 | K28: =IFERROR(VLOOKUP(C28,'COPY DATA XPRO'!$C$7:$AI$58,9,FALSE),0) -> 0 | L28: =IFERROR(VLOOKUP(C28,'COPY DATA XPRO'!$C$7:$AI$58,10,FALSE),0) -> 0 | M28: =IFERROR(VLOOKUP(C28,'COPY DATA XPRO'!$C$7:$AI$58,11,FALSE),0) -> 0 | N28: =IFERROR(VLOOKUP(C28,'COPY DATA XPRO'!$C$7:$AI$58,12,FALSE),0) -> 0 | O28: =IFERROR(VLOOKUP(C28,'COPY DATA XPRO'!$C$7:$AI$58,13,FALSE),0) -> 0 | P28: =IFERROR(VLOOKUP(C28,'COPY DATA XPRO'!$C$7:$AI$58,14,FALSE),0) -> 0 | Q28: =IFERROR(VLOOKUP(C28,'COPY DATA XPRO'!$C$7:$AI$58,15,FALSE),0) -> 0 | R28: =IFERROR(VLOOKUP(C28,'COPY DATA XPRO'!$C$7:$AI$58,16,FALSE),0) -> 0 | S28: =IFERROR(VLOOKUP(C28,'COPY DATA XPRO'!$C$7:$AI$58,17,FALSE),0) -> 0 | T28: =IFERROR(VLOOKUP(C28,'COPY DATA XPRO'!$C$7:$AI$58,18,FALSE),0) -> 0 | U28: =IFERROR(VLOOKUP(C28,'COPY DATA XPRO'!$C$7:$AI$58,19,FALSE),0) -> 0 | V28: =IFERROR(VLOOKUP(C28,'COPY DATA XPRO'!$C$7:$AI$58,20,FALSE),0) -> 0 | W28: =IFERROR(VLOOKUP(C28,'COPY DATA XPRO'!$C$7:$AI$58,21,FALSE),0) -> 0 | X28: =IFERROR(VLOOKUP(C28,'COPY DATA XPRO'!$C$7:$AI$58,22,FALSE),0) -> 0 | Y28: =IFERROR(VLOOKUP(C28,'COPY DATA XPRO'!$C$7:$AI$58,23,FALSE),0) -> 0 | Z28: =IFERROR(VLOOKUP(C28,'COPY DATA XPRO'!$C$7:$AI$58,24,FALSE),0) -> 11 | AA28: =IFERROR(VLOOKUP(C28,'COPY DATA XPRO'!$C$7:$AI$58,25,FALSE),0) -> 0 | AB28: =IFERROR(VLOOKUP(C28,'COPY DATA XPRO'!$C$7:$AI$58,26,FALSE),0) -> 0 | AC28: =IFERROR(VLOOKUP(C28,'COPY DATA XPRO'!$C$7:$AI$58,27,FALSE),0) -> 0 | AD28: =IFERROR(VLOOKUP(C28,'COPY DATA XPRO'!$C$7:$AI$58,28,FALSE),0) -> 1 | AE28: =IFERROR(VLOOKUP(C28,'COPY DATA XPRO'!$C$7:$AI$58,29,FALSE),0) -> 1 | AF28: =IFERROR(VLOOKUP(C28,'COPY DATA XPRO'!$C$7:$AI$58,30,FALSE),0) -> 0 | AG28: =IFERROR(VLOOKUP(C28,'COPY DATA XPRO'!$C$7:$AI$58,31,FALSE),0) -> 100 | AH28: =IFERROR(VLOOKUP(C28,'COPY DATA XPRO'!$C$7:$AI$58,32,FALSE),0) -> 91.67 | AI28: =IFERROR(VLOOKUP(C28,'COPY DATA XPRO'!$C$7:$AI$58,33,FALSE),0) -> 100
C29: INNER - JATIM TIMUR | D29: =IFERROR(VLOOKUP(C29,'COPY DATA XPRO'!$C$7:$AI$58,2,FALSE),0) -> 0 | E29: =IFERROR(VLOOKUP(C29,'COPY DATA XPRO'!$C$7:$AI$58,3,FALSE),0) -> 32 | F29: =IFERROR(VLOOKUP(C29,'COPY DATA XPRO'!$C$7:$AI$58,4,FALSE),0) -> 0 | G29: =IFERROR(VLOOKUP(C29,'COPY DATA XPRO'!$C$7:$AI$58,5,FALSE),0) -> 0 | H29: =IFERROR(VLOOKUP(C29,'COPY DATA XPRO'!$C$7:$AI$58,6,FALSE),0) -> 0 | I29: =IFERROR(VLOOKUP(C29,'COPY DATA XPRO'!$C$7:$AI$58,7,FALSE),0) -> 0 | J29: =IFERROR(VLOOKUP(C29,'COPY DATA XPRO'!$C$7:$AI$58,8,FALSE),0) -> 0 | K29: =IFERROR(VLOOKUP(C29,'COPY DATA XPRO'!$C$7:$AI$58,9,FALSE),0) -> 1 | L29: =IFERROR(VLOOKUP(C29,'COPY DATA XPRO'!$C$7:$AI$58,10,FALSE),0) -> 0 | M29: =IFERROR(VLOOKUP(C29,'COPY DATA XPRO'!$C$7:$AI$58,11,FALSE),0) -> 0 | N29: =IFERROR(VLOOKUP(C29,'COPY DATA XPRO'!$C$7:$AI$58,12,FALSE),0) -> 0 | O29: =IFERROR(VLOOKUP(C29,'COPY DATA XPRO'!$C$7:$AI$58,13,FALSE),0) -> 0 | P29: =IFERROR(VLOOKUP(C29,'COPY DATA XPRO'!$C$7:$AI$58,14,FALSE),0) -> 0 | Q29: =IFERROR(VLOOKUP(C29,'COPY DATA XPRO'!$C$7:$AI$58,15,FALSE),0) -> 0 | R29: =IFERROR(VLOOKUP(C29,'COPY DATA XPRO'!$C$7:$AI$58,16,FALSE),0) -> 0 | S29: =IFERROR(VLOOKUP(C29,'COPY DATA XPRO'!$C$7:$AI$58,17,FALSE),0) -> 0 | T29: =IFERROR(VLOOKUP(C29,'COPY DATA XPRO'!$C$7:$AI$58,18,FALSE),0) -> 0 | U29: =IFERROR(VLOOKUP(C29,'COPY DATA XPRO'!$C$7:$AI$58,19,FALSE),0) -> 0 | V29: =IFERROR(VLOOKUP(C29,'COPY DATA XPRO'!$C$7:$AI$58,20,FALSE),0) -> 0 | W29: =IFERROR(VLOOKUP(C29,'COPY DATA XPRO'!$C$7:$AI$58,21,FALSE),0) -> 0 | X29: =IFERROR(VLOOKUP(C29,'COPY DATA XPRO'!$C$7:$AI$58,22,FALSE),0) -> 0 | Y29: =IFERROR(VLOOKUP(C29,'COPY DATA XPRO'!$C$7:$AI$58,23,FALSE),0) -> 1 | Z29: =IFERROR(VLOOKUP(C29,'COPY DATA XPRO'!$C$7:$AI$58,24,FALSE),0) -> 24 | AA29: =IFERROR(VLOOKUP(C29,'COPY DATA XPRO'!$C$7:$AI$58,25,FALSE),0) -> 1 | AB29: =IFERROR(VLOOKUP(C29,'COPY DATA XPRO'!$C$7:$AI$58,26,FALSE),0) -> 1 | AC29: =IFERROR(VLOOKUP(C29,'COPY DATA XPRO'!$C$7:$AI$58,27,FALSE),0) -> 0 | AD29: =IFERROR(VLOOKUP(C29,'COPY DATA XPRO'!$C$7:$AI$58,28,FALSE),0) -> 1 | AE29: =IFERROR(VLOOKUP(C29,'COPY DATA XPRO'!$C$7:$AI$58,29,FALSE),0) -> 3 | AF29: =IFERROR(VLOOKUP(C29,'COPY DATA XPRO'!$C$7:$AI$58,30,FALSE),0) -> 3 | AG29: =IFERROR(VLOOKUP(C29,'COPY DATA XPRO'!$C$7:$AI$58,31,FALSE),0) -> 87.5 | AH29: =IFERROR(VLOOKUP(C29,'COPY DATA XPRO'!$C$7:$AI$58,32,FALSE),0) -> 85.71 | AI29: =IFERROR(VLOOKUP(C29,'COPY DATA XPRO'!$C$7:$AI$58,33,FALSE),0) -> 96
C30: JEMBER | D30: =IFERROR(VLOOKUP(C30,'COPY DATA XPRO'!$C$7:$AI$58,2,FALSE),0) -> 0 | E30: =IFERROR(VLOOKUP(C30,'COPY DATA XPRO'!$C$7:$AI$58,3,FALSE),0) -> 10 | F30: =IFERROR(VLOOKUP(C30,'COPY DATA XPRO'!$C$7:$AI$58,4,FALSE),0) -> 0 | G30: =IFERROR(VLOOKUP(C30,'COPY DATA XPRO'!$C$7:$AI$58,5,FALSE),0) -> 0 | H30: =IFERROR(VLOOKUP(C30,'COPY DATA XPRO'!$C$7:$AI$58,6,FALSE),0) -> 0 | I30: =IFERROR(VLOOKUP(C30,'COPY DATA XPRO'!$C$7:$AI$58,7,FALSE),0) -> 0 | J30: =IFERROR(VLOOKUP(C30,'COPY DATA XPRO'!$C$7:$AI$58,8,FALSE),0) -> 0 | K30: =IFERROR(VLOOKUP(C30,'COPY DATA XPRO'!$C$7:$AI$58,9,FALSE),0) -> 0 | L30: =IFERROR(VLOOKUP(C30,'COPY DATA XPRO'!$C$7:$AI$58,10,FALSE),0) -> 0 | M30: =IFERROR(VLOOKUP(C30,'COPY DATA XPRO'!$C$7:$AI$58,11,FALSE),0) -> 0 | N30: =IFERROR(VLOOKUP(C30,'COPY DATA XPRO'!$C$7:$AI$58,12,FALSE),0) -> 0 | O30: =IFERROR(VLOOKUP(C30,'COPY DATA XPRO'!$C$7:$AI$58,13,FALSE),0) -> 0 | P30: =IFERROR(VLOOKUP(C30,'COPY DATA XPRO'!$C$7:$AI$58,14,FALSE),0) -> 0 | Q30: =IFERROR(VLOOKUP(C30,'COPY DATA XPRO'!$C$7:$AI$58,15,FALSE),0) -> 0 | R30: =IFERROR(VLOOKUP(C30,'COPY DATA XPRO'!$C$7:$AI$58,16,FALSE),0) -> 0 | S30: =IFERROR(VLOOKUP(C30,'COPY DATA XPRO'!$C$7:$AI$58,17,FALSE),0) -> 0 | T30: =IFERROR(VLOOKUP(C30,'COPY DATA XPRO'!$C$7:$AI$58,18,FALSE),0) -> 0 | U30: =IFERROR(VLOOKUP(C30,'COPY DATA XPRO'!$C$7:$AI$58,19,FALSE),0) -> 0 | V30: =IFERROR(VLOOKUP(C30,'COPY DATA XPRO'!$C$7:$AI$58,20,FALSE),0) -> 0 | W30: =IFERROR(VLOOKUP(C30,'COPY DATA XPRO'!$C$7:$AI$58,21,FALSE),0) -> 0 | X30: =IFERROR(VLOOKUP(C30,'COPY DATA XPRO'!$C$7:$AI$58,22,FALSE),0) -> 0 | Y30: =IFERROR(VLOOKUP(C30,'COPY DATA XPRO'!$C$7:$AI$58,23,FALSE),0) -> 1 | Z30: =IFERROR(VLOOKUP(C30,'COPY DATA XPRO'!$C$7:$AI$58,24,FALSE),0) -> 9 | AA30: =IFERROR(VLOOKUP(C30,'COPY DATA XPRO'!$C$7:$AI$58,25,FALSE),0) -> 0 | AB30: =IFERROR(VLOOKUP(C30,'COPY DATA XPRO'!$C$7:$AI$58,26,FALSE),0) -> 0 | AC30: =IFERROR(VLOOKUP(C30,'COPY DATA XPRO'!$C$7:$AI$58,27,FALSE),0) -> 0 | AD30: =IFERROR(VLOOKUP(C30,'COPY DATA XPRO'!$C$7:$AI$58,28,FALSE),0) -> 0 | AE30: =IFERROR(VLOOKUP(C30,'COPY DATA XPRO'!$C$7:$AI$58,29,FALSE),0) -> 0 | AF30: =IFERROR(VLOOKUP(C30,'COPY DATA XPRO'!$C$7:$AI$58,30,FALSE),0) -> 0 | AG30: =IFERROR(VLOOKUP(C30,'COPY DATA XPRO'!$C$7:$AI$58,31,FALSE),0) -> 100 | AH30: =IFERROR(VLOOKUP(C30,'COPY DATA XPRO'!$C$7:$AI$58,32,FALSE),0) -> 90 | AI30: =IFERROR(VLOOKUP(C30,'COPY DATA XPRO'!$C$7:$AI$58,33,FALSE),0) -> 90
C31: JOMBANG | D31: =IFERROR(VLOOKUP(C31,'COPY DATA XPRO'!$C$7:$AI$58,2,FALSE),0) -> 0 | E31: =IFERROR(VLOOKUP(C31,'COPY DATA XPRO'!$C$7:$AI$58,3,FALSE),0) -> 21 | F31: =IFERROR(VLOOKUP(C31,'COPY DATA XPRO'!$C$7:$AI$58,4,FALSE),0) -> 0 | G31: =IFERROR(VLOOKUP(C31,'COPY DATA XPRO'!$C$7:$AI$58,5,FALSE),0) -> 0 | H31: =IFERROR(VLOOKUP(C31,'COPY DATA XPRO'!$C$7:$AI$58,6,FALSE),0) -> 0 | I31: =IFERROR(VLOOKUP(C31,'COPY DATA XPRO'!$C$7:$AI$58,7,FALSE),0) -> 0 | J31: =IFERROR(VLOOKUP(C31,'COPY DATA XPRO'!$C$7:$AI$58,8,FALSE),0) -> 0 | K31: =IFERROR(VLOOKUP(C31,'COPY DATA XPRO'!$C$7:$AI$58,9,FALSE),0) -> 1 | L31: =IFERROR(VLOOKUP(C31,'COPY DATA XPRO'!$C$7:$AI$58,10,FALSE),0) -> 0 | M31: =IFERROR(VLOOKUP(C31,'COPY DATA XPRO'!$C$7:$AI$58,11,FALSE),0) -> 0 | N31: =IFERROR(VLOOKUP(C31,'COPY DATA XPRO'!$C$7:$AI$58,12,FALSE),0) -> 0 | O31: =IFERROR(VLOOKUP(C31,'COPY DATA XPRO'!$C$7:$AI$58,13,FALSE),0) -> 0 | P31: =IFERROR(VLOOKUP(C31,'COPY DATA XPRO'!$C$7:$AI$58,14,FALSE),0) -> 0 | Q31: =IFERROR(VLOOKUP(C31,'COPY DATA XPRO'!$C$7:$AI$58,15,FALSE),0) -> 0 | R31: =IFERROR(VLOOKUP(C31,'COPY DATA XPRO'!$C$7:$AI$58,16,FALSE),0) -> 0 | S31: =IFERROR(VLOOKUP(C31,'COPY DATA XPRO'!$C$7:$AI$58,17,FALSE),0) -> 0 | T31: =IFERROR(VLOOKUP(C31,'COPY DATA XPRO'!$C$7:$AI$58,18,FALSE),0) -> 0 | U31: =IFERROR(VLOOKUP(C31,'COPY DATA XPRO'!$C$7:$AI$58,19,FALSE),0) -> 0 | V31: =IFERROR(VLOOKUP(C31,'COPY DATA XPRO'!$C$7:$AI$58,20,FALSE),0) -> 0 | W31: =IFERROR(VLOOKUP(C31,'COPY DATA XPRO'!$C$7:$AI$58,21,FALSE),0) -> 0 | X31: =IFERROR(VLOOKUP(C31,'COPY DATA XPRO'!$C$7:$AI$58,22,FALSE),0) -> 0 | Y31: =IFERROR(VLOOKUP(C31,'COPY DATA XPRO'!$C$7:$AI$58,23,FALSE),0) -> 2 | Z31: =IFERROR(VLOOKUP(C31,'COPY DATA XPRO'!$C$7:$AI$58,24,FALSE),0) -> 14 | AA31: =IFERROR(VLOOKUP(C31,'COPY DATA XPRO'!$C$7:$AI$58,25,FALSE),0) -> 0 | AB31: =IFERROR(VLOOKUP(C31,'COPY DATA XPRO'!$C$7:$AI$58,26,FALSE),0) -> 1 | AC31: =IFERROR(VLOOKUP(C31,'COPY DATA XPRO'!$C$7:$AI$58,27,FALSE),0) -> 0 | AD31: =IFERROR(VLOOKUP(C31,'COPY DATA XPRO'!$C$7:$AI$58,28,FALSE),0) -> 0 | AE31: =IFERROR(VLOOKUP(C31,'COPY DATA XPRO'!$C$7:$AI$58,29,FALSE),0) -> 1 | AF31: =IFERROR(VLOOKUP(C31,'COPY DATA XPRO'!$C$7:$AI$58,30,FALSE),0) -> 3 | AG31: =IFERROR(VLOOKUP(C31,'COPY DATA XPRO'!$C$7:$AI$58,31,FALSE),0) -> 80.95 | AH31: =IFERROR(VLOOKUP(C31,'COPY DATA XPRO'!$C$7:$AI$58,32,FALSE),0) -> 82.35 | AI31: =IFERROR(VLOOKUP(C31,'COPY DATA XPRO'!$C$7:$AI$58,33,FALSE),0) -> 87.5
C32: LUMAJANG | D32: =IFERROR(VLOOKUP(C32,'COPY DATA XPRO'!$C$7:$AI$58,2,FALSE),0) -> 0 | E32: =IFERROR(VLOOKUP(C32,'COPY DATA XPRO'!$C$7:$AI$58,3,FALSE),0) -> 8 | F32: =IFERROR(VLOOKUP(C32,'COPY DATA XPRO'!$C$7:$AI$58,4,FALSE),0) -> 0 | G32: =IFERROR(VLOOKUP(C32,'COPY DATA XPRO'!$C$7:$AI$58,5,FALSE),0) -> 0 | H32: =IFERROR(VLOOKUP(C32,'COPY DATA XPRO'!$C$7:$AI$58,6,FALSE),0) -> 0 | I32: =IFERROR(VLOOKUP(C32,'COPY DATA XPRO'!$C$7:$AI$58,7,FALSE),0) -> 0 | J32: =IFERROR(VLOOKUP(C32,'COPY DATA XPRO'!$C$7:$AI$58,8,FALSE),0) -> 0 | K32: =IFERROR(VLOOKUP(C32,'COPY DATA XPRO'!$C$7:$AI$58,9,FALSE),0) -> 0 | L32: =IFERROR(VLOOKUP(C32,'COPY DATA XPRO'!$C$7:$AI$58,10,FALSE),0) -> 0 | M32: =IFERROR(VLOOKUP(C32,'COPY DATA XPRO'!$C$7:$AI$58,11,FALSE),0) -> 0 | N32: =IFERROR(VLOOKUP(C32,'COPY DATA XPRO'!$C$7:$AI$58,12,FALSE),0) -> 0 | O32: =IFERROR(VLOOKUP(C32,'COPY DATA XPRO'!$C$7:$AI$58,13,FALSE),0) -> 0 | P32: =IFERROR(VLOOKUP(C32,'COPY DATA XPRO'!$C$7:$AI$58,14,FALSE),0) -> 0 | Q32: =IFERROR(VLOOKUP(C32,'COPY DATA XPRO'!$C$7:$AI$58,15,FALSE),0) -> 0 | R32: =IFERROR(VLOOKUP(C32,'COPY DATA XPRO'!$C$7:$AI$58,16,FALSE),0) -> 1 | S32: =IFERROR(VLOOKUP(C32,'COPY DATA XPRO'!$C$7:$AI$58,17,FALSE),0) -> 0 | T32: =IFERROR(VLOOKUP(C32,'COPY DATA XPRO'!$C$7:$AI$58,18,FALSE),0) -> 0 | U32: =IFERROR(VLOOKUP(C32,'COPY DATA XPRO'!$C$7:$AI$58,19,FALSE),0) -> 1 | V32: =IFERROR(VLOOKUP(C32,'COPY DATA XPRO'!$C$7:$AI$58,20,FALSE),0) -> 0 | W32: =IFERROR(VLOOKUP(C32,'COPY DATA XPRO'!$C$7:$AI$58,21,FALSE),0) -> 0 | X32: =IFERROR(VLOOKUP(C32,'COPY DATA XPRO'!$C$7:$AI$58,22,FALSE),0) -> 2 | Y32: =IFERROR(VLOOKUP(C32,'COPY DATA XPRO'!$C$7:$AI$58,23,FALSE),0) -> 0 | Z32: =IFERROR(VLOOKUP(C32,'COPY DATA XPRO'!$C$7:$AI$58,24,FALSE),0) -> 6 | AA32: =IFERROR(VLOOKUP(C32,'COPY DATA XPRO'!$C$7:$AI$58,25,FALSE),0) -> 0 | AB32: =IFERROR(VLOOKUP(C32,'COPY DATA XPRO'!$C$7:$AI$58,26,FALSE),0) -> 0 | AC32: =IFERROR(VLOOKUP(C32,'COPY DATA XPRO'!$C$7:$AI$58,27,FALSE),0) -> 0 | AD32: =IFERROR(VLOOKUP(C32,'COPY DATA XPRO'!$C$7:$AI$58,28,FALSE),0) -> 0 | AE32: =IFERROR(VLOOKUP(C32,'COPY DATA XPRO'!$C$7:$AI$58,29,FALSE),0) -> 0 | AF32: =IFERROR(VLOOKUP(C32,'COPY DATA XPRO'!$C$7:$AI$58,30,FALSE),0) -> 0 | AG32: =IFERROR(VLOOKUP(C32,'COPY DATA XPRO'!$C$7:$AI$58,31,FALSE),0) -> 100 | AH32: =IFERROR(VLOOKUP(C32,'COPY DATA XPRO'!$C$7:$AI$58,32,FALSE),0) -> 75 | AI32: =IFERROR(VLOOKUP(C32,'COPY DATA XPRO'!$C$7:$AI$58,33,FALSE),0) -> 75
C33: MOJOKERTO | D33: =IFERROR(VLOOKUP(C33,'COPY DATA XPRO'!$C$7:$AI$58,2,FALSE),0) -> 0 | E33: =IFERROR(VLOOKUP(C33,'COPY DATA XPRO'!$C$7:$AI$58,3,FALSE),0) -> 30 | F33: =IFERROR(VLOOKUP(C33,'COPY DATA XPRO'!$C$7:$AI$58,4,FALSE),0) -> 0 | G33: =IFERROR(VLOOKUP(C33,'COPY DATA XPRO'!$C$7:$AI$58,5,FALSE),0) -> 0 | H33: =IFERROR(VLOOKUP(C33,'COPY DATA XPRO'!$C$7:$AI$58,6,FALSE),0) -> 2 | I33: =IFERROR(VLOOKUP(C33,'COPY DATA XPRO'!$C$7:$AI$58,7,FALSE),0) -> 1 | J33: =IFERROR(VLOOKUP(C33,'COPY DATA XPRO'!$C$7:$AI$58,8,FALSE),0) -> 2 | K33: =IFERROR(VLOOKUP(C33,'COPY DATA XPRO'!$C$7:$AI$58,9,FALSE),0) -> 0 | L33: =IFERROR(VLOOKUP(C33,'COPY DATA XPRO'!$C$7:$AI$58,10,FALSE),0) -> 0 | M33: =IFERROR(VLOOKUP(C33,'COPY DATA XPRO'!$C$7:$AI$58,11,FALSE),0) -> 0 | N33: =IFERROR(VLOOKUP(C33,'COPY DATA XPRO'!$C$7:$AI$58,12,FALSE),0) -> 0 | O33: =IFERROR(VLOOKUP(C33,'COPY DATA XPRO'!$C$7:$AI$58,13,FALSE),0) -> 0 | P33: =IFERROR(VLOOKUP(C33,'COPY DATA XPRO'!$C$7:$AI$58,14,FALSE),0) -> 0 | Q33: =IFERROR(VLOOKUP(C33,'COPY DATA XPRO'!$C$7:$AI$58,15,FALSE),0) -> 0 | R33: =IFERROR(VLOOKUP(C33,'COPY DATA XPRO'!$C$7:$AI$58,16,FALSE),0) -> 0 | S33: =IFERROR(VLOOKUP(C33,'COPY DATA XPRO'!$C$7:$AI$58,17,FALSE),0) -> 0 | T33: =IFERROR(VLOOKUP(C33,'COPY DATA XPRO'!$C$7:$AI$58,18,FALSE),0) -> 0 | U33: =IFERROR(VLOOKUP(C33,'COPY DATA XPRO'!$C$7:$AI$58,19,FALSE),0) -> 0 | V33: =IFERROR(VLOOKUP(C33,'COPY DATA XPRO'!$C$7:$AI$58,20,FALSE),0) -> 0 | W33: =IFERROR(VLOOKUP(C33,'COPY DATA XPRO'!$C$7:$AI$58,21,FALSE),0) -> 0 | X33: =IFERROR(VLOOKUP(C33,'COPY DATA XPRO'!$C$7:$AI$58,22,FALSE),0) -> 0 | Y33: =IFERROR(VLOOKUP(C33,'COPY DATA XPRO'!$C$7:$AI$58,23,FALSE),0) -> 0 | Z33: =IFERROR(VLOOKUP(C33,'COPY DATA XPRO'!$C$7:$AI$58,24,FALSE),0) -> 22 | AA33: =IFERROR(VLOOKUP(C33,'COPY DATA XPRO'!$C$7:$AI$58,25,FALSE),0) -> 0 | AB33: =IFERROR(VLOOKUP(C33,'COPY DATA XPRO'!$C$7:$AI$58,26,FALSE),0) -> 0 | AC33: =IFERROR(VLOOKUP(C33,'COPY DATA XPRO'!$C$7:$AI$58,27,FALSE),0) -> 0 | AD33: =IFERROR(VLOOKUP(C33,'COPY DATA XPRO'!$C$7:$AI$58,28,FALSE),0) -> 0 | AE33: =IFERROR(VLOOKUP(C33,'COPY DATA XPRO'!$C$7:$AI$58,29,FALSE),0) -> 0 | AF33: =IFERROR(VLOOKUP(C33,'COPY DATA XPRO'!$C$7:$AI$58,30,FALSE),0) -> 3 | AG33: =IFERROR(VLOOKUP(C33,'COPY DATA XPRO'!$C$7:$AI$58,31,FALSE),0) -> 73.33 | AH33: =IFERROR(VLOOKUP(C33,'COPY DATA XPRO'!$C$7:$AI$58,32,FALSE),0) -> 84.62 | AI33: =IFERROR(VLOOKUP(C33,'COPY DATA XPRO'!$C$7:$AI$58,33,FALSE),0) -> 100
C34: PASURUAN | D34: =IFERROR(VLOOKUP(C34,'COPY DATA XPRO'!$C$7:$AI$58,2,FALSE),0) -> 0 | E34: =IFERROR(VLOOKUP(C34,'COPY DATA XPRO'!$C$7:$AI$58,3,FALSE),0) -> 23 | F34: =IFERROR(VLOOKUP(C34,'COPY DATA XPRO'!$C$7:$AI$58,4,FALSE),0) -> 1 | G34: =IFERROR(VLOOKUP(C34,'COPY DATA XPRO'!$C$7:$AI$58,5,FALSE),0) -> 0 | H34: =IFERROR(VLOOKUP(C34,'COPY DATA XPRO'!$C$7:$AI$58,6,FALSE),0) -> 1 | I34: =IFERROR(VLOOKUP(C34,'COPY DATA XPRO'!$C$7:$AI$58,7,FALSE),0) -> 1 | J34: =IFERROR(VLOOKUP(C34,'COPY DATA XPRO'!$C$7:$AI$58,8,FALSE),0) -> 0 | K34: =IFERROR(VLOOKUP(C34,'COPY DATA XPRO'!$C$7:$AI$58,9,FALSE),0) -> 0 | L34: =IFERROR(VLOOKUP(C34,'COPY DATA XPRO'!$C$7:$AI$58,10,FALSE),0) -> 0 | M34: =IFERROR(VLOOKUP(C34,'COPY DATA XPRO'!$C$7:$AI$58,11,FALSE),0) -> 0 | N34: =IFERROR(VLOOKUP(C34,'COPY DATA XPRO'!$C$7:$AI$58,12,FALSE),0) -> 0 | O34: =IFERROR(VLOOKUP(C34,'COPY DATA XPRO'!$C$7:$AI$58,13,FALSE),0) -> 0 | P34: =IFERROR(VLOOKUP(C34,'COPY DATA XPRO'!$C$7:$AI$58,14,FALSE),0) -> 0 | Q34: =IFERROR(VLOOKUP(C34,'COPY DATA XPRO'!$C$7:$AI$58,15,FALSE),0) -> 0 | R34: =IFERROR(VLOOKUP(C34,'COPY DATA XPRO'!$C$7:$AI$58,16,FALSE),0) -> 0 | S34: =IFERROR(VLOOKUP(C34,'COPY DATA XPRO'!$C$7:$AI$58,17,FALSE),0) -> 0 | T34: =IFERROR(VLOOKUP(C34,'COPY DATA XPRO'!$C$7:$AI$58,18,FALSE),0) -> 0 | U34: =IFERROR(VLOOKUP(C34,'COPY DATA XPRO'!$C$7:$AI$58,19,FALSE),0) -> 0 | V34: =IFERROR(VLOOKUP(C34,'COPY DATA XPRO'!$C$7:$AI$58,20,FALSE),0) -> 0 | W34: =IFERROR(VLOOKUP(C34,'COPY DATA XPRO'!$C$7:$AI$58,21,FALSE),0) -> 0 | X34: =IFERROR(VLOOKUP(C34,'COPY DATA XPRO'!$C$7:$AI$58,22,FALSE),0) -> 0 | Y34: =IFERROR(VLOOKUP(C34,'COPY DATA XPRO'!$C$7:$AI$58,23,FALSE),0) -> 0 | Z34: =IFERROR(VLOOKUP(C34,'COPY DATA XPRO'!$C$7:$AI$58,24,FALSE),0) -> 16 | AA34: =IFERROR(VLOOKUP(C34,'COPY DATA XPRO'!$C$7:$AI$58,25,FALSE),0) -> 2 | AB34: =IFERROR(VLOOKUP(C34,'COPY DATA XPRO'!$C$7:$AI$58,26,FALSE),0) -> 2 | AC34: =IFERROR(VLOOKUP(C34,'COPY DATA XPRO'!$C$7:$AI$58,27,FALSE),0) -> 0 | AD34: =IFERROR(VLOOKUP(C34,'COPY DATA XPRO'!$C$7:$AI$58,28,FALSE),0) -> 0 | AE34: =IFERROR(VLOOKUP(C34,'COPY DATA XPRO'!$C$7:$AI$58,29,FALSE),0) -> 4 | AF34: =IFERROR(VLOOKUP(C34,'COPY DATA XPRO'!$C$7:$AI$58,30,FALSE),0) -> 0 | AG34: =IFERROR(VLOOKUP(C34,'COPY DATA XPRO'!$C$7:$AI$58,31,FALSE),0) -> 86.96 | AH34: =IFERROR(VLOOKUP(C34,'COPY DATA XPRO'!$C$7:$AI$58,32,FALSE),0) -> 72.73 | AI34: =IFERROR(VLOOKUP(C34,'COPY DATA XPRO'!$C$7:$AI$58,33,FALSE),0) -> 100
C35: PROBOLINGGO | D35: =IFERROR(VLOOKUP(C35,'COPY DATA XPRO'!$C$7:$AI$58,2,FALSE),0) -> 0 | E35: =IFERROR(VLOOKUP(C35,'COPY DATA XPRO'!$C$7:$AI$58,3,FALSE),0) -> 16 | F35: =IFERROR(VLOOKUP(C35,'COPY DATA XPRO'!$C$7:$AI$58,4,FALSE),0) -> 0 | G35: =IFERROR(VLOOKUP(C35,'COPY DATA XPRO'!$C$7:$AI$58,5,FALSE),0) -> 0 | H35: =IFERROR(VLOOKUP(C35,'COPY DATA XPRO'!$C$7:$AI$58,6,FALSE),0) -> 0 | I35: =IFERROR(VLOOKUP(C35,'COPY DATA XPRO'!$C$7:$AI$58,7,FALSE),0) -> 0 | J35: =IFERROR(VLOOKUP(C35,'COPY DATA XPRO'!$C$7:$AI$58,8,FALSE),0) -> 1 | K35: =IFERROR(VLOOKUP(C35,'COPY DATA XPRO'!$C$7:$AI$58,9,FALSE),0) -> 0 | L35: =IFERROR(VLOOKUP(C35,'COPY DATA XPRO'!$C$7:$AI$58,10,FALSE),0) -> 0 | M35: =IFERROR(VLOOKUP(C35,'COPY DATA XPRO'!$C$7:$AI$58,11,FALSE),0) -> 0 | N35: =IFERROR(VLOOKUP(C35,'COPY DATA XPRO'!$C$7:$AI$58,12,FALSE),0) -> 1 | O35: =IFERROR(VLOOKUP(C35,'COPY DATA XPRO'!$C$7:$AI$58,13,FALSE),0) -> 0 | P35: =IFERROR(VLOOKUP(C35,'COPY DATA XPRO'!$C$7:$AI$58,14,FALSE),0) -> 1 | Q35: =IFERROR(VLOOKUP(C35,'COPY DATA XPRO'!$C$7:$AI$58,15,FALSE),0) -> 0 | R35: =IFERROR(VLOOKUP(C35,'COPY DATA XPRO'!$C$7:$AI$58,16,FALSE),0) -> 0 | S35: =IFERROR(VLOOKUP(C35,'COPY DATA XPRO'!$C$7:$AI$58,17,FALSE),0) -> 0 | T35: =IFERROR(VLOOKUP(C35,'COPY DATA XPRO'!$C$7:$AI$58,18,FALSE),0) -> 0 | U35: =IFERROR(VLOOKUP(C35,'COPY DATA XPRO'!$C$7:$AI$58,19,FALSE),0) -> 0 | V35: =IFERROR(VLOOKUP(C35,'COPY DATA XPRO'!$C$7:$AI$58,20,FALSE),0) -> 0 | W35: =IFERROR(VLOOKUP(C35,'COPY DATA XPRO'!$C$7:$AI$58,21,FALSE),0) -> 0 | X35: =IFERROR(VLOOKUP(C35,'COPY DATA XPRO'!$C$7:$AI$58,22,FALSE),0) -> 0 | Y35: =IFERROR(VLOOKUP(C35,'COPY DATA XPRO'!$C$7:$AI$58,23,FALSE),0) -> 1 | Z35: =IFERROR(VLOOKUP(C35,'COPY DATA XPRO'!$C$7:$AI$58,24,FALSE),0) -> 12 | AA35: =IFERROR(VLOOKUP(C35,'COPY DATA XPRO'!$C$7:$AI$58,25,FALSE),0) -> 1 | AB35: =IFERROR(VLOOKUP(C35,'COPY DATA XPRO'!$C$7:$AI$58,26,FALSE),0) -> 0 | AC35: =IFERROR(VLOOKUP(C35,'COPY DATA XPRO'!$C$7:$AI$58,27,FALSE),0) -> 0 | AD35: =IFERROR(VLOOKUP(C35,'COPY DATA XPRO'!$C$7:$AI$58,28,FALSE),0) -> 0 | AE35: =IFERROR(VLOOKUP(C35,'COPY DATA XPRO'!$C$7:$AI$58,29,FALSE),0) -> 1 | AF35: =IFERROR(VLOOKUP(C35,'COPY DATA XPRO'!$C$7:$AI$58,30,FALSE),0) -> 0 | AG35: =IFERROR(VLOOKUP(C35,'COPY DATA XPRO'!$C$7:$AI$58,31,FALSE),0) -> 93.75 | AH35: =IFERROR(VLOOKUP(C35,'COPY DATA XPRO'!$C$7:$AI$58,32,FALSE),0) -> 75 | AI35: =IFERROR(VLOOKUP(C35,'COPY DATA XPRO'!$C$7:$AI$58,33,FALSE),0) -> 85.71
C36: SITUBONDO | D36: =IFERROR(VLOOKUP(C36,'COPY DATA XPRO'!$C$7:$AI$58,2,FALSE),0) -> 0 | E36: =IFERROR(VLOOKUP(C36,'COPY DATA XPRO'!$C$7:$AI$58,3,FALSE),0) -> 3 | F36: =IFERROR(VLOOKUP(C36,'COPY DATA XPRO'!$C$7:$AI$58,4,FALSE),0) -> 0 | G36: =IFERROR(VLOOKUP(C36,'COPY DATA XPRO'!$C$7:$AI$58,5,FALSE),0) -> 0 | H36: =IFERROR(VLOOKUP(C36,'COPY DATA XPRO'!$C$7:$AI$58,6,FALSE),0) -> 0 | I36: =IFERROR(VLOOKUP(C36,'COPY DATA XPRO'!$C$7:$AI$58,7,FALSE),0) -> 0 | J36: =IFERROR(VLOOKUP(C36,'COPY DATA XPRO'!$C$7:$AI$58,8,FALSE),0) -> 0 | K36: =IFERROR(VLOOKUP(C36,'COPY DATA XPRO'!$C$7:$AI$58,9,FALSE),0) -> 0 | L36: =IFERROR(VLOOKUP(C36,'COPY DATA XPRO'!$C$7:$AI$58,10,FALSE),0) -> 0 | M36: =IFERROR(VLOOKUP(C36,'COPY DATA XPRO'!$C$7:$AI$58,11,FALSE),0) -> 0 | N36: =IFERROR(VLOOKUP(C36,'COPY DATA XPRO'!$C$7:$AI$58,12,FALSE),0) -> 0 | O36: =IFERROR(VLOOKUP(C36,'COPY DATA XPRO'!$C$7:$AI$58,13,FALSE),0) -> 0 | P36: =IFERROR(VLOOKUP(C36,'COPY DATA XPRO'!$C$7:$AI$58,14,FALSE),0) -> 0 | Q36: =IFERROR(VLOOKUP(C36,'COPY DATA XPRO'!$C$7:$AI$58,15,FALSE),0) -> 0 | R36: =IFERROR(VLOOKUP(C36,'COPY DATA XPRO'!$C$7:$AI$58,16,FALSE),0) -> 0 | S36: =IFERROR(VLOOKUP(C36,'COPY DATA XPRO'!$C$7:$AI$58,17,FALSE),0) -> 0 | T36: =IFERROR(VLOOKUP(C36,'COPY DATA XPRO'!$C$7:$AI$58,18,FALSE),0) -> 0 | U36: =IFERROR(VLOOKUP(C36,'COPY DATA XPRO'!$C$7:$AI$58,19,FALSE),0) -> 0 | V36: =IFERROR(VLOOKUP(C36,'COPY DATA XPRO'!$C$7:$AI$58,20,FALSE),0) -> 0 | W36: =IFERROR(VLOOKUP(C36,'COPY DATA XPRO'!$C$7:$AI$58,21,FALSE),0) -> 0 | X36: =IFERROR(VLOOKUP(C36,'COPY DATA XPRO'!$C$7:$AI$58,22,FALSE),0) -> 0 | Y36: =IFERROR(VLOOKUP(C36,'COPY DATA XPRO'!$C$7:$AI$58,23,FALSE),0) -> 0 | Z36: =IFERROR(VLOOKUP(C36,'COPY DATA XPRO'!$C$7:$AI$58,24,FALSE),0) -> 3 | AA36: =IFERROR(VLOOKUP(C36,'COPY DATA XPRO'!$C$7:$AI$58,25,FALSE),0) -> 0 | AB36: =IFERROR(VLOOKUP(C36,'COPY DATA XPRO'!$C$7:$AI$58,26,FALSE),0) -> 0 | AC36: =IFERROR(VLOOKUP(C36,'COPY DATA XPRO'!$C$7:$AI$58,27,FALSE),0) -> 0 | AD36: =IFERROR(VLOOKUP(C36,'COPY DATA XPRO'!$C$7:$AI$58,28,FALSE),0) -> 0 | AE36: =IFERROR(VLOOKUP(C36,'COPY DATA XPRO'!$C$7:$AI$58,29,FALSE),0) -> 0 | AF36: =IFERROR(VLOOKUP(C36,'COPY DATA XPRO'!$C$7:$AI$58,30,FALSE),0) -> 0 | AG36: =IFERROR(VLOOKUP(C36,'COPY DATA XPRO'!$C$7:$AI$58,31,FALSE),0) -> 100 | AH36: =IFERROR(VLOOKUP(C36,'COPY DATA XPRO'!$C$7:$AI$58,32,FALSE),0) -> 100 | AI36: =IFERROR(VLOOKUP(C36,'COPY DATA XPRO'!$C$7:$AI$58,33,FALSE),0) -> 100
B37: NUSRA | C37: ATAMBUA | D37: =IFERROR(VLOOKUP(C37,'COPY DATA XPRO'!$C$7:$AI$58,2,FALSE),0) -> 0 | E37: =IFERROR(VLOOKUP(C37,'COPY DATA XPRO'!$C$7:$AI$58,3,FALSE),0) -> 2 | F37: =IFERROR(VLOOKUP(C37,'COPY DATA XPRO'!$C$7:$AI$58,4,FALSE),0) -> 1 | G37: =IFERROR(VLOOKUP(C37,'COPY DATA XPRO'!$C$7:$AI$58,5,FALSE),0) -> 0 | H37: =IFERROR(VLOOKUP(C37,'COPY DATA XPRO'!$C$7:$AI$58,6,FALSE),0) -> 0 | I37: =IFERROR(VLOOKUP(C37,'COPY DATA XPRO'!$C$7:$AI$58,7,FALSE),0) -> 0 | J37: =IFERROR(VLOOKUP(C37,'COPY DATA XPRO'!$C$7:$AI$58,8,FALSE),0) -> 0 | K37: =IFERROR(VLOOKUP(C37,'COPY DATA XPRO'!$C$7:$AI$58,9,FALSE),0) -> 0 | L37: =IFERROR(VLOOKUP(C37,'COPY DATA XPRO'!$C$7:$AI$58,10,FALSE),0) -> 0 | M37: =IFERROR(VLOOKUP(C37,'COPY DATA XPRO'!$C$7:$AI$58,11,FALSE),0) -> 0 | N37: =IFERROR(VLOOKUP(C37,'COPY DATA XPRO'!$C$7:$AI$58,12,FALSE),0) -> 0 | O37: =IFERROR(VLOOKUP(C37,'COPY DATA XPRO'!$C$7:$AI$58,13,FALSE),0) -> 0 | P37: =IFERROR(VLOOKUP(C37,'COPY DATA XPRO'!$C$7:$AI$58,14,FALSE),0) -> 0 | Q37: =IFERROR(VLOOKUP(C37,'COPY DATA XPRO'!$C$7:$AI$58,15,FALSE),0) -> 0 | R37: =IFERROR(VLOOKUP(C37,'COPY DATA XPRO'!$C$7:$AI$58,16,FALSE),0) -> 0 | S37: =IFERROR(VLOOKUP(C37,'COPY DATA XPRO'!$C$7:$AI$58,17,FALSE),0) -> 0 | T37: =IFERROR(VLOOKUP(C37,'COPY DATA XPRO'!$C$7:$AI$58,18,FALSE),0) -> 0 | U37: =IFERROR(VLOOKUP(C37,'COPY DATA XPRO'!$C$7:$AI$58,19,FALSE),0) -> 0 | V37: =IFERROR(VLOOKUP(C37,'COPY DATA XPRO'!$C$7:$AI$58,20,FALSE),0) -> 0 | W37: =IFERROR(VLOOKUP(C37,'COPY DATA XPRO'!$C$7:$AI$58,21,FALSE),0) -> 0 | X37: =IFERROR(VLOOKUP(C37,'COPY DATA XPRO'!$C$7:$AI$58,22,FALSE),0) -> 0 | Y37: =IFERROR(VLOOKUP(C37,'COPY DATA XPRO'!$C$7:$AI$58,23,FALSE),0) -> 0 | Z37: =IFERROR(VLOOKUP(C37,'COPY DATA XPRO'!$C$7:$AI$58,24,FALSE),0) -> 1 | AA37: =IFERROR(VLOOKUP(C37,'COPY DATA XPRO'!$C$7:$AI$58,25,FALSE),0) -> 0 | AB37: =IFERROR(VLOOKUP(C37,'COPY DATA XPRO'!$C$7:$AI$58,26,FALSE),0) -> 0 | AC37: =IFERROR(VLOOKUP(C37,'COPY DATA XPRO'!$C$7:$AI$58,27,FALSE),0) -> 0 | AD37: =IFERROR(VLOOKUP(C37,'COPY DATA XPRO'!$C$7:$AI$58,28,FALSE),0) -> 0 | AE37: =IFERROR(VLOOKUP(C37,'COPY DATA XPRO'!$C$7:$AI$58,29,FALSE),0) -> 0 | AF37: =IFERROR(VLOOKUP(C37,'COPY DATA XPRO'!$C$7:$AI$58,30,FALSE),0) -> 0 | AG37: =IFERROR(VLOOKUP(C37,'COPY DATA XPRO'!$C$7:$AI$58,31,FALSE),0) -> 50 | AH37: =IFERROR(VLOOKUP(C37,'COPY DATA XPRO'!$C$7:$AI$58,32,FALSE),0) -> 50 | AI37: =IFERROR(VLOOKUP(C37,'COPY DATA XPRO'!$C$7:$AI$58,33,FALSE),0) -> 100
C38: BIMA | D38: =IFERROR(VLOOKUP(C38,'COPY DATA XPRO'!$C$7:$AI$58,2,FALSE),0) -> 0 | E38: =IFERROR(VLOOKUP(C38,'COPY DATA XPRO'!$C$7:$AI$58,3,FALSE),0) -> 18 | F38: =IFERROR(VLOOKUP(C38,'COPY DATA XPRO'!$C$7:$AI$58,4,FALSE),0) -> 0 | G38: =IFERROR(VLOOKUP(C38,'COPY DATA XPRO'!$C$7:$AI$58,5,FALSE),0) -> 0 | H38: =IFERROR(VLOOKUP(C38,'COPY DATA XPRO'!$C$7:$AI$58,6,FALSE),0) -> 0 | I38: =IFERROR(VLOOKUP(C38,'COPY DATA XPRO'!$C$7:$AI$58,7,FALSE),0) -> 0 | J38: =IFERROR(VLOOKUP(C38,'COPY DATA XPRO'!$C$7:$AI$58,8,FALSE),0) -> 0 | K38: =IFERROR(VLOOKUP(C38,'COPY DATA XPRO'!$C$7:$AI$58,9,FALSE),0) -> 0 | L38: =IFERROR(VLOOKUP(C38,'COPY DATA XPRO'!$C$7:$AI$58,10,FALSE),0) -> 1 | M38: =IFERROR(VLOOKUP(C38,'COPY DATA XPRO'!$C$7:$AI$58,11,FALSE),0) -> 0 | N38: =IFERROR(VLOOKUP(C38,'COPY DATA XPRO'!$C$7:$AI$58,12,FALSE),0) -> 0 | O38: =IFERROR(VLOOKUP(C38,'COPY DATA XPRO'!$C$7:$AI$58,13,FALSE),0) -> 1 | P38: =IFERROR(VLOOKUP(C38,'COPY DATA XPRO'!$C$7:$AI$58,14,FALSE),0) -> 1 | Q38: =IFERROR(VLOOKUP(C38,'COPY DATA XPRO'!$C$7:$AI$58,15,FALSE),0) -> 0 | R38: =IFERROR(VLOOKUP(C38,'COPY DATA XPRO'!$C$7:$AI$58,16,FALSE),0) -> 0 | S38: =IFERROR(VLOOKUP(C38,'COPY DATA XPRO'!$C$7:$AI$58,17,FALSE),0) -> 0 | T38: =IFERROR(VLOOKUP(C38,'COPY DATA XPRO'!$C$7:$AI$58,18,FALSE),0) -> 0 | U38: =IFERROR(VLOOKUP(C38,'COPY DATA XPRO'!$C$7:$AI$58,19,FALSE),0) -> 1 | V38: =IFERROR(VLOOKUP(C38,'COPY DATA XPRO'!$C$7:$AI$58,20,FALSE),0) -> 0 | W38: =IFERROR(VLOOKUP(C38,'COPY DATA XPRO'!$C$7:$AI$58,21,FALSE),0) -> 0 | X38: =IFERROR(VLOOKUP(C38,'COPY DATA XPRO'!$C$7:$AI$58,22,FALSE),0) -> 1 | Y38: =IFERROR(VLOOKUP(C38,'COPY DATA XPRO'!$C$7:$AI$58,23,FALSE),0) -> 1 | Z38: =IFERROR(VLOOKUP(C38,'COPY DATA XPRO'!$C$7:$AI$58,24,FALSE),0) -> 9 | AA38: =IFERROR(VLOOKUP(C38,'COPY DATA XPRO'!$C$7:$AI$58,25,FALSE),0) -> 0 | AB38: =IFERROR(VLOOKUP(C38,'COPY DATA XPRO'!$C$7:$AI$58,26,FALSE),0) -> 0 | AC38: =IFERROR(VLOOKUP(C38,'COPY DATA XPRO'!$C$7:$AI$58,27,FALSE),0) -> 0 | AD38: =IFERROR(VLOOKUP(C38,'COPY DATA XPRO'!$C$7:$AI$58,28,FALSE),0) -> 0 | AE38: =IFERROR(VLOOKUP(C38,'COPY DATA XPRO'!$C$7:$AI$58,29,FALSE),0) -> 0 | AF38: =IFERROR(VLOOKUP(C38,'COPY DATA XPRO'!$C$7:$AI$58,30,FALSE),0) -> 5 | AG38: =IFERROR(VLOOKUP(C38,'COPY DATA XPRO'!$C$7:$AI$58,31,FALSE),0) -> 66.67 | AH38: =IFERROR(VLOOKUP(C38,'COPY DATA XPRO'!$C$7:$AI$58,32,FALSE),0) -> 69.23 | AI38: =IFERROR(VLOOKUP(C38,'COPY DATA XPRO'!$C$7:$AI$58,33,FALSE),0) -> 75
C39: ENDE | D39: =IFERROR(VLOOKUP(C39,'COPY DATA XPRO'!$C$7:$AI$58,2,FALSE),0) -> 0 | E39: =IFERROR(VLOOKUP(C39,'COPY DATA XPRO'!$C$7:$AI$58,3,FALSE),0) -> 14 | F39: =IFERROR(VLOOKUP(C39,'COPY DATA XPRO'!$C$7:$AI$58,4,FALSE),0) -> 0 | G39: =IFERROR(VLOOKUP(C39,'COPY DATA XPRO'!$C$7:$AI$58,5,FALSE),0) -> 0 | H39: =IFERROR(VLOOKUP(C39,'COPY DATA XPRO'!$C$7:$AI$58,6,FALSE),0) -> 0 | I39: =IFERROR(VLOOKUP(C39,'COPY DATA XPRO'!$C$7:$AI$58,7,FALSE),0) -> 0 | J39: =IFERROR(VLOOKUP(C39,'COPY DATA XPRO'!$C$7:$AI$58,8,FALSE),0) -> 0 | K39: =IFERROR(VLOOKUP(C39,'COPY DATA XPRO'!$C$7:$AI$58,9,FALSE),0) -> 0 | L39: =IFERROR(VLOOKUP(C39,'COPY DATA XPRO'!$C$7:$AI$58,10,FALSE),0) -> 0 | M39: =IFERROR(VLOOKUP(C39,'COPY DATA XPRO'!$C$7:$AI$58,11,FALSE),0) -> 0 | N39: =IFERROR(VLOOKUP(C39,'COPY DATA XPRO'!$C$7:$AI$58,12,FALSE),0) -> 1 | O39: =IFERROR(VLOOKUP(C39,'COPY DATA XPRO'!$C$7:$AI$58,13,FALSE),0) -> 1 | P39: =IFERROR(VLOOKUP(C39,'COPY DATA XPRO'!$C$7:$AI$58,14,FALSE),0) -> 2 | Q39: =IFERROR(VLOOKUP(C39,'COPY DATA XPRO'!$C$7:$AI$58,15,FALSE),0) -> 0 | R39: =IFERROR(VLOOKUP(C39,'COPY DATA XPRO'!$C$7:$AI$58,16,FALSE),0) -> 0 | S39: =IFERROR(VLOOKUP(C39,'COPY DATA XPRO'!$C$7:$AI$58,17,FALSE),0) -> 0 | T39: =IFERROR(VLOOKUP(C39,'COPY DATA XPRO'!$C$7:$AI$58,18,FALSE),0) -> 0 | U39: =IFERROR(VLOOKUP(C39,'COPY DATA XPRO'!$C$7:$AI$58,19,FALSE),0) -> 0 | V39: =IFERROR(VLOOKUP(C39,'COPY DATA XPRO'!$C$7:$AI$58,20,FALSE),0) -> 0 | W39: =IFERROR(VLOOKUP(C39,'COPY DATA XPRO'!$C$7:$AI$58,21,FALSE),0) -> 0 | X39: =IFERROR(VLOOKUP(C39,'COPY DATA XPRO'!$C$7:$AI$58,22,FALSE),0) -> 0 | Y39: =IFERROR(VLOOKUP(C39,'COPY DATA XPRO'!$C$7:$AI$58,23,FALSE),0) -> 0 | Z39: =IFERROR(VLOOKUP(C39,'COPY DATA XPRO'!$C$7:$AI$58,24,FALSE),0) -> 12 | AA39: =IFERROR(VLOOKUP(C39,'COPY DATA XPRO'!$C$7:$AI$58,25,FALSE),0) -> 0 | AB39: =IFERROR(VLOOKUP(C39,'COPY DATA XPRO'!$C$7:$AI$58,26,FALSE),0) -> 0 | AC39: =IFERROR(VLOOKUP(C39,'COPY DATA XPRO'!$C$7:$AI$58,27,FALSE),0) -> 0 | AD39: =IFERROR(VLOOKUP(C39,'COPY DATA XPRO'!$C$7:$AI$58,28,FALSE),0) -> 0 | AE39: =IFERROR(VLOOKUP(C39,'COPY DATA XPRO'!$C$7:$AI$58,29,FALSE),0) -> 0 | AF39: =IFERROR(VLOOKUP(C39,'COPY DATA XPRO'!$C$7:$AI$58,30,FALSE),0) -> 0 | AG39: =IFERROR(VLOOKUP(C39,'COPY DATA XPRO'!$C$7:$AI$58,31,FALSE),0) -> 100 | AH39: =IFERROR(VLOOKUP(C39,'COPY DATA XPRO'!$C$7:$AI$58,32,FALSE),0) -> 85.71 | AI39: =IFERROR(VLOOKUP(C39,'COPY DATA XPRO'!$C$7:$AI$58,33,FALSE),0) -> 85.71
C40: INNER - NUSA TENGGARA | D40: =IFERROR(VLOOKUP(C40,'COPY DATA XPRO'!$C$7:$AI$58,2,FALSE),0) -> 0 | E40: =IFERROR(VLOOKUP(C40,'COPY DATA XPRO'!$C$7:$AI$58,3,FALSE),0) -> 26 | F40: =IFERROR(VLOOKUP(C40,'COPY DATA XPRO'!$C$7:$AI$58,4,FALSE),0) -> 0 | G40: =IFERROR(VLOOKUP(C40,'COPY DATA XPRO'!$C$7:$AI$58,5,FALSE),0) -> 0 | H40: =IFERROR(VLOOKUP(C40,'COPY DATA XPRO'!$C$7:$AI$58,6,FALSE),0) -> 0 | I40: =IFERROR(VLOOKUP(C40,'COPY DATA XPRO'!$C$7:$AI$58,7,FALSE),0) -> 0 | J40: =IFERROR(VLOOKUP(C40,'COPY DATA XPRO'!$C$7:$AI$58,8,FALSE),0) -> 0 | K40: =IFERROR(VLOOKUP(C40,'COPY DATA XPRO'!$C$7:$AI$58,9,FALSE),0) -> 0 | L40: =IFERROR(VLOOKUP(C40,'COPY DATA XPRO'!$C$7:$AI$58,10,FALSE),0) -> 0 | M40: =IFERROR(VLOOKUP(C40,'COPY DATA XPRO'!$C$7:$AI$58,11,FALSE),0) -> 0 | N40: =IFERROR(VLOOKUP(C40,'COPY DATA XPRO'!$C$7:$AI$58,12,FALSE),0) -> 2 | O40: =IFERROR(VLOOKUP(C40,'COPY DATA XPRO'!$C$7:$AI$58,13,FALSE),0) -> 1 | P40: =IFERROR(VLOOKUP(C40,'COPY DATA XPRO'!$C$7:$AI$58,14,FALSE),0) -> 3 | Q40: =IFERROR(VLOOKUP(C40,'COPY DATA XPRO'!$C$7:$AI$58,15,FALSE),0) -> 0 | R40: =IFERROR(VLOOKUP(C40,'COPY DATA XPRO'!$C$7:$AI$58,16,FALSE),0) -> 0 | S40: =IFERROR(VLOOKUP(C40,'COPY DATA XPRO'!$C$7:$AI$58,17,FALSE),0) -> 0 | T40: =IFERROR(VLOOKUP(C40,'COPY DATA XPRO'!$C$7:$AI$58,18,FALSE),0) -> 0 | U40: =IFERROR(VLOOKUP(C40,'COPY DATA XPRO'!$C$7:$AI$58,19,FALSE),0) -> 0 | V40: =IFERROR(VLOOKUP(C40,'COPY DATA XPRO'!$C$7:$AI$58,20,FALSE),0) -> 0 | W40: =IFERROR(VLOOKUP(C40,'COPY DATA XPRO'!$C$7:$AI$58,21,FALSE),0) -> 0 | X40: =IFERROR(VLOOKUP(C40,'COPY DATA XPRO'!$C$7:$AI$58,22,FALSE),0) -> 0 | Y40: =IFERROR(VLOOKUP(C40,'COPY DATA XPRO'!$C$7:$AI$58,23,FALSE),0) -> 0 | Z40: =IFERROR(VLOOKUP(C40,'COPY DATA XPRO'!$C$7:$AI$58,24,FALSE),0) -> 16 | AA40: =IFERROR(VLOOKUP(C40,'COPY DATA XPRO'!$C$7:$AI$58,25,FALSE),0) -> 1 | AB40: =IFERROR(VLOOKUP(C40,'COPY DATA XPRO'!$C$7:$AI$58,26,FALSE),0) -> 0 | AC40: =IFERROR(VLOOKUP(C40,'COPY DATA XPRO'!$C$7:$AI$58,27,FALSE),0) -> 0 | AD40: =IFERROR(VLOOKUP(C40,'COPY DATA XPRO'!$C$7:$AI$58,28,FALSE),0) -> 0 | AE40: =IFERROR(VLOOKUP(C40,'COPY DATA XPRO'!$C$7:$AI$58,29,FALSE),0) -> 1 | AF40: =IFERROR(VLOOKUP(C40,'COPY DATA XPRO'!$C$7:$AI$58,30,FALSE),0) -> 6 | AG40: =IFERROR(VLOOKUP(C40,'COPY DATA XPRO'!$C$7:$AI$58,31,FALSE),0) -> 76.92 | AH40: =IFERROR(VLOOKUP(C40,'COPY DATA XPRO'!$C$7:$AI$58,32,FALSE),0) -> 80 | AI40: =IFERROR(VLOOKUP(C40,'COPY DATA XPRO'!$C$7:$AI$58,33,FALSE),0) -> 84.21
C41: KUPANG | D41: =IFERROR(VLOOKUP(C41,'COPY DATA XPRO'!$C$7:$AI$58,2,FALSE),0) -> 0 | E41: =IFERROR(VLOOKUP(C41,'COPY DATA XPRO'!$C$7:$AI$58,3,FALSE),0) -> 24 | F41: =IFERROR(VLOOKUP(C41,'COPY DATA XPRO'!$C$7:$AI$58,4,FALSE),0) -> 0 | G41: =IFERROR(VLOOKUP(C41,'COPY DATA XPRO'!$C$7:$AI$58,5,FALSE),0) -> 0 | H41: =IFERROR(VLOOKUP(C41,'COPY DATA XPRO'!$C$7:$AI$58,6,FALSE),0) -> 0 | I41: =IFERROR(VLOOKUP(C41,'COPY DATA XPRO'!$C$7:$AI$58,7,FALSE),0) -> 1 | J41: =IFERROR(VLOOKUP(C41,'COPY DATA XPRO'!$C$7:$AI$58,8,FALSE),0) -> 2 | K41: =IFERROR(VLOOKUP(C41,'COPY DATA XPRO'!$C$7:$AI$58,9,FALSE),0) -> 2 | L41: =IFERROR(VLOOKUP(C41,'COPY DATA XPRO'!$C$7:$AI$58,10,FALSE),0) -> 0 | M41: =IFERROR(VLOOKUP(C41,'COPY DATA XPRO'!$C$7:$AI$58,11,FALSE),0) -> 0 | N41: =IFERROR(VLOOKUP(C41,'COPY DATA XPRO'!$C$7:$AI$58,12,FALSE),0) -> 5 | O41: =IFERROR(VLOOKUP(C41,'COPY DATA XPRO'!$C$7:$AI$58,13,FALSE),0) -> 1 | P41: =IFERROR(VLOOKUP(C41,'COPY DATA XPRO'!$C$7:$AI$58,14,FALSE),0) -> 6 | Q41: =IFERROR(VLOOKUP(C41,'COPY DATA XPRO'!$C$7:$AI$58,15,FALSE),0) -> 0 | R41: =IFERROR(VLOOKUP(C41,'COPY DATA XPRO'!$C$7:$AI$58,16,FALSE),0) -> 0 | S41: =IFERROR(VLOOKUP(C41,'COPY DATA XPRO'!$C$7:$AI$58,17,FALSE),0) -> 0 | T41: =IFERROR(VLOOKUP(C41,'COPY DATA XPRO'!$C$7:$AI$58,18,FALSE),0) -> 0 | U41: =IFERROR(VLOOKUP(C41,'COPY DATA XPRO'!$C$7:$AI$58,19,FALSE),0) -> 0 | V41: =IFERROR(VLOOKUP(C41,'COPY DATA XPRO'!$C$7:$AI$58,20,FALSE),0) -> 0 | W41: =IFERROR(VLOOKUP(C41,'COPY DATA XPRO'!$C$7:$AI$58,21,FALSE),0) -> 0 | X41: =IFERROR(VLOOKUP(C41,'COPY DATA XPRO'!$C$7:$AI$58,22,FALSE),0) -> 0 | Y41: =IFERROR(VLOOKUP(C41,'COPY DATA XPRO'!$C$7:$AI$58,23,FALSE),0) -> 1 | Z41: =IFERROR(VLOOKUP(C41,'COPY DATA XPRO'!$C$7:$AI$58,24,FALSE),0) -> 10 | AA41: =IFERROR(VLOOKUP(C41,'COPY DATA XPRO'!$C$7:$AI$58,25,FALSE),0) -> 0 | AB41: =IFERROR(VLOOKUP(C41,'COPY DATA XPRO'!$C$7:$AI$58,26,FALSE),0) -> 3 | AC41: =IFERROR(VLOOKUP(C41,'COPY DATA XPRO'!$C$7:$AI$58,27,FALSE),0) -> 0 | AD41: =IFERROR(VLOOKUP(C41,'COPY DATA XPRO'!$C$7:$AI$58,28,FALSE),0) -> 0 | AE41: =IFERROR(VLOOKUP(C41,'COPY DATA XPRO'!$C$7:$AI$58,29,FALSE),0) -> 3 | AF41: =IFERROR(VLOOKUP(C41,'COPY DATA XPRO'!$C$7:$AI$58,30,FALSE),0) -> 0 | AG41: =IFERROR(VLOOKUP(C41,'COPY DATA XPRO'!$C$7:$AI$58,31,FALSE),0) -> 83.33 | AH41: =IFERROR(VLOOKUP(C41,'COPY DATA XPRO'!$C$7:$AI$58,32,FALSE),0) -> 47.62 | AI41: =IFERROR(VLOOKUP(C41,'COPY DATA XPRO'!$C$7:$AI$58,33,FALSE),0) -> 58.82
C42: LABOAN BAJO | D42: =IFERROR(VLOOKUP(C42,'COPY DATA XPRO'!$C$7:$AI$58,2,FALSE),0) -> 0 | E42: =IFERROR(VLOOKUP(C42,'COPY DATA XPRO'!$C$7:$AI$58,3,FALSE),0) -> 9 | F42: =IFERROR(VLOOKUP(C42,'COPY DATA XPRO'!$C$7:$AI$58,4,FALSE),0) -> 0 | G42: =IFERROR(VLOOKUP(C42,'COPY DATA XPRO'!$C$7:$AI$58,5,FALSE),0) -> 0 | H42: =IFERROR(VLOOKUP(C42,'COPY DATA XPRO'!$C$7:$AI$58,6,FALSE),0) -> 0 | I42: =IFERROR(VLOOKUP(C42,'COPY DATA XPRO'!$C$7:$AI$58,7,FALSE),0) -> 0 | J42: =IFERROR(VLOOKUP(C42,'COPY DATA XPRO'!$C$7:$AI$58,8,FALSE),0) -> 0 | K42: =IFERROR(VLOOKUP(C42,'COPY DATA XPRO'!$C$7:$AI$58,9,FALSE),0) -> 2 | L42: =IFERROR(VLOOKUP(C42,'COPY DATA XPRO'!$C$7:$AI$58,10,FALSE),0) -> 0 | M42: =IFERROR(VLOOKUP(C42,'COPY DATA XPRO'!$C$7:$AI$58,11,FALSE),0) -> 0 | N42: =IFERROR(VLOOKUP(C42,'COPY DATA XPRO'!$C$7:$AI$58,12,FALSE),0) -> 1 | O42: =IFERROR(VLOOKUP(C42,'COPY DATA XPRO'!$C$7:$AI$58,13,FALSE),0) -> 0 | P42: =IFERROR(VLOOKUP(C42,'COPY DATA XPRO'!$C$7:$AI$58,14,FALSE),0) -> 1 | Q42: =IFERROR(VLOOKUP(C42,'COPY DATA XPRO'!$C$7:$AI$58,15,FALSE),0) -> 0 | R42: =IFERROR(VLOOKUP(C42,'COPY DATA XPRO'!$C$7:$AI$58,16,FALSE),0) -> 0 | S42: =IFERROR(VLOOKUP(C42,'COPY DATA XPRO'!$C$7:$AI$58,17,FALSE),0) -> 0 | T42: =IFERROR(VLOOKUP(C42,'COPY DATA XPRO'!$C$7:$AI$58,18,FALSE),0) -> 0 | U42: =IFERROR(VLOOKUP(C42,'COPY DATA XPRO'!$C$7:$AI$58,19,FALSE),0) -> 0 | V42: =IFERROR(VLOOKUP(C42,'COPY DATA XPRO'!$C$7:$AI$58,20,FALSE),0) -> 0 | W42: =IFERROR(VLOOKUP(C42,'COPY DATA XPRO'!$C$7:$AI$58,21,FALSE),0) -> 0 | X42: =IFERROR(VLOOKUP(C42,'COPY DATA XPRO'!$C$7:$AI$58,22,FALSE),0) -> 0 | Y42: =IFERROR(VLOOKUP(C42,'COPY DATA XPRO'!$C$7:$AI$58,23,FALSE),0) -> 0 | Z42: =IFERROR(VLOOKUP(C42,'COPY DATA XPRO'!$C$7:$AI$58,24,FALSE),0) -> 6 | AA42: =IFERROR(VLOOKUP(C42,'COPY DATA XPRO'!$C$7:$AI$58,25,FALSE),0) -> 0 | AB42: =IFERROR(VLOOKUP(C42,'COPY DATA XPRO'!$C$7:$AI$58,26,FALSE),0) -> 0 | AC42: =IFERROR(VLOOKUP(C42,'COPY DATA XPRO'!$C$7:$AI$58,27,FALSE),0) -> 0 | AD42: =IFERROR(VLOOKUP(C42,'COPY DATA XPRO'!$C$7:$AI$58,28,FALSE),0) -> 0 | AE42: =IFERROR(VLOOKUP(C42,'COPY DATA XPRO'!$C$7:$AI$58,29,FALSE),0) -> 0 | AF42: =IFERROR(VLOOKUP(C42,'COPY DATA XPRO'!$C$7:$AI$58,30,FALSE),0) -> 0 | AG42: =IFERROR(VLOOKUP(C42,'COPY DATA XPRO'!$C$7:$AI$58,31,FALSE),0) -> 77.78 | AH42: =IFERROR(VLOOKUP(C42,'COPY DATA XPRO'!$C$7:$AI$58,32,FALSE),0) -> 85.71 | AI42: =IFERROR(VLOOKUP(C42,'COPY DATA XPRO'!$C$7:$AI$58,33,FALSE),0) -> 85.71
C43: LOMBOK BARAT TENGAH | D43: =IFERROR(VLOOKUP(C43,'COPY DATA XPRO'!$C$7:$AI$58,2,FALSE),0) -> 0 | E43: =IFERROR(VLOOKUP(C43,'COPY DATA XPRO'!$C$7:$AI$58,3,FALSE),0) -> 32 | F43: =IFERROR(VLOOKUP(C43,'COPY DATA XPRO'!$C$7:$AI$58,4,FALSE),0) -> 1 | G43: =IFERROR(VLOOKUP(C43,'COPY DATA XPRO'!$C$7:$AI$58,5,FALSE),0) -> 0 | H43: =IFERROR(VLOOKUP(C43,'COPY DATA XPRO'!$C$7:$AI$58,6,FALSE),0) -> 0 | I43: =IFERROR(VLOOKUP(C43,'COPY DATA XPRO'!$C$7:$AI$58,7,FALSE),0) -> 1 | J43: =IFERROR(VLOOKUP(C43,'COPY DATA XPRO'!$C$7:$AI$58,8,FALSE),0) -> 2 | K43: =IFERROR(VLOOKUP(C43,'COPY DATA XPRO'!$C$7:$AI$58,9,FALSE),0) -> 1 | L43: =IFERROR(VLOOKUP(C43,'COPY DATA XPRO'!$C$7:$AI$58,10,FALSE),0) -> 0 | M43: =IFERROR(VLOOKUP(C43,'COPY DATA XPRO'!$C$7:$AI$58,11,FALSE),0) -> 0 | N43: =IFERROR(VLOOKUP(C43,'COPY DATA XPRO'!$C$7:$AI$58,12,FALSE),0) -> 0 | O43: =IFERROR(VLOOKUP(C43,'COPY DATA XPRO'!$C$7:$AI$58,13,FALSE),0) -> 2 | P43: =IFERROR(VLOOKUP(C43,'COPY DATA XPRO'!$C$7:$AI$58,14,FALSE),0) -> 2 | Q43: =IFERROR(VLOOKUP(C43,'COPY DATA XPRO'!$C$7:$AI$58,15,FALSE),0) -> 1 | R43: =IFERROR(VLOOKUP(C43,'COPY DATA XPRO'!$C$7:$AI$58,16,FALSE),0) -> 0 | S43: =IFERROR(VLOOKUP(C43,'COPY DATA XPRO'!$C$7:$AI$58,17,FALSE),0) -> 0 | T43: =IFERROR(VLOOKUP(C43,'COPY DATA XPRO'!$C$7:$AI$58,18,FALSE),0) -> 1 | U43: =IFERROR(VLOOKUP(C43,'COPY DATA XPRO'!$C$7:$AI$58,19,FALSE),0) -> 0 | V43: =IFERROR(VLOOKUP(C43,'COPY DATA XPRO'!$C$7:$AI$58,20,FALSE),0) -> 0 | W43: =IFERROR(VLOOKUP(C43,'COPY DATA XPRO'!$C$7:$AI$58,21,FALSE),0) -> 0 | X43: =IFERROR(VLOOKUP(C43,'COPY DATA XPRO'!$C$7:$AI$58,22,FALSE),0) -> 2 | Y43: =IFERROR(VLOOKUP(C43,'COPY DATA XPRO'!$C$7:$AI$58,23,FALSE),0) -> 0 | Z43: =IFERROR(VLOOKUP(C43,'COPY DATA XPRO'!$C$7:$AI$58,24,FALSE),0) -> 19 | AA43: =IFERROR(VLOOKUP(C43,'COPY DATA XPRO'!$C$7:$AI$58,25,FALSE),0) -> 0 | AB43: =IFERROR(VLOOKUP(C43,'COPY DATA XPRO'!$C$7:$AI$58,26,FALSE),0) -> 0 | AC43: =IFERROR(VLOOKUP(C43,'COPY DATA XPRO'!$C$7:$AI$58,27,FALSE),0) -> 0 | AD43: =IFERROR(VLOOKUP(C43,'COPY DATA XPRO'!$C$7:$AI$58,28,FALSE),0) -> 0 | AE43: =IFERROR(VLOOKUP(C43,'COPY DATA XPRO'!$C$7:$AI$58,29,FALSE),0) -> 0 | AF43: =IFERROR(VLOOKUP(C43,'COPY DATA XPRO'!$C$7:$AI$58,30,FALSE),0) -> 4 | AG43: =IFERROR(VLOOKUP(C43,'COPY DATA XPRO'!$C$7:$AI$58,31,FALSE),0) -> 71.88 | AH43: =IFERROR(VLOOKUP(C43,'COPY DATA XPRO'!$C$7:$AI$58,32,FALSE),0) -> 73.08 | AI43: =IFERROR(VLOOKUP(C43,'COPY DATA XPRO'!$C$7:$AI$58,33,FALSE),0) -> 82.61
C44: LOMBOK TIMUR UTARA | D44: =IFERROR(VLOOKUP(C44,'COPY DATA XPRO'!$C$7:$AI$58,2,FALSE),0) -> 0 | E44: =IFERROR(VLOOKUP(C44,'COPY DATA XPRO'!$C$7:$AI$58,3,FALSE),0) -> 32 | F44: =IFERROR(VLOOKUP(C44,'COPY DATA XPRO'!$C$7:$AI$58,4,FALSE),0) -> 1 | G44: =IFERROR(VLOOKUP(C44,'COPY DATA XPRO'!$C$7:$AI$58,5,FALSE),0) -> 0 | H44: =IFERROR(VLOOKUP(C44,'COPY DATA XPRO'!$C$7:$AI$58,6,FALSE),0) -> 0 | I44: =IFERROR(VLOOKUP(C44,'COPY DATA XPRO'!$C$7:$AI$58,7,FALSE),0) -> 1 | J44: =IFERROR(VLOOKUP(C44,'COPY DATA XPRO'!$C$7:$AI$58,8,FALSE),0) -> 2 | K44: =IFERROR(VLOOKUP(C44,'COPY DATA XPRO'!$C$7:$AI$58,9,FALSE),0) -> 0 | L44: =IFERROR(VLOOKUP(C44,'COPY DATA XPRO'!$C$7:$AI$58,10,FALSE),0) -> 0 | M44: =IFERROR(VLOOKUP(C44,'COPY DATA XPRO'!$C$7:$AI$58,11,FALSE),0) -> 0 | N44: =IFERROR(VLOOKUP(C44,'COPY DATA XPRO'!$C$7:$AI$58,12,FALSE),0) -> 1 | O44: =IFERROR(VLOOKUP(C44,'COPY DATA XPRO'!$C$7:$AI$58,13,FALSE),0) -> 0 | P44: =IFERROR(VLOOKUP(C44,'COPY DATA XPRO'!$C$7:$AI$58,14,FALSE),0) -> 1 | Q44: =IFERROR(VLOOKUP(C44,'COPY DATA XPRO'!$C$7:$AI$58,15,FALSE),0) -> 0 | R44: =IFERROR(VLOOKUP(C44,'COPY DATA XPRO'!$C$7:$AI$58,16,FALSE),0) -> 0 | S44: =IFERROR(VLOOKUP(C44,'COPY DATA XPRO'!$C$7:$AI$58,17,FALSE),0) -> 0 | T44: =IFERROR(VLOOKUP(C44,'COPY DATA XPRO'!$C$7:$AI$58,18,FALSE),0) -> 0 | U44: =IFERROR(VLOOKUP(C44,'COPY DATA XPRO'!$C$7:$AI$58,19,FALSE),0) -> 1 | V44: =IFERROR(VLOOKUP(C44,'COPY DATA XPRO'!$C$7:$AI$58,20,FALSE),0) -> 0 | W44: =IFERROR(VLOOKUP(C44,'COPY DATA XPRO'!$C$7:$AI$58,21,FALSE),0) -> 0 | X44: =IFERROR(VLOOKUP(C44,'COPY DATA XPRO'!$C$7:$AI$58,22,FALSE),0) -> 1 | Y44: =IFERROR(VLOOKUP(C44,'COPY DATA XPRO'!$C$7:$AI$58,23,FALSE),0) -> 1 | Z44: =IFERROR(VLOOKUP(C44,'COPY DATA XPRO'!$C$7:$AI$58,24,FALSE),0) -> 19 | AA44: =IFERROR(VLOOKUP(C44,'COPY DATA XPRO'!$C$7:$AI$58,25,FALSE),0) -> 0 | AB44: =IFERROR(VLOOKUP(C44,'COPY DATA XPRO'!$C$7:$AI$58,26,FALSE),0) -> 0 | AC44: =IFERROR(VLOOKUP(C44,'COPY DATA XPRO'!$C$7:$AI$58,27,FALSE),0) -> 0 | AD44: =IFERROR(VLOOKUP(C44,'COPY DATA XPRO'!$C$7:$AI$58,28,FALSE),0) -> 0 | AE44: =IFERROR(VLOOKUP(C44,'COPY DATA XPRO'!$C$7:$AI$58,29,FALSE),0) -> 0 | AF44: =IFERROR(VLOOKUP(C44,'COPY DATA XPRO'!$C$7:$AI$58,30,FALSE),0) -> 6 | AG44: =IFERROR(VLOOKUP(C44,'COPY DATA XPRO'!$C$7:$AI$58,31,FALSE),0) -> 68.75 | AH44: =IFERROR(VLOOKUP(C44,'COPY DATA XPRO'!$C$7:$AI$58,32,FALSE),0) -> 76 | AI44: =IFERROR(VLOOKUP(C44,'COPY DATA XPRO'!$C$7:$AI$58,33,FALSE),0) -> 86.36
C45: MAUMERE | D45: =IFERROR(VLOOKUP(C45,'COPY DATA XPRO'!$C$7:$AI$58,2,FALSE),0) -> 0 | E45: =IFERROR(VLOOKUP(C45,'COPY DATA XPRO'!$C$7:$AI$58,3,FALSE),0) -> 8 | F45: =IFERROR(VLOOKUP(C45,'COPY DATA XPRO'!$C$7:$AI$58,4,FALSE),0) -> 0 | G45: =IFERROR(VLOOKUP(C45,'COPY DATA XPRO'!$C$7:$AI$58,5,FALSE),0) -> 0 | H45: =IFERROR(VLOOKUP(C45,'COPY DATA XPRO'!$C$7:$AI$58,6,FALSE),0) -> 0 | I45: =IFERROR(VLOOKUP(C45,'COPY DATA XPRO'!$C$7:$AI$58,7,FALSE),0) -> 0 | J45: =IFERROR(VLOOKUP(C45,'COPY DATA XPRO'!$C$7:$AI$58,8,FALSE),0) -> 0 | K45: =IFERROR(VLOOKUP(C45,'COPY DATA XPRO'!$C$7:$AI$58,9,FALSE),0) -> 0 | L45: =IFERROR(VLOOKUP(C45,'COPY DATA XPRO'!$C$7:$AI$58,10,FALSE),0) -> 0 | M45: =IFERROR(VLOOKUP(C45,'COPY DATA XPRO'!$C$7:$AI$58,11,FALSE),0) -> 0 | N45: =IFERROR(VLOOKUP(C45,'COPY DATA XPRO'!$C$7:$AI$58,12,FALSE),0) -> 1 | O45: =IFERROR(VLOOKUP(C45,'COPY DATA XPRO'!$C$7:$AI$58,13,FALSE),0) -> 1 | P45: =IFERROR(VLOOKUP(C45,'COPY DATA XPRO'!$C$7:$AI$58,14,FALSE),0) -> 2 | Q45: =IFERROR(VLOOKUP(C45,'COPY DATA XPRO'!$C$7:$AI$58,15,FALSE),0) -> 0 | R45: =IFERROR(VLOOKUP(C45,'COPY DATA XPRO'!$C$7:$AI$58,16,FALSE),0) -> 0 | S45: =IFERROR(VLOOKUP(C45,'COPY DATA XPRO'!$C$7:$AI$58,17,FALSE),0) -> 0 | T45: =IFERROR(VLOOKUP(C45,'COPY DATA XPRO'!$C$7:$AI$58,18,FALSE),0) -> 0 | U45: =IFERROR(VLOOKUP(C45,'COPY DATA XPRO'!$C$7:$AI$58,19,FALSE),0) -> 0 | V45: =IFERROR(VLOOKUP(C45,'COPY DATA XPRO'!$C$7:$AI$58,20,FALSE),0) -> 0 | W45: =IFERROR(VLOOKUP(C45,'COPY DATA XPRO'!$C$7:$AI$58,21,FALSE),0) -> 0 | X45: =IFERROR(VLOOKUP(C45,'COPY DATA XPRO'!$C$7:$AI$58,22,FALSE),0) -> 0 | Y45: =IFERROR(VLOOKUP(C45,'COPY DATA XPRO'!$C$7:$AI$58,23,FALSE),0) -> 2 | Z45: =IFERROR(VLOOKUP(C45,'COPY DATA XPRO'!$C$7:$AI$58,24,FALSE),0) -> 4 | AA45: =IFERROR(VLOOKUP(C45,'COPY DATA XPRO'!$C$7:$AI$58,25,FALSE),0) -> 0 | AB45: =IFERROR(VLOOKUP(C45,'COPY DATA XPRO'!$C$7:$AI$58,26,FALSE),0) -> 0 | AC45: =IFERROR(VLOOKUP(C45,'COPY DATA XPRO'!$C$7:$AI$58,27,FALSE),0) -> 0 | AD45: =IFERROR(VLOOKUP(C45,'COPY DATA XPRO'!$C$7:$AI$58,28,FALSE),0) -> 0 | AE45: =IFERROR(VLOOKUP(C45,'COPY DATA XPRO'!$C$7:$AI$58,29,FALSE),0) -> 0 | AF45: =IFERROR(VLOOKUP(C45,'COPY DATA XPRO'!$C$7:$AI$58,30,FALSE),0) -> 0 | AG45: =IFERROR(VLOOKUP(C45,'COPY DATA XPRO'!$C$7:$AI$58,31,FALSE),0) -> 100 | AH45: =IFERROR(VLOOKUP(C45,'COPY DATA XPRO'!$C$7:$AI$58,32,FALSE),0) -> 50 | AI45: =IFERROR(VLOOKUP(C45,'COPY DATA XPRO'!$C$7:$AI$58,33,FALSE),0) -> 50
